Workbook

Sheet 00_Инструкция
A1: Как читать доказательный реестр
A4: Цель | B4: Показать: 1) соответствие Программы развития требованиям государственных органов; 2) обеспечение требований Планом мероприятий; 3) согласованность Программы и Плана; 4) исполнение KPI за 2025 год.
A5: 01_Требования_госорганов | B5: Полный реестр внешних требований, показателей, нормативных требований и поручений. Значения по годам переносятся только из внешнего документа.
A6: 02_Программа_развития | B6: Все 65 KPI университета, включая собственные цели, не связанные напрямую с внешними требованиями. Здесь же показано обеспечение Планом. Подробный анализ исполнения за 2025 год вынесен в отдельный лист «05_Отчёт_2025».
A7: 03_План_мероприятий | B7: Полный перечень мероприятий Программы развития: срок, форма завершения, плановые значения и ответственный. Отдельной графы финансирования в утверждённом Плане нет; источник и объём средств запрашиваются дополнительно.
A8: 04_Анализ_соответствия | B8: Сквозной анализ по каждой записи: требование госоргана — KPI Программы — мероприятие Плана — значения 2023–2029 — сравнение плана и факта за 2025 год — положение факта относительно целей 2026–2029 — пробел — управленческое действие. Факт 2025 не изменяет утверждённые будущие значения без отдельного решения.
A9: Подтверждённая связь | B9: Связь считается установленной только при наличии проверяемого ID требования, KPI Программы и кода мероприятия. Сходство формулировок без документальной связи не считается соответствием.
A10: Формальная цепочка | B10: Дашборд разделяет внешние требования, собственные KPI университета, обеспеченность мероприятиями и факт за 2025 год. График по годам показывает наличие установленных значений, но не подменяет проверку сопоставимости единиц и содержания показателей.
A11: Пустые годовые ячейки | B11: Не означают ноль. Они означают, что значение в документе не установлено, год не относится к периоду либо запись не является числовым показателем. Причина раскрывается в статусе и аналитическом комментарии.
A12: Факт 2025 | B12: Переносится только при совпадении объекта, единицы, периода и формулы. Расчётные факты отдельно помечены. Если сопоставимость не подтверждена, KPI не считается выполненным или невыполненным.
A13: Национальные показатели | B13: Не являются KPI университета без утверждённой декомпозиции и индивидуального значения Abai University.
A14: Собственные цели | B14: Если связь с внешним требованием не установлена, KPI не удаляется: он отражается как собственная цель университета либо как связь, требующая дополнительного подтверждения.
A15: Цвет | B15: Подтверждено / достигнуто | C15: Частично / требуется проверка | D15: Установлен пробел / не достигнуто | E15: Оценка невозможна
A16: Источники | B16: Лист содержит один документ в одной строке. Для источников, охватывающих несколько направлений, отдельно указаны тип охвата и полный перечень направлений. Основное направление не назначается, если оно не определено документом.
A18: Навигация по мероприятиям: в листе «04_Анализ_соответствия» нажмите «Открыть: N» в столбце AZ. Откроется лист «08_Навигация_мероприятий», где каждое мероприятие имеет отдельную ссылку на соответствующую строку Плана.
A31: Итоговая инструкция к доказательному реестру
A32: Рекомендуемый порядок чтения | C32: 1) 07_Дашборд — общие факты и пробелы; 2) 04_Анализ_соответствия — сквозная цепочка; 3) 09_Пояснения_KPI — пояснение каждого KPI; 4) 10_Внешние_без_связи — внешние записи без подтверждённой связи; 5) 11_Контроль_мероприятий — годовые результаты и запросы; 6) 05_Отчёт_2025 — исторический факт; 7) 06_Источники.
A33: Зелёная строка | C33: Подтверждённый положительный результат или подтверждённая полнота плановых данных. На листе контроля мероприятий зелёный цвет не означает исполнение мероприятия.
A34: Жёлтая строка | C34: Связь или данные частичны; требуется декомпозиция, проверка применимости либо подтверждение сопоставимости.
A35: Красная строка | C35: Установлен конкретный пробел: KPI не достигнут, связанное мероприятие не найдено либо прямое/совместное внешнее требование не отражено в Программе.
A36: Серая строка | C36: Оценка невозможна по представленным документам: например, отсутствует числовой факт или запись является аналитическим ориентиром.
A37: Переход к KPI | C37: Это активная ссылка. Нажатие открывает строку соответствующего KPI на листе 09_Пояснения_KPI; значение KPI не изменяется.
A38: Как читать «без связи» | C38: Фраза означает: в представленных документах не найден KPI Программы, который можно документально связать с внешним требованием. Она не означает автоматического невыполнения.
A39: Факт 2025 | C39: Отделён от плановых значений и используется как исторический факт. Если единица, определение или методика не совпадают, результат помечается как требующий проверки, а не как достигнутый/не достигнутый.
A40: Запрет на вывод без доказательства | C40: Пустое значение не заменяется предположением. В реестре используется формулировка «не найдено/не подтверждено в представленных документах».

Sheet 01_Требования_госорганов
A1: Реестр требований государственных органов и внешних ориентиров
A2: № | B2: ID требования | C2: Направление | D2: Тип записи | E2: Требование / показатель / поручение | F2: Документ | G2: Источник ID | H2: Точное место | I2: Цитата-якорь | J2: Уровень | K2: Обязательность | L2: Применимость к Abai | M2: Вклад Abai / декомпозиция | N2: Единица | O2: 2023 | P2: 2024 | Q2: 2025 | R2: 2026 | S2: 2027 | T2: 2028 | U2: 2029 | V2: 2030 | W2: Статус проверки
A3: 1 | B3: K002 | C3: Образование | D3: Показатель | E3: Количество казахстанских вузов в топ-700 рейтинга QS World University Rankings | F3: Ключевые прказатели МНВО.docx | G3: D04 | H3: Таблица 1, показатель №1 («Количество казахстанских вузов в топ-700 рейтинга QS World University Rankings»); значения 2024–2030 | I3: Количество казахстанских вузов в топ-700 рейтинга QS World University Rankings | J3: Национальный | K3: Национальный/отраслевой показатель | L3: Требуется декомпозиция | M3: Указать после подтверждения индивидуального значения | N3: ед. | P3: 6 | Q3: 7 | R3: 8 | S3: 9 | T3: 10 | U3: 11 | V3: 12 | W3: Сверено с таблицей первоисточника
A4: 2 | B4: K004 | C4: Образование | D4: Показатель | E4: Количество казахстанских вузов, вошедших в рейтинг QS WUR | F4: Ключевые прказатели МНВО.docx | G4: D04 | H4: Таблица 1, показатель №3 («Количество казахстанских вузов, вошедших в рейтинг QS WUR»); значения 2024–2030 | I4: Количество казахстанских вузов, вошедших в рейтинг QS WUR | J4: Национальный | K4: Национальный/отраслевой показатель | L4: Требуется декомпозиция | M4: Указать после подтверждения индивидуального значения | N4: ед. | P4: 21 | Q4: 22 | R4: 23 | S4: 24 | T4: 25 | U4: 26 | V4: 27 | W4: Сверено с таблицей первоисточника
A5: 3 | B5: K005 | C5: Образование | D5: Показатель | E5: Доля обновленных образовательных программ вузов с учетом профессиональных стандартов | F5: Ключевые прказатели МНВО.docx | G5: D04 | H5: Таблица 1, показатель №4 («Доля обновленных образовательных программ вузов с учетом профессиональных стандартов»); значения 2024–2030 | I5: Доля обновленных образовательных программ вузов с учетом профессиональных стандартов | J5: Национальный | K5: Национальный/отраслевой показатель | L5: Требуется декомпозиция | M5: Указать после подтверждения индивидуального значения | N5: % | P5: 75.8 | Q5: 77 | R5: 80 | S5: 85 | T5: 90 | U5: 95 | V5: 97 | W5: Сверено с таблицей первоисточника
A6: 4 | B6: K006 | C6: Образование | D6: Показатель | E6: Доля организаций высшего и послевузовского образования, создавших условия для инклюзивного образования | F6: Ключевые прказатели МНВО.docx | G6: D04 | H6: Таблица 1, показатель №5 («Доля организаций высшего и послевузовского образования, создавших условия для инклюзивного»); значения 2024–2030 | I6: Доля организаций высшего и послевузовского образования, создавших условия для инклюзивного образования | J6: Национальный | K6: Национальный/отраслевой показатель | L6: Требуется декомпозиция | M6: Указать после подтверждения индивидуального значения | N6: % | P6: 70 | Q6: 80 | R6: 100 | S6: 100 | T6: 100 | U6: 100 | V6: 100 | W6: Сверено с таблицей первоисточника
A7: 5 | B7: K007 | C7: Образование | D7: Показатель | E7: Доля обучающихся, вовлеченных в организованную общественную деятельность, в том числе через студенческое самоуправление и дебатное движение с целью повышения уровня гражданственности и патриотизма | F7: Ключевые прказатели МНВО.docx | G7: D04 | H7: Таблица 1, показатель №6 («Доля обучающихся, вовлеченных в организованную общественную деятельность, в том числе чере»); значения 2024–2030 | I7: Доля обучающихся, вовлеченных в организованную общественную деятельность, в том числе через студенческое самоуправление и дебатное движение с целью повышения уровня гражданственности и патриотизма | J7: Национальный | K7: Национальный/отраслевой показатель | L7: Требуется декомпозиция | M7: Указать после подтверждения индивидуального значения | N7: % | P7: 40 | Q7: 45 | R7: 50 | S7: 55 | T7: 60 | U7: 65 | V7: 70 | W7: Сверено с таблицей первоисточника
A8: 6 | B8: K008 | C8: Образование | D8: Показатель | E8: Доля отрабатывающих выпускников в первый год после окончания ОВПО | F8: Ключевые прказатели МНВО.docx | G8: D04 | H8: Таблица 1, показатель №7 («Доля отрабатывающих выпускников в первый год после окончания ОВПО»); значения 2024–2030 | I8: Доля отрабатывающих выпускников в первый год после окончания ОВПО | J8: Национальный | K8: Национальный/отраслевой показатель | L8: Требуется декомпозиция | M8: Указать после подтверждения индивидуального значения | N8: % | P8: 40 | Q8: 41 | R8: 42 | S8: 43 | T8: 44 | U8: 45 | V8: 46 | W8: Сверено с таблицей первоисточника
A9: 7 | B9: K009 | C9: Образование | D9: Показатель | E9: Количество введенных койко-мест общежитий | F9: Ключевые прказатели МНВО.docx | G9: D04 | H9: Таблица 1, показатель №8 («Количество введенных койко-мест общежитий»); значения 2024–2030 | I9: Количество введенных койко-мест общежитий | J9: Национальный | K9: Национальный/отраслевой показатель | L9: Требуется декомпозиция | M9: Указать после подтверждения индивидуального значения | N9: место | P9: 11079 | Q9: 10000 | R9: 10000 | S9: 10000 | T9: 10000 | U9: 10000 | V9: 10000 | W9: Сверено с таблицей первоисточника
A10: 8 | B10: K011 | C10: Образование | D10: Показатель | E10: Доля вузов, охваченных специальными предметами, курсами в сфере интеллектуальной собственности | F10: Ключевые прказатели МНВО.docx | G10: D04 | H10: Таблица 1, показатель №10 («Доля вузов, охваченных специальными предметами, курсами в сфере интеллектуальной собственн»); значения 2024–2030 | I10: Доля вузов, охваченных специальными предметами, курсами в сфере интеллектуальной собственности | J10: Национальный | K10: Национальный/отраслевой показатель | L10: Требуется декомпозиция | M10: Указать после подтверждения индивидуального значения | N10: % | P10: ‒ | Q10: 3 | R10: 6 | S10: 7 | T10: 8 | U10: 9 | V10: 10 | W10: Сверено с таблицей первоисточника
A11: 9 | B11: K096 | C11: Образование | D11: Показатель | E11: Актуализированные НПА в сфере педагогического образования | F11: 0707_План действий -рус.docx | G11: D02 | H11: Целевой индикатор 1; строка определяется по формулировке «Актуализированные НПА в сфере педагогического образования» | I11: Актуализированные НПА в сфере педагогического образования | J11: Национальный | K11: Требование/мероприятие применимо к ОВПО | L11: Прямая или совместная | N11: % | S11: 40 | T11: 100 | U11: 100 | V11: 100 | W11: Сверено с первоисточником: формулировка реестра не подтверждена дословно; требуется уточнение
A12: 10 | B12: K097 | C12: Образование | D12: Показатель | E12: Образовательные программы на основе школоцентричной и практикоориентированной модели | F12: 0707_План действий -рус.docx | G12: D02 | H12: Целевой индикатор 2; строка определяется по формулировке «Образовательные программы на основе школоцентричной и практикоориентированной модели» | I12: Образовательные программы на основе школоцентричной и практикоориентированной модели | J12: Национальный | K12: Требование/мероприятие применимо к ОВПО | L12: Прямая или совместная | N12: % | S12: 20 | T12: 50 | U12: 80 | V12: 100 | W12: Сверено с первоисточником: формулировка реестра не подтверждена дословно; требуется уточнение
A13: 11 | B13: K098 | C13: Образование | D13: Показатель | E13: Образовательные программы, интегрирующие ИИ и цифровую педагогику | F13: 0707_План действий -рус.docx | G13: D02 | H13: Целевой индикатор 3; строка определяется по формулировке «Образовательные программы, интегрирующие ИИ и цифровую педагогику» | I13: Образовательные программы, интегрирующие ИИ и цифровую педагогику | J13: Национальный | K13: Требование/мероприятие применимо к ОВПО | L13: Прямая или совместная | N13: % | S13: 20 | T13: 50 | U13: 80 | V13: 100 | W13: Сверено с первоисточником: формулировка реестра не подтверждена дословно; требуется уточнение
A14: 12 | B14: K099 | C14: Образование | D14: Показатель | E14: Педагогические вузы, применяющие Learning Analytics и ИИ | F14: 0707_План действий -рус.docx | G14: D02 | H14: Целевой индикатор 4; строка определяется по формулировке «Педагогические вузы, применяющие Learning Analytics и ИИ» | I14: Педагогические вузы, применяющие Learning Analytics и ИИ | J14: Национальный | K14: Требование/мероприятие применимо к ОВПО | L14: Прямая или совместная | N14: % | S14: 20 | T14: 40 | U14: 70 | V14: 100 | W14: Сверено с первоисточником: формулировка реестра не подтверждена дословно; требуется уточнение
A15: 13 | B15: K100 | C15: Образование | D15: Показатель | E15: Педагогические вузы с международными программами, мобильностью и совместными проектами | F15: 0707_План действий -рус.docx | G15: D02 | H15: Целевой индикатор 5; строка определяется по формулировке «Педагогические вузы с международными программами, мобильностью и совместными проектами» | I15: Педагогические вузы с международными программами, мобильностью и совместными проектами | J15: Национальный | K15: Требование/мероприятие применимо к ОВПО | L15: Прямая или совместная | N15: % | S15: 40 | T15: 50 | U15: 60 | V15: 70 | W15: Сверено с первоисточником: формулировка реестра не подтверждена дословно; требуется уточнение
A16: 14 | B16: K102 | C16: Образование | D16: Показатель | E16: ППС педагогических вузов, прошедший повышение квалификации и стажировки | F16: 0707_План действий -рус.docx | G16: D02 | H16: Целевой индикатор 7; строка определяется по формулировке «ППС педагогических вузов, прошедший повышение квалификации и стажировки» | I16: ППС педагогических вузов, прошедший повышение квалификации и стажировки | J16: Национальный | K16: Требование/мероприятие применимо к ОВПО | L16: Прямая или совместная | N16: % | S16: 40 | T16: 55 | U16: 70 | V16: 80 | W16: Сверено с первоисточником: формулировка реестра не подтверждена дословно; требуется уточнение
A17: 15 | B17: K105 | C17: Образование | D17: Показатель | E17: Вузы РК в ТОП-700 QS WUR | F17: прил 1 рус.pdf | G17: D07 | H17: Таблица «Направления, цели, целевые индикаторы…», строка 1, стр. 2 | I17: Вузы РК в ТОП-700 QS WUR | J17: Национальный | K17: Национальный/отраслевой показатель | L17: Требуется декомпозиция | M17: Указать после подтверждения индивидуального значения | N17: ед. | R17: 8 | S17: 9 | W17: Сверено с первоисточником; формулировка сокращена без изменения содержания
A18: 16 | B18: K106 | C18: Образование | D18: Показатель | E18: Казахстанские вузы в рейтинге QS WUR | F18: прил 1 рус.pdf | G18: D07 | H18: Таблица «Направления, цели, целевые индикаторы…», строка 2, стр. 2 | I18: Казахстанские вузы в рейтинге QS WUR | J18: Национальный | K18: Национальный/отраслевой показатель | L18: Требуется декомпозиция | M18: Указать после подтверждения индивидуального значения | N18: ед. | R18: 23 | S18: 24 | W18: Сверено с первоисточником; формулировка сокращена без изменения содержания
A19: 17 | B19: K108 | C19: Образование | D19: Показатель | E19: Доля двудипломных образовательных программ | F19: прил 1 рус.pdf | G19: D07 | H19: Таблица «Направления, цели, целевые индикаторы…», строка 6, стр. 2 | I19: Доля двудипломных образовательных программ | J19: Национальный | K19: Национальный/отраслевой показатель | L19: Требуется декомпозиция | M19: Указать после подтверждения индивидуального значения | N19: % | R19: 55 | S19: 60 | W19: Сверено с первоисточником; формулировка сокращена без изменения содержания
A20: 18 | B20: K117 | C20: Образование | D20: Показатель | E20: Вузы, внедрившие курс по интеллектуальной собственности | F20: прил 1 рус.pdf | G20: D07 | H20: Таблица «Направления, цели, целевые индикаторы…», строка 21, стр. 4 | I20: Вузы, внедрившие курс по интеллектуальной собственности | J20: Национальный | K20: Национальный/отраслевой показатель | L20: Требуется декомпозиция | M20: Указать после подтверждения индивидуального значения | N20: ед. | R20: 6 | S20: 7 | W20: Сверено с первоисточником; формулировка сокращена без изменения содержания
A21: 19 | B21: K131 | C21: Образование | D21: Показатель | E21: Дефицит педагогических кадров в дошкольных организациях | F21: Комплексный план 3.06.26.docx | G21: D05 | H21: Сводные целевые показатели, позиция 1; строка определяется по формулировке «Дефицит педагогических кадров в дошкольных организациях» | I21: Дефицит педагогических кадров в дошкольных организациях | J21: Национальный/секторный | K21: Национальный/отраслевой показатель | L21: Требуется декомпозиция | M21: Указать после подтверждения индивидуального значения | N21: % | R21: 16 | S21: 15 | T21: 14 | W21: Сверено с первоисточником: формулировка реестра не подтверждена дословно; требуется уточнение
A22: 20 | B22: K132 | C22: Образование | D22: Показатель | E22: Доля молодых специалистов в дошкольных организациях | F22: Комплексный план 3.06.26.docx | G22: D05 | H22: Сводные целевые показатели, позиция 2; строка определяется по формулировке «Доля молодых специалистов в дошкольных организациях» | I22: Доля молодых специалистов в дошкольных организациях | J22: Национальный/секторный | K22: Национальный/отраслевой показатель | L22: Требуется декомпозиция | M22: Указать после подтверждения индивидуального значения | N22: % | R22: 32.3 | S22: 33.9 | T22: 35.5 | W22: Сверено с первоисточником: формулировка реестра не подтверждена дословно; требуется уточнение
A23: 21 | B23: K133 | C23: Образование | D23: Показатель | E23: Дошкольные педагоги с квалификацией | F23: Комплексный план 3.06.26.docx | G23: D05 | H23: Сводные целевые показатели, позиция 3; строка определяется по формулировке «Дошкольные педагоги с квалификацией» | I23: Дошкольные педагоги с квалификацией | J23: Национальный/секторный | K23: Национальный/отраслевой показатель | L23: Требуется декомпозиция | M23: Указать после подтверждения индивидуального значения | N23: % | R23: 44 | S23: 46 | T23: 48 | W23: Сверено с первоисточником: формулировка реестра не подтверждена дословно; требуется уточнение
A24: 22 | B24: K134 | C24: Образование | D24: Показатель | E24: Дошкольные педагоги с профильным образованием | F24: Комплексный план 3.06.26.docx | G24: D05 | H24: Сводные целевые показатели, позиция 4; строка определяется по формулировке «Дошкольные педагоги с профильным образованием» | I24: Дошкольные педагоги с профильным образованием | J24: Национальный/секторный | K24: Национальный/отраслевой показатель | L24: Требуется декомпозиция | M24: Указать после подтверждения индивидуального значения | N24: % | R24: 87 | S24: 88.2 | T24: 90 | W24: Сверено с первоисточником: формулировка реестра не подтверждена дословно; требуется уточнение
A25: 23 | B25: K135 | C25: Образование | D25: Показатель | E25: Охват дошкольных педагогов повышением квалификации | F25: Комплексный план 3.06.26.docx | G25: D05 | H25: Сводные целевые показатели, позиция 5; строка определяется по формулировке «Охват дошкольных педагогов повышением квалификации» | I25: Охват дошкольных педагогов повышением квалификации | J25: Национальный/секторный | K25: Национальный/отраслевой показатель | L25: Требуется декомпозиция | M25: Указать после подтверждения индивидуального значения | N25: % | R25: 68.9 | S25: 74.1 | T25: 79.3 | W25: Сверено с первоисточником: формулировка реестра не подтверждена дословно; требуется уточнение
A26: 24 | B26: K136 | C26: Образование | D26: Показатель | E26: Учителя начальных классов с высшим педагогическим образованием | F26: Комплексный план 3.06.26.docx | G26: D05 | H26: Сводные целевые показатели, позиция 6; строка определяется по формулировке «Учителя начальных классов с высшим педагогическим образованием» | I26: Учителя начальных классов с высшим педагогическим образованием | J26: Национальный/секторный | K26: Национальный/отраслевой показатель | L26: Требуется декомпозиция | M26: Указать после подтверждения индивидуального значения | N26: % | R26: 91 | S26: 93 | T26: 95 | W26: Сверено с первоисточником: формулировка реестра не подтверждена дословно; требуется уточнение
A27: 25 | B27: K137 | C27: Образование | D27: Показатель | E27: Охват учителей начальных классов повышением квалификации | F27: Комплексный план 3.06.26.docx | G27: D05 | H27: Сводные целевые показатели, позиция 7; строка определяется по формулировке «Охват учителей начальных классов повышением квалификации» | I27: Охват учителей начальных классов повышением квалификации | J27: Национальный/секторный | K27: Национальный/отраслевой показатель | L27: Требуется декомпозиция | M27: Указать после подтверждения индивидуального значения | N27: % | R27: 70 | S27: 80 | T27: 90 | W27: Сверено с первоисточником: формулировка реестра не подтверждена дословно; требуется уточнение
A28: 26 | B28: K145 | C28: Образование | D28: Показатель | E28: PhD на одного академического сотрудника | F28: THE анализ 2026.pdf | G28: D03 | H28: Стр. 25; строка определяется по формулировке «PhD на одного академического сотрудника» | I28: PhD на одного академического сотрудника | J28: Abai University | K28: Не является обязательным KPI | L28: Аналитический ориентир | N28: ед. | W28: Сверено с первоисточником
A29: 27 | B29: K146 | C29: Образование | D29: Показатель | E29: Соотношение студентов и преподавателей | F29: THE анализ 2026.pdf | G29: D03 | H29: Стр. 26; строка определяется по формулировке «Соотношение студентов и преподавателей» | I29: Соотношение студентов и преподавателей | J29: Abai University | K29: Не является обязательным KPI | L29: Аналитический ориентир | N29: ед. | W29: Сверено с первоисточником
A30: 28 | B30: K152 | C30: Образование | D30: Показатель | E30: Доля международных сотрудников | F30: THE анализ 2026.pdf | G30: D03 | H30: Стр. 63; строка определяется по формулировке «Доля международных сотрудников» | I30: Доля международных сотрудников | J30: Abai University | K30: Не является обязательным KPI | L30: Аналитический ориентир | N30: % | W30: Сверено с первоисточником: формулировка реестра не подтверждена дословно; требуется уточнение
A31: 29 | B31: K153 | C31: Образование | D31: Показатель | E31: Доля иностранных студентов | F31: THE анализ 2026.pdf | G31: D03 | H31: Стр. 63; строка определяется по формулировке «Доля иностранных студентов» | I31: Доля иностранных студентов | J31: Abai University | K31: Не является обязательным KPI | L31: Аналитический ориентир | N31: % | W31: Сверено с первоисточником
A32: 30 | B32: K155 | C32: Образование | D32: Показатель | E32: Голоса за преподавательскую репутацию | F32: THE анализ 2026.pdf | G32: D03 | H32: Стр. 73; строка определяется по формулировке «Голоса за преподавательскую репутацию» | I32: Голоса за преподавательскую репутацию | J32: Abai University | K32: Не является обязательным KPI | L32: Аналитический ориентир | N32: ед. | W32: Сверено с первоисточником: формулировка реестра не подтверждена дословно; требуется уточнение
A33: 31 | B33: K160 | C33: Образование | D33: Показатель | E33: Итоговый балл THE WUR 2031 — сценарий A | F33: THE анализ 2026.pdf | G33: D03 | H33: Итоговая симуляция; строка определяется по формулировке «Итоговый балл THE WUR 2031 — сценарий A» | I33: Итоговый балл THE WUR 2031 — сценарий A | J33: Abai University | K33: Не является обязательным KPI | L33: Аналитический ориентир | N33: балл | W33: Сверено с первоисточником: формулировка реестра не подтверждена дословно; требуется уточнение
A34: 32 | B34: K161 | C34: Образование | D34: Показатель | E34: Итоговый балл THE WUR 2031 — сценарий B | F34: THE анализ 2026.pdf | G34: D03 | H34: Итоговая симуляция; строка определяется по формулировке «Итоговый балл THE WUR 2031 — сценарий B» | I34: Итоговый балл THE WUR 2031 — сценарий B | J34: Abai University | K34: Не является обязательным KPI | L34: Аналитический ориентир | N34: балл | W34: Сверено с первоисточником: формулировка реестра не подтверждена дословно; требуется уточнение
A35: 33 | B35: K162 | C35: Образование | D35: Показатель | E35: Итоговый балл THE WUR 2031 — сценарий C | F35: THE анализ 2026.pdf | G35: D03 | H35: Итоговая симуляция; строка определяется по формулировке «Итоговый балл THE WUR 2031 — сценарий C» | I35: Итоговый балл THE WUR 2031 — сценарий C | J35: Abai University | K35: Не является обязательным KPI | L35: Аналитический ориентир | N35: балл | W35: Сверено с первоисточником: формулировка реестра не подтверждена дословно; требуется уточнение
A36: 34 | B36: M001 | C36: Образование | D36: Мероприятие | E36: Разработка единых требований к ОП педагогических направлении | F36: 0707_План действий -рус.docx | G36: D02 | H36: Таблица 1, строка 5; строка определяется по формулировке «Разработка единых требований к ОП педагогических направлении» | I36: Разработка единых требований к ОП педагогических направлении | J36: Организация/исполнитель по документу | K36: Требование/мероприятие применимо к ОВПО | L36: Прямая или совместная | W36: Сверено с первоисточником
A37: 35 | B37: M002 | C37: Образование | D37: Мероприятие | E37: Переход к двух этапному отбору абитуриентов на педагогические образовательные программы (ETS/AIT) | F37: 0707_План действий -рус.docx | G37: D02 | H37: Таблица 1, строка 6; строка определяется по формулировке «Переход к двух этапному отбору абитуриентов на педагогические образовательные программы (ETS/AIT)» | I37: Переход к двух этапному отбору абитуриентов на педагогические образовательные программы (ETS/AIT) | J37: Организация/исполнитель по документу | K37: Требование/мероприятие применимо к ОВПО | L37: Прямая или совместная | W37: Сверено с первоисточником
A38: 36 | B38: M003 | C38: Образование | D38: Мероприятие | E38: Выработка предложении по актуализации профессионального стандарта «Педагог» | F38: 0707_План действий -рус.docx | G38: D02 | H38: Таблица 1, строка 7; строка определяется по формулировке «Выработка предложении по актуализации профессионального стандарта «Педагог»» | I38: Выработка предложении по актуализации профессионального стандарта «Педагог» | J38: Организация/исполнитель по документу | K38: Требование/мероприятие применимо к ОВПО | L38: Прямая или совместная | W38: Сверено с первоисточником
A39: 37 | B39: M004 | C39: Образование | D39: Мероприятие | E39: Введение требований по AI-компетенциям выпускников педагогических образовательных программ | F39: 0707_План действий -рус.docx | G39: D02 | H39: Таблица 1, строка 8; строка определяется по формулировке «Введение требований по AI-компетенциям выпускников педагогических образовательных программ» | I39: Введение требований по AI-компетенциям выпускников педагогических образовательных программ | J39: Организация/исполнитель по документу | K39: Требование/мероприятие применимо к ОВПО | L39: Прямая или совместная | W39: Сверено с первоисточником
A40: 38 | B40: M005 | C40: Образование | D40: Мероприятие | E40: Модель школоцентричной подготовки педагогов | F40: 0707_План действий -рус.docx | G40: D02 | H40: Таблица 1, строка 9; строка определяется по формулировке «Модель школоцентричной подготовки педагогов» | I40: Модель школоцентричной подготовки педагогов | J40: Организация/исполнитель по документу | K40: Требование/мероприятие применимо к ОВПО | L40: Прямая или совместная | W40: Сверено с первоисточником
A41: 39 | B41: M006 | C41: Образование | D41: Мероприятие | E41: Введение системы оценки качества подготовки педагогов по методологии PRL и S-PRL | F41: 0707_План действий -рус.docx | G41: D02 | H41: Таблица 1, строка 10; строка определяется по формулировке «Введение системы оценки качества подготовки педагогов по методологии PRL и S-PRL» | I41: Введение системы оценки качества подготовки педагогов по методологии PRL и S-PRL | J41: Организация/исполнитель по документу | K41: Требование/мероприятие применимо к ОВПО | L41: Прямая или совместная | W41: Сверено с первоисточником
A42: 40 | B42: M007 | C42: Образование | D42: Мероприятие | E42: Введение демонстрационного педагогического экзамена как механизма итоговой аттестации выпускников | F42: 0707_План действий -рус.docx | G42: D02 | H42: Таблица 1, строка 11; строка определяется по формулировке «Введение демонстрационного педагогического экзамена как механизма итоговой аттестации выпускников» | I42: Введение демонстрационного педагогического экзамена как механизма итоговой аттестации выпускников | J42: Организация/исполнитель по документу | K42: Требование/мероприятие применимо к ОВПО | L42: Прямая или совместная | W42: Сверено с первоисточником
A43: 41 | B43: M008 | C43: Образование | D43: Мероприятие | E43: Проработка вопроса размещения государственного образовательного заказа с учетом региональной потребности по педагогическим направлениям. | F43: 0707_План действий -рус.docx | G43: D02 | H43: Таблица 1, строка 12; строка определяется по формулировке «Проработка вопроса размещения государственного образовательного заказа с учетом региональной потребности по педагогическим направлениям.» | I43: Проработка вопроса размещения государственного образовательного заказа с учетом региональной потребности по педагогическим направлениям. | J43: Организация/исполнитель по документу | K43: Применимость определяется по документу | L43: Требуется проверка | W43: Сверено с первоисточником
A44: 42 | B44: M009 | C44: Образование | D44: Мероприятие | E44: Разработка стандартов по применению ИИ-педагогики | F44: 0707_План действий -рус.docx | G44: D02 | H44: Таблица 1, строка 13; строка определяется по формулировке «Разработка стандартов по применению ИИ-педагогики» | I44: Разработка стандартов по применению ИИ-педагогики | J44: Организация/исполнитель по документу | K44: Требование/мероприятие применимо к ОВПО | L44: Прямая или совместная | W44: Сверено с первоисточником
A45: 43 | B45: M010 | C45: Образование | D45: Мероприятие | E45: Разработка положение ранней профориентации школьников на педагогические профессии | F45: 0707_План действий -рус.docx | G45: D02 | H45: Таблица 1, строка 14; строка определяется по формулировке «Разработка положение ранней профориентации школьников на педагогические профессии» | I45: Разработка положение ранней профориентации школьников на педагогические профессии | J45: Организация/исполнитель по документу | K45: Требование/мероприятие применимо к ОВПО | L45: Прямая или совместная | W45: Сверено с первоисточником
A46: 44 | B46: M011 | C46: Образование | D46: Мероприятие | E46: Создание сети партнерских организации образования | F46: 0707_План действий -рус.docx | G46: D02 | H46: Таблица 1, строка 17; строка определяется по формулировке «Создание сети партнерских организации образования» | I46: Создание сети партнерских организации образования | J46: Организация/исполнитель по документу | K46: Требование/мероприятие применимо к ОВПО | L46: Прямая или совместная | W46: Сверено с первоисточником
A47: 45 | B47: M012 | C47: Образование | D47: Мероприятие | E47: Механизмы масштабирования элементов дуального обучения | F47: 0707_План действий -рус.docx | G47: D02 | H47: Таблица 1, строка 18; строка определяется по формулировке «Механизмы масштабирования элементов дуального обучения» | I47: Механизмы масштабирования элементов дуального обучения | J47: Организация/исполнитель по документу | K47: Требование/мероприятие применимо к ОВПО | L47: Прямая или совместная | W47: Сверено с первоисточником
... A151: 149 | B151: Q043 | C151: Квалификационные требования — онлайн-обучение (условно) | D151: Нормативное требование | E151: Доля преподавателей по направлению подготовки кадров, для которых основным местом работы является ОВПО, с ученой степенью и (или) степенью (академической) доктора философии PhD/доктора по профилю и (или) ученым званием, выданными/признанными уполномоченным органом в области науки и высшего образования и (или) с присвоением спортивного звания "Заслуженный тренер Республики Казахстан", от общего числа преподавателей по образовательной программе направления подготовки кадров – не менее 70 %. Наличие не менее 3 (трех) штатных преподавателей, имеющих не менее 3-х (трех) статей и/или обзоров в рецензируемых международных научных журналах по направлению EdTech за последние 5 (пять) лет входящих в 1, 2 квартиль по данным Journal Citation Reports компании Clarivate или имеющих в базе данных Scopus показатель процентиль по CiteScore не менее 50-ти (пятидесяти) в которых они являются авторами-корреспондентами или первыми (основными) авторами. | F151: квалиф. требования с орг.образ6.rus.pdf | G151: D10 | H151: Таблица 3, строка 53; строка определяется по формулировке «Доля преподавателей по направлению подготовки кадров, для которых основным местом работы является ОВПО, с ученой степенью и (или) степенью (академической) доктора философии PhD/док» | I151: Доля преподавателей по направлению подготовки кадров, для которых основным местом работы является ОВПО, с ученой степенью и (или) степенью (академической) доктора философии PhD/доктора по профилю и (или) ученым званием, выданными/признанным | J151: Онлайн-обучение (условно, при реализации) | K151: Применяется только при реализации образовательных программ в форме онлайн-обучения | L151: Условная — при реализации онлайн-обучения | W151: Сверено с первоисточником: формулировка реестра не подтверждена дословно; требуется уточнение
A152: 150 | B152: K014 | C152: Наука | D152: Показатель | E152: Уровень активности в области инноваций | F152: Ключевые прказатели МНВО.docx | G152: D04 | H152: Таблица 2, показатель №13 («Уровень активности в области инноваций»); значения 2024–2030 | I152: Уровень активности в области инноваций | J152: Национальный | K152: Национальный/отраслевой показатель | L152: Требуется декомпозиция | M152: Указать после подтверждения индивидуального значения | N152: % | P152: 11.9 | Q152: 15.9 | R152: 17.4 | S152: 18.9 | T152: 20.4 | U152: 21.9 | V152: 23.4 | W152: Сверено с таблицей первоисточника
A153: 151 | B153: K015 | C153: Наука | D153: Показатель | E153: Количество заключенных договоров по предоставлению инновационных грантов | F153: Ключевые прказатели МНВО.docx | G153: D04 | H153: Таблица 2, показатель №14 («Количество заключенных договоров по предоставлению инновационных грантов»); значения 2024–2030 | I153: Количество заключенных договоров по предоставлению инновационных грантов | J153: Национальный | K153: Национальный/отраслевой показатель | L153: Требуется декомпозиция | M153: Указать после подтверждения индивидуального значения | N153: ед. | P153: 20 | Q153: 20 | R153: 20 | S153: 20 | T153: 20 | U153: 20 | V153: 20 | W153: Сверено с таблицей первоисточника
A154: 152 | B154: K016 | C154: Наука | D154: Показатель | E154: Отношение количества статей и обзоров в журналах из основных индексов Web of Science к количеству статей и обзоров в журналах из Scopus | F154: Ключевые прказатели МНВО.docx | G154: D04 | H154: Таблица 2, показатель №15 («Отношение количества статей и обзоров в журналах из основных индексов Web of Science к кол»); значения 2024–2030 | I154: Отношение количества статей и обзоров в журналах из основных индексов Web of Science к количеству статей и обзоров в журналах из Scopus | J154: Национальный | K154: Национальный/отраслевой показатель | L154: Требуется декомпозиция | M154: Указать после подтверждения индивидуального значения | N154: % | P154: 47 | Q154: 50 | R154: 54 | S154: 58 | T154: 62 | U154: 67 | V154: 70 | W154: Сверено с таблицей первоисточника
A155: 153 | B155: K017 | C155: Наука | D155: Показатель | E155: Место в рейтинге Глобальный индекс инноваций (Global innovation index) | F155: Ключевые прказатели МНВО.docx | G155: D04 | H155: Таблица 2, показатель №16 («Место в рейтинге Глобальный индекс инноваций (Global innovation index)»); значения 2024–2030 | I155: Место в рейтинге Глобальный индекс инноваций (Global innovation index) | J155: Национальный | K155: Национальный/отраслевой показатель | L155: Требуется декомпозиция | M155: Указать после подтверждения индивидуального значения | N155: место в рейтинге | P155: 78 | Q155: 77 | R155: 76 | S155: 75 | T155: 74 | U155: 73 | V155: 72 | W155: Сверено с таблицей первоисточника
A156: 154 | B156: K018 | C156: Наука | D156: Показатель | E156: Доля расходов предпринимательского сектора от общего объема затрат на НИОКР | F156: Ключевые прказатели МНВО.docx | G156: D04 | H156: Таблица 2, показатель №17 («Доля расходов предпринимательского сектора от общего объема затрат на НИОКР»); значения 2024–2030 | I156: Доля расходов предпринимательского сектора от общего объема затрат на НИОКР | J156: Национальный | K156: Национальный/отраслевой показатель | L156: Требуется декомпозиция | M156: Указать после подтверждения индивидуального значения | N156: % | P156: 28.2 | Q156: 30 | R156: 32 | S156: 38 | T156: 43 | U156: 50 | V156: 55 | W156: Сверено с таблицей первоисточника
A157: 155 | B157: K019 | C157: Наука | D157: Показатель | E157: Доля внутренних затрат на НИОКР от валового внутреннего продукта | F157: Ключевые прказатели МНВО.docx | G157: D04 | H157: Таблица 2, показатель №18 («Доля внутренних затрат на НИОКР от валового внутреннего продукта»); значения 2024–2030 | I157: Доля внутренних затрат на НИОКР от валового внутреннего продукта | J157: Национальный | K157: Национальный/отраслевой показатель | L157: Требуется декомпозиция | M157: Указать после подтверждения индивидуального значения | N157: % | P157: 0.16 | Q157: 0.16 | R157: 0.2 | S157: 0.4 | T157: 0.5 | U157: 1 | V157: 1.1 | W157: Сверено с таблицей первоисточника
A158: 156 | B158: K020 | C158: Наука | D158: Показатель | E158: Рост позиции Казахстана в страновом рейтинге InCites по общему количеству статей в индексируемых научных журналах | F158: Ключевые прказатели МНВО.docx | G158: D04 | H158: Таблица 2, показатель №19 («Рост позиции Казахстана в страновом рейтинге InCites по общему количеству статей в индекси»); значения 2024–2030 | I158: Рост позиции Казахстана в страновом рейтинге InCites по общему количеству статей в индексируемых научных журналах | J158: Национальный | K158: Национальный/отраслевой показатель | L158: Требуется декомпозиция | M158: Указать после подтверждения индивидуального значения | N158: место | P158: 72 | Q158: 71 | R158: 70 | S158: 69 | T158: 68 | U158: 67 | V158: 66 | W158: Сверено с таблицей первоисточника
A159: 157 | B159: K021 | C159: Наука | D159: Показатель | E159: Доля коммерциализируемых проектов от общего количества завершенных прикладных научно-исследовательских работ | F159: Ключевые прказатели МНВО.docx | G159: D04 | H159: Таблица 2, показатель №20 («Доля коммерциализируемых проектов от общего количества завершенных прикладных научно-иссле»); значения 2024–2030 | I159: Доля коммерциализируемых проектов от общего количества завершенных прикладных научно-исследовательских работ | J159: Национальный | K159: Национальный/отраслевой показатель | L159: Требуется декомпозиция | M159: Указать после подтверждения индивидуального значения | N159: % | P159: 29.4 | Q159: 35 | R159: 37 | S159: 40 | T159: 45 | U159: 50 | V159: 55 | W159: Сверено с таблицей первоисточника
A160: 158 | B160: K022 | C160: Наука | D160: Показатель | E160: Коэффициент обеспечения базового финансирования субъектов научной и (или) научно-технической деятельности реализующих НИОКР | F160: Ключевые прказатели МНВО.docx | G160: D04 | H160: Таблица 2, показатель №21 («Коэффициент обеспечения базового финансирования субъектов научной и (или) научно-техническ»); значения 2024–2030 | I160: Коэффициент обеспечения базового финансирования субъектов научной и (или) научно-технической деятельности реализующих НИОКР | J160: Национальный | K160: Национальный/отраслевой показатель | L160: Требуется декомпозиция | M160: Указать после подтверждения индивидуального значения | N160: % | P160: 100 | Q160: 100 | R160: 100 | S160: 100 | T160: 100 | U160: 100 | V160: 100 | W160: Сверено с таблицей первоисточника
A161: 159 | B161: K023 | C161: Наука | D161: Показатель | E161: Количество исследователей (в эквиваленте полной занятости), выполнявших НИОКР | F161: Ключевые прказатели МНВО.docx | G161: D04 | H161: Таблица 2, показатель №22 («Количество исследователей (в эквиваленте полной занятости), выполнявших НИОКР»); значения 2024–2030 | I161: Количество исследователей (в эквиваленте полной занятости), выполнявших НИОКР | J161: Национальный | K161: Национальный/отраслевой показатель | L161: Требуется декомпозиция | M161: Указать после подтверждения индивидуального значения | N161: человек на 1 млн. жителей | P161: 769 | Q161: 855 | R161: 860 | S161: 865 | T161: 870 | U161: 875 | V161: 880 | W161: Сверено с таблицей первоисточника
A162: 160 | B162: K024 | C162: Наука | D162: Показатель | E162: Доля обновленного оборудования лабораторий научных организаций и университетов | F162: Ключевые прказатели МНВО.docx | G162: D04 | H162: Таблица 2, показатель №23 («Доля обновленного оборудования лабораторий научных организаций и университетов»); значения 2024–2030 | I162: Доля обновленного оборудования лабораторий научных организаций и университетов | J162: Национальный | K162: Национальный/отраслевой показатель | L162: Требуется декомпозиция | M162: Указать после подтверждения индивидуального значения | N162: % | P162: ‒ | Q162: 20 | R162: 25 | S162: 30 | T162: 35 | U162: 40 | V162: 45 | W162: Сверено с таблицей первоисточника
A163: 161 | B163: K025 | C163: Наука | D163: Показатель | E163: Степень удовлетворенности научного сообщества, бизнеса и других стейкхолдеров государственным администрированием науки (социологический опрос) | F163: Ключевые прказатели МНВО.docx | G163: D04 | H163: Таблица 2, показатель №24 («Степень удовлетворенности научного сообщества, бизнеса и других стейкхолдеров государствен»); значения 2024–2030 | I163: Степень удовлетворенности научного сообщества, бизнеса и других стейкхолдеров государственным администрированием науки (социологический опрос) | J163: Национальный | K163: Национальный/отраслевой показатель | L163: Требуется декомпозиция | M163: Указать после подтверждения индивидуального значения | N163: % | P163: 49.6 | Q163: 59 | R163: 62 | S163: 65 | T163: 68 | U163: 70 | V163: 72 | W163: Сверено с таблицей первоисточника
A164: 162 | B164: K026 | C164: Наука | D164: Показатель | E164: Доля молодых ученых от общего числа ученых и исследователей, осуществляющих НИОКР | F164: Ключевые прказатели МНВО.docx | G164: D04 | H164: Таблица 2, показатель №25 («Доля молодых ученых от общего числа ученых и исследователей, осуществляющих НИОКР»); значения 2024–2030 | I164: Доля молодых ученых от общего числа ученых и исследователей, осуществляющих НИОКР | J164: Национальный | K164: Национальный/отраслевой показатель | L164: Требуется декомпозиция | M164: Указать после подтверждения индивидуального значения | N164: % | P164: 39.5 | Q164: 40 | R164: 43 | S164: 45 | T164: 46 | U164: 47 | V164: 48 | W164: Сверено с таблицей первоисточника
A165: 163 | B165: K027 | C165: Наука | D165: Показатель | E165: Доля ненаблюдаемой (теневой) экономики в сфере образования, % к ВВП в т.ч.: | F165: Ключевые прказатели МНВО.docx | G165: D04 | H165: Таблица 2, показатель №26 («Доля ненаблюдаемой (теневой) экономики в сфере образования, % к ВВП в т.ч.:»); значения 2024–2030 | I165: Доля ненаблюдаемой (теневой) экономики в сфере образования, % к ВВП в т.ч.: | J165: Национальный | K165: Национальный/отраслевой показатель | L165: Требуется декомпозиция | M165: Указать после подтверждения индивидуального значения | N165: % | P165: 0.55 | Q165: 0.51 | R165: 0.49 | S165: 0.47 | T165: 0.46 | U165: 0.44 | V165: 0.4 | W165: Сверено с таблицей первоисточника
A166: 164 | B166: K101 | C166: Наука | D166: Показатель | E166: Результаты педагогических исследований, внедренные в практику | F166: 0707_План действий -рус.docx | G166: D02 | H166: Целевой индикатор 6; строка определяется по формулировке «Результаты педагогических исследований, внедренные в практику» | I166: Результаты педагогических исследований, внедренные в практику | J166: Национальный | K166: Требование/мероприятие применимо к ОВПО | L166: Прямая или совместная | N166: % | S166: 20 | T166: 40 | U166: 60 | V166: 80 | W166: Сверено с первоисточником: формулировка реестра не подтверждена дословно; требуется уточнение
A167: 165 | B167: K111 | C167: Наука | D167: Показатель | E167: Публикации в WoS/Scopus к общему числу публикаций | F167: прил 1 рус.pdf | G167: D07 | H167: Таблица «Направления, цели, целевые индикаторы…», строка 9, стр. 3 | I167: Публикации в WoS/Scopus к общему числу публикаций | J167: Национальный | K167: Национальный/отраслевой показатель | L167: Требуется декомпозиция | M167: Указать после подтверждения индивидуального значения | N167: % | R167: 54 | S167: 58 | W167: Сверено с первоисточником; формулировка сокращена без изменения содержания
A168: 166 | B168: K112 | C168: Наука | D168: Показатель | E168: Уровень инновационной активности | F168: прил 1 рус.pdf | G168: D07 | H168: Таблица «Направления, цели, целевые индикаторы…», строка 12, стр. 3 | I168: Уровень инновационной активности | J168: Национальный | K168: Национальный/отраслевой показатель | L168: Требуется декомпозиция | M168: Указать после подтверждения индивидуального значения | N168: % | R168: 17.4 | S168: 18.9 | W168: Сверено с первоисточником; формулировка сокращена без изменения содержания
A169: 167 | B169: K113 | C169: Наука | D169: Показатель | E169: Затраты на НИОКР к ВВП | F169: прил 1 рус.pdf | G169: D07 | H169: Таблица «Направления, цели, целевые индикаторы…», строка 14, стр. 3 | I169: Затраты на НИОКР к ВВП | J169: Национальный | K169: Национальный/отраслевой показатель | L169: Требуется декомпозиция | M169: Указать после подтверждения индивидуального значения | N169: % | R169: 0.2 | S169: 0.4 | W169: Сверено с первоисточником; формулировка сокращена без изменения содержания
A170: 168 | B170: K114 | C170: Наука | D170: Показатель | E170: Доля коммерциализированных проектов | F170: прил 1 рус.pdf | G170: D07 | H170: Таблица «Направления, цели, целевые индикаторы…», строка 16, стр. 3 | I170: Доля коммерциализированных проектов | J170: Национальный | K170: Национальный/отраслевой показатель | L170: Требуется декомпозиция | M170: Указать после подтверждения индивидуального значения | N170: % | R170: 37 | S170: 40 | W170: Сверено с первоисточником; формулировка сокращена без изменения содержания
A171: 169 | B171: K115 | C171: Наука | D171: Показатель | E171: Доля предпринимательского сектора в расходах на НИОКР | F171: прил 1 рус.pdf | G171: D07 | H171: Таблица «Направления, цели, целевые индикаторы…», строка 17, стр. 4 | I171: Доля предпринимательского сектора в расходах на НИОКР | J171: Национальный | K171: Национальный/отраслевой показатель | L171: Требуется декомпозиция | M171: Указать после подтверждения индивидуального значения | N171: % | R171: 32 | S171: 38 | W171: Сверено с первоисточником; формулировка сокращена без изменения содержания
A172: 170 | B172: K116 | C172: Наука | D172: Показатель | E172: Уровень защиты интеллектуальной собственности | F172: прил 1 рус.pdf | G172: D07 | H172: Таблица «Направления, цели, целевые индикаторы…», строка 19, стр. 4 | I172: Уровень защиты интеллектуальной собственности | J172: Национальный | K172: Национальный/отраслевой показатель | L172: Требуется декомпозиция | M172: Указать после подтверждения индивидуального значения | N172: % | R172: 61 | S172: 62 | W172: Сверено с первоисточником; формулировка сокращена без изменения содержания
A173: 171 | B173: K120 | C173: Наука | D173: Показатель | E173: Внутренние затраты на науку к ВВП | F173: прил 1 рус.pdf | G173: D07 | H173: Таблица «Направления, цели, целевые индикаторы…», строка 30, стр. 5 | I173: Внутренние затраты на науку к ВВП | J173: Национальный | K173: Национальный/отраслевой показатель | L173: Требуется декомпозиция | M173: Указать после подтверждения индивидуального значения | N173: % | R173: 0.2 | S173: 0.25 | W173: Сверено с первоисточником; формулировка сокращена без изменения содержания
A174: 172 | B174: K121 | C174: Наука | D174: Показатель | E174: Позиция Казахстана в рейтинге InCites | F174: прил 1 рус.pdf | G174: D07 | H174: Таблица «Направления, цели, целевые индикаторы…», строка 32, стр. 5 | I174: Позиция Казахстана в рейтинге InCites | J174: Национальный | K174: Национальный/отраслевой показатель | L174: Требуется декомпозиция | M174: Указать после подтверждения индивидуального значения | N174: место | R174: 70 | S174: 69 | W174: Сверено с первоисточником; формулировка сокращена без изменения содержания
A175: 173 | B175: K122 | C175: Наука | D175: Показатель | E175: Доля коммерциализированных результатов НИОКР | F175: прил 1 рус.pdf | G175: D07 | H175: Таблица «Направления, цели, целевые индикаторы…», строка 33, стр. 5 | I175: Доля коммерциализированных результатов НИОКР | J175: Национальный | K175: Национальный/отраслевой показатель | L175: Требуется декомпозиция | M175: Указать после подтверждения индивидуального значения | N175: % | R175: 37 | S175: 40 | W175: Сверено с первоисточником; формулировка сокращена без изменения содержания
A176: 174 | B176: K123 | C176: Наука | D176: Показатель | E176: Доля бизнеса в финансировании НИОКР | F176: прил 1 рус.pdf | G176: D07 | H176: Таблица «Направления, цели, целевые индикаторы…», строка 34, стр. 5 | I176: Доля бизнеса в финансировании НИОКР | J176: Национальный | K176: Национальный/отраслевой показатель | L176: Требуется декомпозиция | M176: Указать после подтверждения индивидуального значения | N176: % | R176: 32 | S176: 38 | W176: Сверено с первоисточником; формулировка сокращена без изменения содержания
A177: 175 | B177: K124 | C177: Наука | D177: Показатель | E177: Рост патентной активности | F177: прил 1 рус.pdf | G177: D07 | H177: Таблица «Направления, цели, целевые индикаторы…», строка 35, стр. 5 | I177: Рост патентной активности | J177: Национальный | K177: Национальный/отраслевой показатель | L177: Требуется декомпозиция | M177: Указать после подтверждения индивидуального значения | N177: % | R177: 21 | S177: 23 | W177: Сверено с первоисточником; формулировка сокращена без изменения содержания
A178: 176 | B178: K125 | C178: Наука | D178: Показатель | E178: Охват базовым финансированием субъектов науки | F178: прил 1 рус.pdf | G178: D07 | H178: Таблица «Направления, цели, целевые индикаторы…», строка 36, стр. 6 | I178: Охват базовым финансированием субъектов науки | J178: Национальный | K178: Национальный/отраслевой показатель | L178: Требуется декомпозиция | M178: Указать после подтверждения индивидуального значения | N178: % | R178: 100 | S178: 100 | W178: Сверено с первоисточником; формулировка сокращена без изменения содержания
A179: 177 | B179: K126 | C179: Наука | D179: Показатель | E179: Численность исследователей на 1 млн населения | F179: прил 1 рус.pdf | G179: D07 | H179: Таблица «Направления, цели, целевые индикаторы…», строка 38, стр. 6 | I179: Численность исследователей на 1 млн населения | J179: Национальный | K179: Национальный/отраслевой показатель | L179: Требуется декомпозиция | M179: Указать после подтверждения индивидуального значения | N179: чел. | R179: 860 | S179: 865 | W179: Сверено с первоисточником; формулировка сокращена без изменения содержания
A180: 178 | B180: K147 | C180: Наука | D180: Показатель | E180: Публикации на одного академического сотрудника | F180: THE анализ 2026.pdf | G180: D03 | H180: Стр. 37; строка определяется по формулировке «Публикации на одного академического сотрудника» | I180: Публикации на одного академического сотрудника | J180: Abai University | K180: Не является обязательным KPI | L180: Аналитический ориентир | N180: ед. | W180: Сверено с первоисточником: формулировка реестра не подтверждена дословно; требуется уточнение
A181: 179 | B181: K148 | C181: Наука | D181: Показатель | E181: Публикации в ТОП-10% по цитируемости | F181: THE анализ 2026.pdf | G181: D03 | H181: Стр. 38; строка определяется по формулировке «Публикации в ТОП-10% по цитируемости» | I181: Публикации в ТОП-10% по цитируемости | J181: Abai University | K181: Не является обязательным KPI | L181: Аналитический ориентир | N181: ед. | W181: Сверено с первоисточником: формулировка реестра не подтверждена дословно; требуется уточнение
A182: 180 | B182: K149 | C182: Наука | D182: Показатель | E182: Нормированный показатель публикаций ТОП-10% | F182: THE анализ 2026.pdf | G182: D03 | H182: Стр. 38; строка определяется по формулировке «Нормированный показатель публикаций ТОП-10%» | I182: Нормированный показатель публикаций ТОП-10% | J182: Abai University | K182: Не является обязательным KPI | L182: Аналитический ориентир | N182: ед. | W182: Сверено с первоисточником: формулировка реестра не подтверждена дословно; требуется уточнение
A183: 181 | B183: K150 | C183: Наука | D183: Показатель | E183: Патенты, цитирующие исследования | F183: THE анализ 2026.pdf | G183: D03 | H183: Стр. 51; строка определяется по формулировке «Патенты, цитирующие исследования» | I183: Патенты, цитирующие исследования | J183: Abai University | K183: Не является обязательным KPI | L183: Аналитический ориентир | N183: ед. | W183: Сверено с первоисточником: формулировка реестра не подтверждена дословно; требуется уточнение
A184: 182 | B184: K151 | C184: Наука | D184: Показатель | E184: Нормированный показатель патентов, цитирующих исследования | F184: THE анализ 2026.pdf | G184: D03 | H184: Стр. 51; строка определяется по формулировке «Нормированный показатель патентов, цитирующих исследования» | I184: Нормированный показатель патентов, цитирующих исследования | J184: Abai University | K184: Не является обязательным KPI | L184: Аналитический ориентир | N184: ед. | W184: Сверено с первоисточником: формулировка реестра не подтверждена дословно; требуется уточнение
A185: 183 | B185: K154 | C185: Наука | D185: Показатель | E185: Международное соавторство | F185: THE анализ 2026.pdf | G185: D03 | H185: Стр. 64; строка определяется по формулировке «Международное соавторство» | I185: Международное соавторство | J185: Abai University | K185: Не является обязательным KPI | L185: Аналитический ориентир | N185: % | W185: Сверено с первоисточником
A186: 184 | B186: K156 | C186: Наука | D186: Показатель | E186: Голоса за исследовательскую репутацию | F186: THE анализ 2026.pdf | G186: D03 | H186: Стр. 73; строка определяется по формулировке «Голоса за исследовательскую репутацию» | I186: Голоса за исследовательскую репутацию | J186: Abai University | K186: Не является обязательным KPI | L186: Аналитический ориентир | N186: ед. | W186: Сверено с первоисточником: формулировка реестра не подтверждена дословно; требуется уточнение
A187: 185 | B187: M030 | C187: Наука | D187: Мероприятие | E187: Оснащение педагогических вузов лабораториями цифровой педагогики | F187: 0707_План действий -рус.docx | G187: D02 | H187: Таблица 1, строка 39; строка определяется по формулировке «Оснащение педагогических вузов лабораториями цифровой педагогики» | I187: Оснащение педагогических вузов лабораториями цифровой педагогики | J187: Организация/исполнитель по документу | K187: Требование/мероприятие применимо к ОВПО | L187: Прямая или совместная | W187: Сверено с первоисточником
A188: 186 | B188: M033 | C188: Наука | D188: Мероприятие | E188: Привлечение зарубежных экспертов к преподавательской деятельности из ведущих университетов дальнего зарубежья, имеющих публикации в высокорейтинговых научных изданиях | F188: 0707_План действий -рус.docx | G188: D02 | H188: Таблица 1, строка 44; строка определяется по формулировке «Привлечение зарубежных экспертов к преподавательской деятельности из ведущих университетов дальнего зарубежья, имеющих публикации в высокорейтинговых научных изданиях» | I188: Привлечение зарубежных экспертов к преподавательской деятельности из ведущих университетов дальнего зарубежья, имеющих публикации в высокорейтинговых научных изданиях | J188: Организация/исполнитель по документу | K188: Требование/мероприятие применимо к ОВПО | L188: Прямая или совместная | W188: Сверено с первоисточником
A189: 187 | B189: M037 | C189: Наука | D189: Мероприятие | E189: Увеличение количества исследований в области педагогики и школьного образования | F189: 0707_План действий -рус.docx | G189: D02 | H189: Таблица 1, строка 50; строка определяется по формулировке «Увеличение количества исследований в области педагогики и школьного образования» | I189: Увеличение количества исследований в области педагогики и школьного образования | J189: Организация/исполнитель по документу | K189: Требование/мероприятие применимо к ОВПО | L189: Прямая или совместная | W189: Сверено с первоисточником
A190: 188 | B190: M038 | C190: Наука | D190: Мероприятие | E190: Создание центров образовательных исследований в педагогических вузах | F190: 0707_План действий -рус.docx | G190: D02 | H190: Таблица 1, строка 51; строка определяется по формулировке «Создание центров образовательных исследований в педагогических вузах» | I190: Создание центров образовательных исследований в педагогических вузах | J190: Организация/исполнитель по документу | K190: Требование/мероприятие применимо к ОВПО | L190: Прямая или совместная | W190: Сверено с первоисточником
A191: 189 | B191: M041 | C191: Наука | D191: Мероприятие | E191: Финансирование прикладных исследований в области образования | F191: 0707_План действий -рус.docx | G191: D02 | H191: Таблица 1, строка 54; строка определяется по формулировке «Финансирование прикладных исследований в области образования» | I191: Финансирование прикладных исследований в области образования | J191: Организация/исполнитель по документу | K191: Применимость определяется по документу | L191: Требуется проверка | W191: Сверено с первоисточником
A192: 190 | B192: M042 | C192: Наука | D192: Мероприятие | E192: Реализация магистерских и докторских исследований с помощью analytics date и внедрение в практику организации образования | F192: 0707_План действий -рус.docx | G192: D02 | H192: Таблица 1, строка 55; строка определяется по формулировке «Реализация магистерских и докторских исследований с помощью analytics date и внедрение в практику организации образования» | I192: Реализация магистерских и докторских исследований с помощью analytics date и внедрение в практику организации образования | J192: Организация/исполнитель по документу | K192: Требование/мероприятие применимо к ОВПО | L192: Прямая или совместная | W192: Сверено с первоисточником
A193: 191 | B193: M043 | C193: Наука | D193: Мероприятие | E193: Наличие системы распространения лучших педагогических практик и результатов исследований среди организаций образования | F193: 0707_План действий -рус.docx | G193: D02 | H193: Таблица 1, строка 56; строка определяется по формулировке «Наличие системы распространения лучших педагогических практик и результатов исследований среди организаций образования» | I193: Наличие системы распространения лучших педагогических практик и результатов исследований среди организаций образования | J193: Организация/исполнитель по документу | K193: Требование/мероприятие применимо к ОВПО | L193: Прямая или совместная | W193: Сверено с первоисточником
A194: 192 | B194: M045 | C194: Наука | D194: Мероприятие | E194: Реализация исследований в области образования для устойчивого развития (ESD) | F194: 0707_План действий -рус.docx | G194: D02 | H194: Таблица 1, строка 58; строка определяется по формулировке «Реализация исследований в области образования для устойчивого развития (ESD)» | I194: Реализация исследований в области образования для устойчивого развития (ESD) | J194: Организация/исполнитель по документу | K194: Требование/мероприятие применимо к ОВПО | L194: Прямая или совместная | W194: Сверено с первоисточником
A195: 193 | B195: M072 | C195: Наука | D195: Мероприятие | E195: Обновление внутренних документов ОВПО по применению ИИ в учебной, научной, административной и управленческой деятельности | F195: План по ИИ.pdf | G195: D06 | H195: Пункт 1.3; строка определяется по формулировке «Обновление внутренних документов ОВПО по применению ИИ в учебной, научной, административной и управленческой деятельности» | I195: Обновление внутренних документов ОВПО по применению ИИ в учебной, научной, административной и управленческой деятельности | J195: Организация/исполнитель по документу | K195: Требование/мероприятие применимо к ОВПО | L195: Прямая или совместная | W195: Сверено с первоисточником; формулировка сокращена без изменения содержания
A196: 194 | B196: M074 | C196: Наука | D196: Мероприятие | E196: Дипломные работы и диссертации в формате стартап-проектов по ИИ | F196: План по ИИ.pdf | G196: D06 | H196: Пункт 1.5; строка определяется по формулировке «Дипломные работы и диссертации в формате стартап-проектов по ИИ» | I196: Дипломные работы и диссертации в формате стартап-проектов по ИИ | J196: Организация/исполнитель по документу | K196: Требование/мероприятие применимо к ОВПО | L196: Прямая или совместная | W196: Сверено с первоисточником; формулировка сокращена без изменения содержания
A197: 195 | B197: M084 | C197: Наука | D197: Мероприятие | E197: Создание исследовательских центров, лабораторий и кафедр по ИИ | F197: План по ИИ.pdf | G197: D06 | H197: Пункт 3.4; строка определяется по формулировке «Создание исследовательских центров, лабораторий и кафедр по ИИ» | I197: Создание исследовательских центров, лабораторий и кафедр по ИИ | J197: Организация/исполнитель по документу | K197: Требование/мероприятие применимо к ОВПО | L197: Прямая или совместная | W197: Сверено с первоисточником; формулировка сокращена без изменения содержания
A198: 196 | B198: M088 | C198: Наука | D198: Мероприятие | E198: Научные конференции, выставки и семинары по ИИ | F198: План по ИИ.pdf | G198: D06 | H198: Пункт 3.8; строка определяется по формулировке «Научные конференции, выставки и семинары по ИИ» | I198: Научные конференции, выставки и семинары по ИИ | J198: Организация/исполнитель по документу | K198: Требование/мероприятие применимо к ОВПО | L198: Прямая или совместная | W198: Сверено с первоисточником; формулировка сокращена без изменения содержания
A199: 197 | B199: M099 | C199: Наука | D199: Мероприятие | E199: Анализ конкурсных процедур научных грантов и программно-целевого финансирования, включая цифровизацию, анонимность советов и международных экспертов | F199: Протокол Коллегии р0218095334.docx | G199: D09 | H199: Пункты 11–25, отобранное поручение 11; строка определяется по формулировке «Анализ конкурсных процедур научных грантов и программно-целевого финансирования, включая цифровизацию, анонимность советов и международных экспертов» | I199: Анализ конкурсных процедур научных грантов и программно-целевого финансирования, включая цифровизацию, анонимность советов и международных экспертов | J199: Организация/исполнитель по документу | K199: Применимость определяется по документу | L199: Требуется проверка | W199: Сверено с первоисточником: формулировка реестра не подтверждена дословно; требуется уточнение
A200: 198 | B200: K028 | C200: Социальное | D200: Показатель | E200: Доля населения, владеющего государственным языком | F200: Ключевые прказатели МНВО.docx | G200: D04 | H200: Таблица 3, показатель №27 («Доля населения, владеющего государственным языком»); значения 2024–2030 | I200: Доля населения, владеющего государственным языком | J200: Национальный | K200: Национальный/отраслевой показатель | L200: Требуется декомпозиция | M200: Указать после подтверждения индивидуального значения | N200: % | P200: 81.5 | Q200: 82 | R200: 82.5 | S200: 83 | T200: 83.5 | U200: 84 | V200: 84.5 | W200: Сверено с таблицей первоисточника
A201: 199 | B201: K029 | C201: Социальное | D201: Показатель | E201: Доля государственных служащих, владеющих государственным языком на уровне В2 по системе «КАЗТЕСТ» | F201: Ключевые прказатели МНВО.docx | G201: D04 | H201: Таблица 3, показатель №28 («Доля государственных служащих, владеющих государственным языком на уровне В2 по системе «К»); значения 2024–2030 | I201: Доля государственных служащих, владеющих государственным языком на уровне В2 по системе «КАЗТЕСТ» | J201: Национальный | K201: Национальный/отраслевой показатель | L201: Требуется декомпозиция | M201: Указать после подтверждения индивидуального значения | N201: % | P201: 40 | Q201: 45 | R201: 47 | S201: 48 | T201: 49 | U201: 50 | V201: 51 | W201: Сверено с таблицей первоисточника
A202: 200 | B202: K030 | C202: Социальное | D202: Показатель | E202: Доля упорядоченного терминологического фонда (с нарастающим итогом) | F202: Ключевые прказатели МНВО.docx | G202: D04 | H202: Таблица 3, показатель №29 («Доля упорядоченного терминологического фонда (с нарастающим итогом)»); значения 2024–2030 | I202: Доля упорядоченного терминологического фонда (с нарастающим итогом) | J202: Национальный | K202: Национальный/отраслевой показатель | L202: Требуется декомпозиция | M202: Указать после подтверждения индивидуального значения | N202: % | P202: 15 | Q202: 20 | R202: 25 | S202: 30 | T202: 35 | U202: 40 | V202: 45 | W202: Сверено с таблицей первоисточника
A203: 201 | B203: K031 | C203: Социальное | D203: Показатель | E203: Доля объема текстовой базы проекта «Национальный корпус казахского языка» (с нарастающим итогом) | F203: Ключевые прказатели МНВО.docx | G203: D04 | H203: Таблица 3, показатель №30 («Доля объема текстовой базы проекта «Национальный корпус казахского языка» (с нарастающим и»); значения 2024–2030 | I203: Доля объема текстовой базы проекта «Национальный корпус казахского языка» (с нарастающим итогом) | J203: Национальный | K203: Национальный/отраслевой показатель | L203: Требуется декомпозиция | M203: Указать после подтверждения индивидуального значения | N203: % | P203: 24.5 | Q203: 36 | R203: 48 | S203: 60 | T203: 72 | U203: 84 | V203: 96 | W203: Сверено с таблицей первоисточника
...

Sheet 02_Программа_развития
A1: Реестр KPI Программы развития, обеспечение Планом и факт за 2025 год
A2: № | B2: ID KPI | C2: Направление | D2: KPI Программы развития | E2: Единица | F2: 2023 | G2: 2024 | H2: План 2025 | I2: 2026 | J2: 2027 | K2: 2028 | L2: 2029 | M2: Ответственный по Программе | N2: Источник ID | O2: Точное место | P2: Связь с требованиями госорганов | Q2: ID внешних требований | R2: Количество мероприятий | S2: ID мероприятий | T2: Обеспечение Планом | U2: Факт 2025 | V2: Источник факта / расчёт | W2: Качество сопоставления факта | X2: Оценка 2025 | Y2: Отклонение от плана | Z2: Ограничение данных / аналитический комментарий
A3: 1 | B3: PRG001 | C3: Образование | D3: 1.1.1. Образовательные услуги в области высшего и послевузовского образования | E3: чел. | F3: 16151 | G3: 16700 | H3: 17400 | I3: 17700 | J3: 18100 | K3: 18300 | L3: 18500 | M3: Проректор по академической деятельности | N3: D20 | O3: Раздел 7 «Ключевые показатели деятельности», стр. 33–43; KPI 1.1.1; строка определяется по полному наименованию | P3: Прямая связь не установлена — собственная цель университета либо требуется дополнительное подтверждение | R3: 3 | S3: ACT001; ACT002; ACT003 | T3: Связанное мероприятие найдено; достаточность обеспечения оценивается по результату, сроку, ответственности и финансированию | U3: 20925 | V3: Отчёт о результатах деятельности за 2025 год, раздел 1; презентация, раздел 3: общий контингент — 20 925 человек | W3: Сопоставимо | X3: Цель перевыполнена | Y3: =IF(OR(H3="",U3=""),"",U3-H3) -> 3525 | Z3: В исходной таблице годы 2028 и 2029 продублированы техническими колонками; использованы первые значения для каждого года.
A4: 2 | B4: PRG002 | C4: Образование | D4: 1.1.2. Доля поступивших в ВУЗ, имеющих знаки «Алтын белгі», победителей международных олимпиад и конкурсов научных проектов последних трех лет, победителей президентской, республиканских олимпиад и конкурсов научных проектов текущего учебного года (награжденные дипломами первой, второй и третьей степени) от их общего количества | E4: % | F4: 8.6 | G4: 8.7 | H4: 8.8 | I4: 8.9 | J4: 9 | K4: 9.1 | L4: 9.2 | M4: Проректор по академической деятельности | N4: D20 | O4: Раздел 7 «Ключевые показатели деятельности», стр. 33–43; KPI 1.1.2; строка определяется по полному наименованию | P4: Прямая связь не установлена — собственная цель университета либо требуется дополнительное подтверждение | R4: 2 | S4: ACT004; ACT005 | T4: Связанное мероприятие найдено; достаточность обеспечения оценивается по результату, сроку, ответственности и финансированию | W4: Факт с формулой и единицей KPI в отчётах не найден | X4: Невозможно оценить — сопоставимый факт отсутствует | Z4: В исходной таблице годы 2028 и 2029 продублированы техническими колонками; использованы первые значения для каждого года.
A5: 3 | B5: PRG003 | C5: Образование | D5: 1.1.3. Доля ППС, прошедших повышение квалификации и зарубежную стажировку (в соответствии с коэффициентом для национальных университетов -1,5) | E5: % | F5: 50 | G5: 50 | H5: 50 | I5: 50 | J5: 50 | K5: 50 | L5: 50 | M5: Проректор по академической деятельности Проректор по стратегии и интернационализации | N5: D20 | O5: Раздел 7 «Ключевые показатели деятельности», стр. 33–43; KPI 1.1.3; строка определяется по полному наименованию | P5: Связь с внешними требованиями найдена | Q5: K102; Q009; Q041 | R5: 3 | S5: ACT006; ACT007; ACT008 | T5: Связанное мероприятие найдено; достаточность обеспечения оценивается по результату, сроку, ответственности и финансированию | W5: Факт с формулой и единицей KPI в отчётах не найден | X5: Невозможно оценить — сопоставимый факт отсутствует | Z5: В исходной таблице годы 2028 и 2029 продублированы техническими колонками; использованы первые значения для каждого года.
A6: 4 | B6: PRG004 | C6: Образование | D6: 1.1.4. Доля привлеченных работодателей, представителей бизнес-структур к учебному процессу от общего количества ППС | E6: % | F6: 16 | G6: 18 | H6: 20 | I6: 21 | J6: 23 | K6: 25 | L6: 27 | M6: Проректор по академическим вопросам | N6: D20 | O6: Раздел 7 «Ключевые показатели деятельности», стр. 33–43; KPI 1.1.4; строка определяется по полному наименованию | P6: Прямая связь не установлена — собственная цель университета либо требуется дополнительное подтверждение | R6: 3 | S6: ACT009; ACT010; ACT011 | T6: Связанное мероприятие найдено; достаточность обеспечения оценивается по результату, сроку, ответственности и финансированию | W6: Факт с формулой и единицей KPI в отчётах не найден | X6: Невозможно оценить — сопоставимый факт отсутствует | Z6: В исходной таблице годы 2028 и 2029 продублированы техническими колонками; использованы первые значения для каждого года.
A7: 5 | B7: PRG005 | C7: Образование | D7: 1.1.5. Прирост респондентов, привлеченных к участию в академических опросах | E7: чел. | F7: 400 | G7: 500 | H7: 600 | I7: 700 | J7: 800 | K7: 900 | L7: 1000 | M7: Проректор по стратегии и интернационализации Проректор по академической деятельности Директора институтов | N7: D20 | O7: Раздел 7 «Ключевые показатели деятельности», стр. 33–43; KPI 1.1.5; строка определяется по полному наименованию | P7: Прямая связь не установлена — собственная цель университета либо требуется дополнительное подтверждение | R7: 1 | S7: ACT012 | T7: Связанное мероприятие найдено; достаточность обеспечения оценивается по результату, сроку, ответственности и финансированию | W7: Факт с формулой и единицей KPI в отчётах не найден | X7: Невозможно оценить — сопоставимый факт отсутствует | Z7: В исходной таблице годы 2028 и 2029 продублированы техническими колонками; использованы первые значения для каждого года.
A8: 6 | B8: PRG006 | C8: Образование | D8: 1.1.6. Соотношение студентов и ППС | E8: ед. | F8: 16 | G8: 14 | H8: 14 | I8: 13 | J8: 13 | K8: 12 | L8: 12 | M8: Проректор по академической деятельности | N8: D20 | O8: Раздел 7 «Ключевые показатели деятельности», стр. 33–43; KPI 1.1.6; строка определяется по полному наименованию | P8: Связь с внешними требованиями найдена | Q8: K146 | R8: 0 | T8: Мероприятие для KPI не найдено | W8: Факт с формулой и единицей KPI в отчётах не найден | X8: Невозможно оценить — сопоставимый факт отсутствует | Z8: В отчёте есть численность студентов и ППС, но методика KPI не уточняет используемый состав ППС; расчёт без методики может быть некорректным. В исходной таблице годы 2028 и 2029 продублированы техническими колонками; использованы первые значения для каждого года.
A9: 7 | B9: PRG007 | C9: Образование | D9: 1.1.7. Количество штатных ППС | E9: чел. | F9: 859 | G9: 990 | H9: 1040 | I9: 1160 | J9: 1190 | K9: 1325 | L9: 1340 | M9: Руководитель аппарата ректора Проректор по академической деятельности | N9: D20 | O9: Раздел 7 «Ключевые показатели деятельности», стр. 33–43; KPI 1.1.7; строка определяется по полному наименованию | P9: Прямая связь не установлена — собственная цель университета либо требуется дополнительное подтверждение | R9: 1 | S9: ACT013 | T9: Связанное мероприятие найдено; достаточность обеспечения оценивается по результату, сроку, ответственности и финансированию | U9: 989 | V9: Отчёт о результатах деятельности за 2025 год, стр. 2–3; презентация, раздел 3: штатная численность ППС — 989 человек | W9: Сопоставимо | X9: Цель не достигнута | Y9: =IF(OR(H9="",U9=""),"",U9-H9) -> -51 | Z9: В исходной таблице годы 2028 и 2029 продублированы техническими колонками; использованы первые значения для каждого года.
A10: 8 | B10: PRG008 | C10: Образование | D10: 1.1.8. Остепенность ППС | E10: % | F10: 56 | G10: 56 | H10: 56 | I10: 56 | J10: 57 | K10: 58 | L10: 60 | M10: Руководитель аппарата ректора Проректор по академической деятельности | N10: D20 | O10: Раздел 7 «Ключевые показатели деятельности», стр. 33–43; KPI 1.1.8; строка определяется по полному наименованию | P10: Связь с внешними требованиями найдена | Q10: K145; Q043 | R10: 1 | S10: ACT014 | T10: Связанное мероприятие найдено; достаточность обеспечения оценивается по результату, сроку, ответственности и финансированию | U10: 57 | V10: Отчёт о результатах деятельности за 2025 год, стр. 3: ППС, имеющие учёную степень — 562 человека, или 57% | W10: Сопоставимо | X10: Цель перевыполнена | Y10: =IF(OR(H10="",U10=""),"",U10-H10) -> 1 | Z10: В исходной таблице годы 2028 и 2029 продублированы техническими колонками; использованы первые значения для каждого года.
A11: 9 | B11: PRG009 | C11: Образование | D11: 1.1.9. Доля документооборота в университете на государственном языке | E11: % | F11: 91 | G11: 91.5 | H11: 92 | I11: 92.5 | J11: 93 | K11: 93.5 | L11: 94 | M11: Руководитель аппарата ректора | N11: D20 | O11: Раздел 7 «Ключевые показатели деятельности», стр. 33–43; KPI 1.1.9; строка определяется по полному наименованию | P11: Прямая связь не установлена — собственная цель университета либо требуется дополнительное подтверждение | R11: 0 | T11: Мероприятие для KPI не найдено | W11: Факт с формулой и единицей KPI в отчётах не найден | X11: Невозможно оценить — сопоставимый факт отсутствует | Z11: В исходной таблице годы 2028 и 2029 продублированы техническими колонками; использованы первые значения для каждого года.
A12: 10 | B12: PRG010 | C12: Образование | D12: 1.2.1. Количество образовательных программ в рамках двудипломного образования с вузами-партнерами, в том числе из ТОП-700 рейтинга QS | E12: ед. | F12: 11 | G12: 11 | H12: 11 | I12: 12 | J12: 13 | K12: 13 | L12: 14 | M12: Проректор по стратегии и интернационализации Проректор по академической деятельности | N12: D20 | O12: Раздел 7 «Ключевые показатели деятельности», стр. 33–43; KPI 1.2.1; строка определяется по полному наименованию | P12: Связь с внешними требованиями найдена | Q12: K108 | R12: 3 | S12: ACT015; ACT016; ACT017 | T12: Связанное мероприятие найдено; достаточность обеспечения оценивается по результату, сроку, ответственности и финансированию | U12: 15 | V12: Отчёт о результатах деятельности за 2025 год, раздел 1; презентация, раздел 3: 15 двудипломных программ | W12: Сопоставимо | X12: Цель перевыполнена | Y12: =IF(OR(H12="",U12=""),"",U12-H12) -> 4 | Z12: В исходной таблице годы 2028 и 2029 продублированы техническими колонками; использованы первые значения для каждого года.
A13: 11 | B13: PRG011 | C13: Образование | D13: 1.2.2. Доля студентов, выехавших по программе академической мобильности за рубеж на срок не менее триместра, семестра, учебного года от общего количества студентов | E13: % | F13: 0.6 | H13: 0.68 | I13: 0.93 | J13: 1.05 | K13: 1.11 | L13: 1.23 | M13: Проректор по стратегии и интернационализации | N13: D20 | O13: Раздел 7 «Ключевые показатели деятельности», стр. 33–43; KPI 1.2.2; строка определяется по полному наименованию | P13: Прямая связь не установлена — собственная цель университета либо требуется дополнительное подтверждение | R13: 3 | S13: ACT018; ACT019; ACT020 | T13: Связанное мероприятие найдено; достаточность обеспечения оценивается по результату, сроку, ответственности и финансированию | U13: 1.52 | V13: Отчёт о результатах деятельности за 2025 год, раздел 3 «Интернационализация»: внешняя академическая мобильность — 280 человек, или 1,52% контингента бакалавриата | W13: Сопоставимо | X13: Цель перевыполнена | Y13: =IF(OR(H13="",U13=""),"",U13-H13) -> 0.84 | Z13: В исходной таблице годы 2028 и 2029 продублированы техническими колонками; использованы первые значения для каждого года.
A14: 12 | B14: PRG012 | C14: Образование | D14: 1.2.3. Доля ППС, преподающих на английском языке, от общего количества ППС | E14: % | F14: 18.7 | G14: 18.7 | H14: 18.8 | I14: 18.9 | J14: 19 | K14: 19.1 | L14: 19.2 | M14: Проректор по академической деятельности | N14: D20 | O14: Раздел 7 «Ключевые показатели деятельности», стр. 33–43; KPI 1.2.3; строка определяется по полному наименованию | P14: Прямая связь не установлена — собственная цель университета либо требуется дополнительное подтверждение | R14: 3 | S14: ACT021; ACT022; ACT023 | T14: Связанное мероприятие найдено; достаточность обеспечения оценивается по результату, сроку, ответственности и финансированию | U14: 21.12 | V14: Отчёт о результатах деятельности за 2025 год, раздел 3 «Интернационализация»: более 21,12% ППС ведут преподавание на английском языке | W14: Сопоставимо | X14: Цель перевыполнена | Y14: =IF(OR(H14="",U14=""),"",U14-H14) -> 2.32 | Z14: В исходной таблице годы 2028 и 2029 продублированы техническими колонками; использованы первые значения для каждого года.
A15: 13 | B15: PRG013 | C15: Образование | D15: 1.2.4. Доля иностранных студентов в вузе от общего количества студентов (в соответствии с коэффициентом для национальных университетов -1,5) | E15: % | F15: 3.5 | G15: 4.2 | H15: 4.3 | I15: 4.4 | J15: 4.6 | K15: 4.6 | L15: 5 | M15: Проректор по стратегии и интернационализации | N15: D20 | O15: Раздел 7 «Ключевые показатели деятельности», стр. 33–43; KPI 1.2.4; строка определяется по полному наименованию | P15: Связь с внешними требованиями найдена | Q15: K153 | R15: 3 | S15: ACT024; ACT025; ACT026 | T15: Связанное мероприятие найдено; достаточность обеспечения оценивается по результату, сроку, ответственности и финансированию | U15: 9.72 | V15: Отчёт о результатах деятельности за 2025 год, раздел 3 «Интернационализация»: доля иностранных студентов — 9,72%, 1 936 человек | W15: Сопоставимо | X15: Цель перевыполнена | Y15: =IF(OR(H15="",U15=""),"",U15-H15) -> 5.42 | Z15: Код уточнён по контрольному перечню 65 KPI: 1.2.4.
A16: 14 | B16: PRG014 | C16: Образование | D16: 1.2.5. Доля привлеченных зарубежных экспертов к преподавательской деятельности | E16: % | F16: 1.6 | G16: 1.7 | H16: 1.8 | I16: 1.9 | J16: 2 | K16: 2.1 | L16: 2.3 | M16: Проректор по академической деятельности Проректор по стратегии и интернационализации | N16: D20 | O16: Раздел 7 «Ключевые показатели деятельности», стр. 33–43; KPI 1.2.5; строка определяется по полному наименованию | P16: Прямая связь не установлена — собственная цель университета либо требуется дополнительное подтверждение | R16: 5 | S16: ACT027; ACT028; ACT029; ACT030; ACT031 | T16: Связанное мероприятие найдено; достаточность обеспечения оценивается по результату, сроку, ответственности и финансированию | W16: Факт с формулой и единицей KPI в отчётах не найден | X16: Невозможно оценить — сопоставимый факт отсутствует | Z16: В отчёте указано 51 зарубежный учёный, но не подтверждено, что все они привлечены именно к преподавательской деятельности. В исходной таблице годы 2028 и 2029 продублированы техническими колонками; использованы первые значения для каждого года.
A17: 15 | B17: PRG015 | C17: Образование | D17: 1.2.6. Количество международных образовательных программ | E17: ед. | F17: 2 | G17: 2 | H17: 2 | I17: 2 | J17: 3 | K17: 3 | L17: 3 | M17: Проректор по академической деятельности Проректор по стратегии и интернационализации | N17: D20 | O17: Раздел 7 «Ключевые показатели деятельности», стр. 33–43; KPI 1.2.6; строка определяется по полному наименованию | P17: Прямая связь не установлена — собственная цель университета либо требуется дополнительное подтверждение | R17: 2 | S17: ACT032; ACT033 | T17: Связанное мероприятие найдено; достаточность обеспечения оценивается по результату, сроку, ответственности и финансированию | U17: 10 | V17: Отчёт о результатах деятельности за 2025 год, раздел 3 «Интернационализация»: количество международных образовательных проектов — 10 | W17: Сопоставимо при подтверждении, что термин «проект» соответствует KPI «программа» | X17: Цель перевыполнена | Y17: =IF(OR(H17="",U17=""),"",U17-H17) -> 8 | Z17: В исходной таблице годы 2028 и 2029 продублированы техническими колонками; использованы первые значения для каждого года.
A18: 16 | B18: PRG016 | C18: Образование | D18: 1.2.7. Позиция вуза в рейтинге QS-WUR, в том числе ТОП-700 | E18: место | F18: 690 | G18: 680 | H18: 680 | I18: 670 | J18: 660 | K18: 650 | L18: 640 | M18: Проректор по стратегии и интернационализации | N18: D20 | O18: Раздел 7 «Ключевые показатели деятельности», стр. 33–43; KPI 1.2.7; строка определяется по полному наименованию | P18: Связь с внешними требованиями найдена | Q18: K002; K004; K105; K106 | R18: 1 | S18: ACT034 | T18: Связанное мероприятие найдено; достаточность обеспечения оценивается по результату, сроку, ответственности и финансированию | W18: Факт с формулой и единицей KPI в отчётах не найден | X18: Невозможно оценить — сопоставимый факт отсутствует | Z18: В исходной таблице годы 2028 и 2029 продублированы техническими колонками; использованы первые значения для каждого года.
A19: 17 | B19: PRG017 | C19: Образование | D19: 1.2.8. Количество программ, вошедших в QS BY SUBJECT, в том числе ТОП-100 | E19: ед. | F19: 2 | G19: 2 | H19: 2 | I19: 2 | J19: 3 | K19: 3 | L19: 3 | M19: Проректор по стратегии и интернационализации | N19: D20 | O19: Раздел 7 «Ключевые показатели деятельности», стр. 33–43; KPI 1.2.8; строка определяется по полному наименованию | P19: Прямая связь не установлена — собственная цель университета либо требуется дополнительное подтверждение | R19: 2 | S19: ACT035; ACT036 | T19: Связанное мероприятие найдено; достаточность обеспечения оценивается по результату, сроку, ответственности и финансированию | W19: Факт с формулой и единицей KPI в отчётах не найден | X19: Невозможно оценить — сопоставимый факт отсутствует | Z19: В исходной таблице годы 2028 и 2029 продублированы техническими колонками; использованы первые значения для каждого года.
A20: 18 | B20: PRG018 | C20: Образование | D20: 1.3.1. Доля образовательных программ, при реализации которых используются мировые цифровые библиотеки | E20: % | F20: 85 | G20: 86 | H20: 87 | I20: 88 | J20: 88 | K20: 89 | L20: 90 | M20: Проректор по академической деятельности | N20: D20 | O20: Раздел 7 «Ключевые показатели деятельности», стр. 33–43; KPI 1.3.1; строка определяется по полному наименованию | P20: Прямая связь не установлена — собственная цель университета либо требуется дополнительное подтверждение | R20: 3 | S20: ACT037; ACT038; ACT039 | T20: Связанное мероприятие найдено; достаточность обеспечения оценивается по результату, сроку, ответственности и финансированию | W20: Факт с формулой и единицей KPI в отчётах не найден | X20: Невозможно оценить — сопоставимый факт отсутствует | Z20: В исходной таблице годы 2028 и 2029 продублированы техническими колонками; использованы первые значения для каждого года.
A21: 19 | B21: PRG019 | C21: Образование | D21: 1.3.2. Доля студентов, использующих мировые цифровые библиотеки в учебном процессе | E21: % | F21: 80 | G21: 82 | H21: 84 | I21: 86 | J21: 88 | K21: 90 | L21: 92 | M21: Проректор по академической деятельности | N21: D20 | O21: Раздел 7 «Ключевые показатели деятельности», стр. 33–43; KPI 1.3.2; строка определяется по полному наименованию | P21: Прямая связь не установлена — собственная цель университета либо требуется дополнительное подтверждение | R21: 2 | S21: ACT040; ACT041 | T21: Связанное мероприятие найдено; достаточность обеспечения оценивается по результату, сроку, ответственности и финансированию | W21: Факт с формулой и единицей KPI в отчётах не найден | X21: Невозможно оценить — сопоставимый факт отсутствует | Z21: В исходной таблице годы 2028 и 2029 продублированы техническими колонками; использованы первые значения для каждого года.
A22: 20 | B22: PRG020 | C22: Образование | D22: 1.3.3. Количество образовательных программ, использующих онлайн-курсы, в том числе платформы Coursera | E22: ед. | F22: 51 | G22: 54 | H22: 57 | I22: 60 | J22: 62 | K22: 65 | L22: 67 | M22: Проректор по академической деятельности | N22: D20 | O22: Раздел 7 «Ключевые показатели деятельности», стр. 33–43; KPI 1.3.3; строка определяется по полному наименованию | P22: Прямая связь не установлена — собственная цель университета либо требуется дополнительное подтверждение | R22: 2 | S22: ACT042; ACT043 | T22: Связанное мероприятие найдено; достаточность обеспечения оценивается по результату, сроку, ответственности и финансированию | W22: Факт с формулой и единицей KPI в отчётах не найден | X22: Невозможно оценить — сопоставимый факт отсутствует | Z22: В отчёте указаны 2 собственных MOOC на Coursera, но KPI измеряет количество образовательных программ, использующих онлайн-курсы. В исходной таблице годы 2028 и 2029 продублированы техническими колонками; использованы первые значения для каждого года.
A23: 21 | B23: PRG021 | C23: Образование | D23: 1.3.4. Доля обучающихся, прошедших онлайн обучение, в том числе на платформе Coursera | E23: % | F23: 9 | G23: 10 | H23: 11 | I23: 12 | J23: 13 | K23: 14 | L23: 15 | M23: Проректор по академической деятельности | N23: D20 | O23: Раздел 7 «Ключевые показатели деятельности», стр. 33–43; KPI 1.3.4; строка определяется по полному наименованию | P23: Прямая связь не установлена — собственная цель университета либо требуется дополнительное подтверждение | R23: 0 | T23: Мероприятие для KPI не найдено | W23: Факт с формулой и единицей KPI в отчётах не найден | X23: Невозможно оценить — сопоставимый факт отсутствует | Z23: В исходной таблице годы 2028 и 2029 продублированы техническими колонками; использованы первые значения для каждого года.
A24: 22 | B24: PRG022 | C24: Образование | D24: 1.3.5 Доля обученных студентов латинской графике казахского языка от общего контингента обучающихся бакалавриата | E24: % | G24: 25 | H24: 35 | I24: 45 | J24: 55 | K24: 60 | L24: 70 | M24: Проректор по академической деятельности | N24: D20 | O24: Раздел 7 «Ключевые показатели деятельности», стр. 33–43; KPI 1.3.5; строка определяется по полному наименованию | P24: Прямая связь не установлена — собственная цель университета либо требуется дополнительное подтверждение | R24: 1 | S24: ACT137 | T24: Связанное мероприятие найдено; достаточность обеспечения оценивается по результату, сроку, ответственности и финансированию | W24: Факт с формулой и единицей KPI в отчётах не найден | X24: Невозможно оценить — сопоставимый факт отсутствует | Z24: В исходной таблице годы 2028 и 2029 продублированы техническими колонками; использованы первые значения для каждого года.
A25: 23 | B25: PRG023 | C25: Образование | D25: 2.1.1. Уровень созданных условий для инклюзивного образования в университете | E25: % | F25: 40 | G25: 42 | H25: 43 | I25: 44 | J25: 45 | K25: 45 | L25: 45 | M25: Проректор по академической деятельности | N25: D20 | O25: Раздел 7 «Ключевые показатели деятельности», стр. 33–43; KPI 2.1.1; строка определяется по полному наименованию | P25: Связь с внешними требованиями найдена | Q25: K006; K109; Q006 | R25: 2 | S25: ACT044; ACT045 | T25: Связанное мероприятие найдено; достаточность обеспечения оценивается по результату, сроку, ответственности и финансированию | W25: Факт с формулой и единицей KPI в отчётах не найден | X25: Невозможно оценить — сопоставимый факт отсутствует | Z25: В исходной таблице годы 2028 и 2029 продублированы техническими колонками; использованы первые значения для каждого года.
A26: 24 | B26: PRG024 | C26: Образование | D26: 2.1.2. Количество привлечённых к работе по развитию инклюзивного образования неправительственных организаций, общественных фондов и объединений | E26: ед. | F26: 3 | G26: 3 | H26: 3 | I26: 3 | J26: 3 | K26: 3 | L26: 3 | M26: Проректор по академической деятельности; директор Института педагогики и психологии | N26: D20 | O26: Раздел 7 «Ключевые показатели деятельности», стр. 33–43; KPI 2.1.2; строка определяется по полному наименованию | P26: Прямая связь не установлена — собственная цель университета либо требуется дополнительное подтверждение | R26: 1 | S26: ACT046 | T26: Связанное мероприятие найдено; достаточность обеспечения оценивается по результату, сроку, ответственности и финансированию | W26: Факт с формулой и единицей KPI в отчётах не найден | X26: Невозможно оценить — сопоставимый факт отсутствует | Z26: Показатель отсутствовал в предыдущей версии Excel; восстановлен по утверждённой Программе и контрольному перечню из 65 KPI.
A27: 25 | B27: PRG025 | C27: Образование | D27: 2.2.1. Количество слушателей по программам Серебряного университета | E27: чел. | G27: 10 | H27: 20 | I27: 25 | J27: 30 | K27: 35 | L27: 40 | M27: Проректор по академической деятельности | N27: D20 | O27: Раздел 7 «Ключевые показатели деятельности», стр. 33–43; KPI 2.2.1; строка определяется по полному наименованию | P27: Прямая связь не установлена — собственная цель университета либо требуется дополнительное подтверждение | R27: 2 | S27: ACT047; ACT048 | T27: Связанное мероприятие найдено; достаточность обеспечения оценивается по результату, сроку, ответственности и финансированию | W27: Факт с формулой и единицей KPI в отчётах не найден | X27: Невозможно оценить — сопоставимый факт отсутствует | Z27: В презентации указано 236 слушателей Серебряного университета за два года; показатель 2025 года отдельно не выделен. В исходной таблице годы 2028 и 2029 продублированы техническими колонками; использованы первые значения для каждого года.
A28: 26 | B28: PRG026 | C28: Образование | D28: 2.2.2. Количество слушателей по программам неформального образования (кроме Серебряного университета) | E28: чел. | G28: 350 | H28: 350 | I28: 400 | J28: 400 | K28: 450 | L28: 500 | M28: Проректор по академической деятельности | N28: D20 | O28: Раздел 7 «Ключевые показатели деятельности», стр. 33–43; KPI 2.2.2; строка определяется по полному наименованию | P28: Прямая связь не установлена — собственная цель университета либо требуется дополнительное подтверждение | R28: 2 | S28: ACT049; ACT050 | T28: Связанное мероприятие найдено; достаточность обеспечения оценивается по результату, сроку, ответственности и финансированию | W28: Факт с формулой и единицей KPI в отчётах не найден | X28: Невозможно оценить — сопоставимый факт отсутствует | Z28: В исходной таблице годы 2028 и 2029 продублированы техническими колонками; использованы первые значения для каждого года.
A29: 27 | B29: PRG027 | C29: Образование | D29: 2.2.3. Количество слушателей по программам педагогической переподготовки | E29: чел. | F29: 100 | G29: 120 | H29: 130 | I29: 140 | J29: 150 | K29: 160 | L29: 170 | M29: Проректор по академической деятельности | N29: D20 | O29: Раздел 7 «Ключевые показатели деятельности», стр. 33–43; KPI 2.2.3; строка определяется по полному наименованию | P29: Прямая связь не установлена — собственная цель университета либо требуется дополнительное подтверждение | R29: 3 | S29: ACT051; ACT052; ACT053 | T29: Связанное мероприятие найдено; достаточность обеспечения оценивается по результату, сроку, ответственности и финансированию | W29: Факт с формулой и единицей KPI в отчётах не найден | X29: Невозможно оценить — сопоставимый факт отсутствует | Z29: В исходной таблице годы 2028 и 2029 продублированы техническими колонками; использованы первые значения для каждого года.
A30: 28 | B30: PRG028 | C30: Образование | D30: 2.3.1. Результаты трудоустройства выпускников в первый год после окончания вуза | E30: % | F30: 95 | G30: 95 | H30: 95 | I30: 95 | J30: 96 | K30: 96 | L30: 96 | M30: Проректор по академической деятельности | N30: D20 | O30: Раздел 7 «Ключевые показатели деятельности», стр. 33–43; KPI 2.3.1; строка определяется по полному наименованию | P30: Связь с внешними требованиями найдена | Q30: K008; K103; K107; Q019 | R30: 3 | S30: ACT054; ACT055; ACT056 | T30: Связанное мероприятие найдено; достаточность обеспечения оценивается по результату, сроку, ответственности и финансированию | U30: 95 | V30: Отчёт о результатах деятельности за 2025 год; презентация, раздел 3: трудоустройство выпускников в первый год — 95% | W30: Сопоставимо | X30: Цель достигнута | Y30: =IF(OR(H30="",U30=""),"",U30-H30) -> 0 | Z30: В исходной таблице годы 2028 и 2029 продублированы техническими колонками; использованы первые значения для каждого года.
A31: 29 | B31: PRG029 | C31: Образование | D31: 2.3.2. Прирост респондентов, привлеченных к участию в репутационных опросах работодателей | E31: чел. | F31: 250 | G31: 300 | H31: 350 | I31: 400 | J31: 450 | K31: 500 | L31: 550 | M31: Проректор по академической деятельности Директора институтов | N31: D20 | O31: Раздел 7 «Ключевые показатели деятельности», стр. 33–43; KPI 2.3.2; строка определяется по полному наименованию | P31: Прямая связь не установлена — собственная цель университета либо требуется дополнительное подтверждение | R31: 1 | S31: ACT057 | T31: Связанное мероприятие найдено; достаточность обеспечения оценивается по результату, сроку, ответственности и финансированию | W31: Факт с формулой и единицей KPI в отчётах не найден | X31: Невозможно оценить — сопоставимый факт отсутствует | Z31: В исходной таблице годы 2028 и 2029 продублированы техническими колонками; использованы первые значения для каждого года.
A32: 30 | B32: PRG030 | C32: Образование | D32: 2.3.3. Степень удовлетворенности обучающихся качеством образовательных услуг и образовательной экосистемой | E32: % | F32: 70 | G32: 71 | H32: 72 | I32: 75 | J32: 76 | K32: 78 | L32: 80 | M32: Офис институциональной эффективности | N32: D20 | O32: Раздел 7 «Ключевые показатели деятельности», стр. 33–43; KPI 2.3.3; строка определяется по полному наименованию | P32: Прямая связь не установлена — собственная цель университета либо требуется дополнительное подтверждение | R32: 2 | S32: ACT058; ACT059 | T32: Связанное мероприятие найдено; достаточность обеспечения оценивается по результату, сроку, ответственности и финансированию | W32: Факт с формулой и единицей KPI в отчётах не найден | X32: Невозможно оценить — сопоставимый факт отсутствует | Z32: В исходной таблице годы 2028 и 2029 продублированы техническими колонками; использованы первые значения для каждого года.
A33: 31 | B33: PRG031 | C33: Наука | D33: 1.1.1. Количество статей и обзоров ППС, работников университета в высокорейтинговых изданиях Q1, Q2 Journal Citation Reports JCR, WoS, Scopus | E33: ед. | F33: 110 | G33: 115 | H33: 120 | I33: 125 | J33: 130 | K33: 135 | L33: 140 | M33: Проректор по исследовательской деятельности и инновации | N33: D20 | O33: Раздел 7 «Ключевые показатели деятельности», стр. 33–43; KPI 1.1.1; строка определяется по полному наименованию | P33: Связь с внешними требованиями найдена | Q33: K016; K111; K147; K148; K149 | R33: 2 | S33: ACT060; ACT061 | T33: Связанное мероприятие найдено; достаточность обеспечения оценивается по результату, сроку, ответственности и финансированию | W33: Факт с формулой и единицей KPI в отчётах не найден | X33: Невозможно оценить — сопоставимый факт отсутствует | Z33: В отчёте приведено общее количество публикаций Scopus и Web of Science, но не выделены статьи Q1–Q2 по формуле KPI. В исходной таблице годы 2028 и 2029 продублированы техническими колонками; использованы первые значения для каждого года.
A34: 32 | B34: PRG032 | C34: Наука | D34: 1.1.2. Цитируемость на одного работника | E34: % | F34: 1.2 | G34: 1.2 | H34: 1.2 | I34: 1.3 | J34: 1.3 | K34: 1.4 | L34: 1.5 | M34: Проректор по исследовательской деятельности и инновации | N34: D20 | O34: Раздел 7 «Ключевые показатели деятельности», стр. 33–43; KPI 1.1.2; строка определяется по полному наименованию | P34: Прямая связь не установлена — собственная цель университета либо требуется дополнительное подтверждение | R34: 1 | S34: ACT138 | T34: Связанное мероприятие найдено; достаточность обеспечения оценивается по результату, сроку, ответственности и финансированию | W34: Факт с формулой и единицей KPI в отчётах не найден | X34: Невозможно оценить — сопоставимый факт отсутствует | Z34: В исходной таблице годы 2028 и 2029 продублированы техническими колонками; использованы первые значения для каждого года.
A35: 33 | B35: PRG033 | C35: Наука | D35: 1.1.3. Цитируемость на одну публикацию | E35: % | F35: 0.4 | G35: 0.5 | H35: 0.6 | I35: 0.7 | J35: 0.8 | K35: 0.9 | L35: 1 | M35: Проректор по исследовательской деятельности и инновации | N35: D20 | O35: Раздел 7 «Ключевые показатели деятельности», стр. 33–43; KPI 1.1.3; строка определяется по полному наименованию | P35: Прямая связь не установлена — собственная цель университета либо требуется дополнительное подтверждение | R35: 1 | S35: ACT139 | T35: Связанное мероприятие найдено; достаточность обеспечения оценивается по результату, сроку, ответственности и финансированию | W35: Факт с формулой и единицей KPI в отчётах не найден | X35: Невозможно оценить — сопоставимый факт отсутствует | Z35: В исходной таблице годы 2028 и 2029 продублированы техническими колонками; использованы первые значения для каждого года.
A36: 34 | B36: PRG034 | C36: Наука | D36: 1.1.4. Международная исследовательская сеть: коллаборации (соавторство) с зарубежными партнерами | E36: ед. | F36: 72 | G36: 74 | H36: 76 | I36: 80 | J36: 82 | K36: 84 | L36: 86 | M36: Проректор по исследовательской деятельности и инновации | N36: D20 | O36: Раздел 7 «Ключевые показатели деятельности», стр. 33–43; KPI 1.1.4; строка определяется по полному наименованию | P36: Связь с внешними требованиями найдена | Q36: K154 | R36: 1 | S36: ACT140 | T36: Связанное мероприятие найдено; достаточность обеспечения оценивается по результату, сроку, ответственности и финансированию | W36: Факт с формулой и единицей KPI в отчётах не найден | X36: Невозможно оценить — сопоставимый факт отсутствует | Z36: В исходной таблице годы 2028 и 2029 продублированы техническими колонками; использованы первые значения для каждого года.
A37: 35 | B37: PRG035 | C37: Наука | D37: 1.1.5. Количество публикаций в области ЦУР в Scopus и Web of Science | E37: ед. | F37: 24 | G37: 25 | H37: 26 | I37: 27 | J37: 28 | K37: 29 | L37: 30 | M37: Проректор по исследовательской деятельности и инновации | N37: D20 | O37: Раздел 7 «Ключевые показатели деятельности», стр. 33–43; KPI 1.1.5; строка определяется по полному наименованию | P37: Прямая связь не установлена — собственная цель университета либо требуется дополнительное подтверждение | R37: 1 | S37: ACT141 | T37: Связанное мероприятие найдено; достаточность обеспечения оценивается по результату, сроку, ответственности и финансированию | U37: 190 | V37: Отчёт о результатах деятельности за 2025 год, раздел 2: 190 публикаций по ЦУР в Scopus и Web of Science | W37: Сопоставимо | X37: Цель перевыполнена | Y37: =IF(OR(H37="",U37=""),"",U37-H37) -> 164 | Z37: В исходной таблице годы 2028 и 2029 продублированы техническими колонками; использованы первые значения для каждого года.
A38: 36 | B38: PRG036 | C38: Наука | D38: 1.2.1. Доля ППС занимающейся научно-исследовательской работой (в соответствии с коэффициентом для национальных университетов -1,5) | E38: % | F38: 62 | G38: 62.5 | H38: 63 | I38: 63.5 | J38: 64 | K38: 64.5 | L38: 65 | M38: Проректор по исследовательской деятельности и инновации | N38: D20 | O38: Раздел 7 «Ключевые показатели деятельности», стр. 33–43; KPI 1.2.1; строка определяется по полному наименованию | P38: Прямая связь не установлена — собственная цель университета либо требуется дополнительное подтверждение | R38: 2 | S38: ACT062; ACT063 | T38: Связанное мероприятие найдено; достаточность обеспечения оценивается по результату, сроку, ответственности и финансированию | W38: Факт с формулой и единицей KPI в отчётах не найден | X38: Невозможно оценить — сопоставимый факт отсутствует | Z38: В исходной таблице годы 2028 и 2029 продублированы техническими колонками; использованы первые значения для каждого года.
A39: 37 | B39: PRG037 | C39: Наука | D39: 1.2.2. Доля ППС, принявших участие в международных научных проектах | E39: % | F39: 0.5 | G39: 0.6 | H39: 0.7 | I39: 0.8 | J39: 0.9 | K39: 1 | L39: 1.5 | M39: Проректор по исследовательской деятельности и инновации | N39: D20 | O39: Раздел 7 «Ключевые показатели деятельности», стр. 33–43; KPI 1.2.2; строка определяется по полному наименованию | P39: Прямая связь не установлена — собственная цель университета либо требуется дополнительное подтверждение | R39: 1 | S39: ACT064 | T39: Связанное мероприятие найдено; достаточность обеспечения оценивается по результату, сроку, ответственности и финансированию | W39: Факт с формулой и единицей KPI в отчётах не найден | X39: Невозможно оценить — сопоставимый факт отсутствует | Z39: В исходной таблице годы 2028 и 2029 продублированы техническими колонками; использованы первые значения для каждого года.
A40: 38 | B40: PRG038 | C40: Наука | D40: 1.2.3. Создать пул постдокторантов и профессоров-исследователей – не менее 5% от общего состава ППС | E40: % | F40: 3 | G40: 3 | H40: 3 | I40: 4 | J40: 4.5 | K40: 4.7 | L40: 5 | M40: Проректор по исследовательской деятельности и инновации | N40: D20 | O40: Раздел 7 «Ключевые показатели деятельности», стр. 33–43; KPI 1.2.3; строка определяется по полному наименованию | P40: Прямая связь не установлена — собственная цель университета либо требуется дополнительное подтверждение | R40: 2 | S40: ACT065; ACT066 | T40: Связанное мероприятие найдено; достаточность обеспечения оценивается по результату, сроку, ответственности и финансированию | U40: 3.03 | V40: Отчёт о результатах деятельности за 2025 год, раздел 2: 21 постдокторант и 16 профессоров-исследователей; расчёт 37 / 1 219 ППС × 100 = 3,03% | W40: Расчётный факт; требуется подтвердить знаменатель по методике KPI | X40: Цель перевыполнена | Y40: =IF(OR(H40="",U40=""),"",U40-H40) -> 0.03 | Z40: В исходной таблице годы 2028 и 2029 продублированы техническими колонками; использованы первые значения для каждого года.
A41: 39 | B41: PRG039 | C41: Наука | D41: 1.2.4. Количество молодых ППС, занимающихся научно-исследовательской работой (в соответствии с коэффициентом для национальных университетов -1,5) | E41: чел. | F41: 60 | G41: 65 | H41: 68 | I41: 70 | J41: 73 | K41: 75 | L41: 80 | M41: Проректор по исследовательской деятельности и инновации | N41: D20 | O41: Раздел 7 «Ключевые показатели деятельности», стр. 33–43; KPI 1.2.4; строка определяется по полному наименованию | P41: Связь с внешними требованиями найдена | Q41: K026 | R41: 2 | S41: ACT067; ACT068 | T41: Связанное мероприятие найдено; достаточность обеспечения оценивается по результату, сроку, ответственности и финансированию | W41: Факт с формулой и единицей KPI в отчётах не найден | X41: Невозможно оценить — сопоставимый факт отсутствует | Z41: В исходной таблице годы 2028 и 2029 продублированы техническими колонками; использованы первые значения для каждого года.
A42: 40 | B42: PRG040 | C42: Наука | D42: 1.3.1. Доля полученных доходов от научной деятельности, инновационных разработок и коммерциализируемых проектов от общего дохода университета | E42: % | F42: 3 | G42: 3.1 | H42: 3.2 | I42: 3.3 | J42: 3.4 | K42: 3.5 | L42: 3.6 | M42: Проректор по исследовательской деятельности и инновации | N42: D20 | O42: Раздел 7 «Ключевые показатели деятельности», стр. 33–43; KPI 1.3.1; строка определяется по полному наименованию | P42: Связь с внешними требованиями найдена | Q42: K158 | R42: 2 | S42: ACT069; ACT142 | T42: Связанное мероприятие найдено; достаточность обеспечения оценивается по результату, сроку, ответственности и финансированию | U42: 9.5 | V42: Отчёт о результатах деятельности за 2025 год, раздел 2: доля доходов от научно-исследовательской деятельности — 9,5% общего бюджета | W42: Сопоставимо | X42: Цель перевыполнена | Y42: =IF(OR(H42="",U42=""),"",U42-H42) -> 6.3 | Z42: В исходной таблице годы 2028 и 2029 продублированы техническими колонками; использованы первые значения для каждого года.
A43: 41 | B43: PRG041 | C43: Наука | D43: 1.3.2. Доля ППС, участвующих в проектах за счет республиканского бюджета | E43: % | F43: 37 | G43: 38 | H43: 39 | I43: 40 | J43: 41 | K43: 42 | L43: 43 | M43: Проректор по исследовательской деятельности и инновации | N43: D20 | O43: Раздел 7 «Ключевые показатели деятельности», стр. 33–43; KPI 1.3.2; строка определяется по полному наименованию | P43: Связь с внешними требованиями найдена | Q43: Q022; Q030 | R43: 1 | S43: ACT070 | T43: Связанное мероприятие найдено; достаточность обеспечения оценивается по результату, сроку, ответственности и финансированию | W43: Факт с формулой и единицей KPI в отчётах не найден | X43: Невозможно оценить — сопоставимый факт отсутствует | Z43: В исходной таблице годы 2028 и 2029 продублированы техническими колонками; использованы первые значения для каждого года.
A44: 42 | B44: PRG042 | C44: Наука | D44: 1.3.3. Доля реализуемых международных научных проектов от общего количества научных проектов | E44: % | F44: 2.5 | G44: 2.5 | H44: 2.5 | I44: 4.7 | J44: 4.7 | K44: 6.6 | L44: 6.6 | M44: Проректор по исследовательской деятельности и инновации | N44: D20 | O44: Раздел 7 «Ключевые показатели деятельности», стр. 33–43; KPI 1.3.3; строка определяется по полному наименованию | P44: Прямая связь не установлена — собственная цель университета либо требуется дополнительное подтверждение | R44: 1 | S44: ACT071 | T44: Связанное мероприятие найдено; достаточность обеспечения оценивается по результату, сроку, ответственности и финансированию | U44: 8.77 | V44: Отчёт о результатах деятельности за 2025 год, раздел 2: 5 международных проектов из 57 научных проектов; расчёт 5 / 57 × 100 = 8,77% | W44: Расчётный факт; требуется подтвердить состав общего количества проектов | X44: Цель перевыполнена | Y44: =IF(OR(H44="",U44=""),"",U44-H44) -> 6.27 | Z44: В исходной таблице годы 2028 и 2029 продублированы техническими колонками; использованы первые значения для каждого года.
A45: 43 | B45: PRG043 | C45: Наука | D45: 1.3.4. Количество научных проектов и программ в рамках международной коллаборации на основе межправительственных соглашений | E45: ед. | F45: 0 | G45: 0 | H45: 1 | I45: 1 | J45: 1 | K45: 2 | L45: 2 | M45: Проректор по исследовательской деятельности и инновации | N45: D20 | O45: Раздел 7 «Ключевые показатели деятельности», стр. 33–43; KPI 1.3.4; строка определяется по полному наименованию | P45: Прямая связь не установлена — собственная цель университета либо требуется дополнительное подтверждение | R45: 1 | S45: ACT072 | T45: Связанное мероприятие найдено; достаточность обеспечения оценивается по результату, сроку, ответственности и финансированию | W45: Факт с формулой и единицей KPI в отчётах не найден | X45: Невозможно оценить — сопоставимый факт отсутствует | Z45: В исходной таблице годы 2028 и 2029 продублированы техническими колонками; использованы первые значения для каждого года.
A46: 44 | B46: PRG044 | C46: Наука | D46: 1.3.5. Количество патентов, полученных в рамках НИР, реализованных за счет государственного бюджета | E46: ед. | F46: 1 | G46: 1 | H46: 1 | I46: 2 | J46: 2 | K46: 2 | L46: 3 | M46: Проректор по исследовательской деятельности и инновации | N46: D20 | O46: Раздел 7 «Ключевые показатели деятельности», стр. 33–43; KPI 1.3.5; строка определяется по полному наименованию | P46: Связь с внешними требованиями найдена | Q46: K124; K150; K151 | R46: 1 | S46: ACT073 | T46: Связанное мероприятие найдено; достаточность обеспечения оценивается по результату, сроку, ответственности и финансированию | W46: Факт с формулой и единицей KPI в отчётах не найден | X46: Невозможно оценить — сопоставимый факт отсутствует | Z46: В отчёте указано 5 патентов, но не подтверждено, что они получены именно в рамках НИР за счёт государственного бюджета. В исходной таблице годы 2028 и 2029 продублированы техническими колонками; использованы первые значения для каждого года.
A47: 45 | B47: PRG045 | C47: Наука | D47: 1.3.6. Количество коммерциализируемых проектов научно-исследовательской деятельности | E47: ед. | F47: 1 | G47: 1 | H47: 2 | I47: 2 | J47: 2 | K47: 2 | L47: 3 | M47: Проректор по исследовательской деятельности и инновации | N47: D20 | O47: Раздел 7 «Ключевые показатели деятельности», стр. 33–43; KPI 1.3.6; строка определяется по полному наименованию | P47: Связь с внешними требованиями найдена | Q47: K021; K114; K122 | R47: 1 | S47: ACT074 | T47: Связанное мероприятие найдено; достаточность обеспечения оценивается по результату, сроку, ответственности и финансированию | U47: 1 | V47: Отчёт о результатах деятельности за 2025 год, раздел 2: 1 проект коммерциализации на сумму 52,5 млн тенге | W47: Сопоставимо | X47: Цель не достигнута | Y47: =IF(OR(H47="",U47=""),"",U47-H47) -> -1 | Z47: В исходной таблице годы 2028 и 2029 продублированы техническими колонками; использованы первые значения для каждого года.
A48: 46 | B48: PRG046 | C48: Наука | D48: 1.3.7. Объем частного со-финансирования коммерциализируемых проектов РННТД и прикладного научного исследования (МИО, представители бизнеса) | E48: % | F48: 0.5 | G48: 0.5 | H48: 0.6 | I48: 0.6 | J48: 0.7 | K48: 0.7 | L48: 0.8 | M48: Проректор по исследовательской деятельности и инновации | N48: D20 | O48: Раздел 7 «Ключевые показатели деятельности», стр. 33–43; KPI 1.3.7; строка определяется по полному наименованию | P48: Связь с внешними требованиями найдена | Q48: K018; K115; K123 | R48: 1 | S48: ACT075 | T48: Связанное мероприятие найдено; достаточность обеспечения оценивается по результату, сроку, ответственности и финансированию | W48: Факт с формулой и единицей KPI в отчётах не найден | X48: Невозможно оценить — сопоставимый факт отсутствует | Z48: В исходной таблице годы 2028 и 2029 продублированы техническими колонками; использованы первые значения для каждого года.
A49: 47 | B49: PRG047 | C49: Наука | D49: 1.3.8. Доля стартап проектов, реализованных ППС и обучающимися от общего количества научных проектов | E49: % | F49: 0 | G49: 1 | H49: 1 | I49: 2 | J49: 2 | K49: 3 | L49: 3 | M49: Проректор по исследовательской деятельности и инновации | N49: D20 | O49: Раздел 7 «Ключевые показатели деятельности», стр. 33–43; KPI 1.3.8; строка определяется по полному наименованию | P49: Прямая связь не установлена — собственная цель университета либо требуется дополнительное подтверждение | R49: 2 | S49: ACT076; ACT077 | T49: Связанное мероприятие найдено; достаточность обеспечения оценивается по результату, сроку, ответственности и финансированию | W49: Факт с формулой и единицей KPI в отчётах не найден | X49: Невозможно оценить — сопоставимый факт отсутствует | Z49: В исходной таблице годы 2028 и 2029 продублированы техническими колонками; использованы первые значения для каждого года.
A50: 48 | B50: PRG048 | C50: Социальное развитие | D50: 1.1.1. Охват студентов услугами психологической службы, в том числе с ООП | E50: % | F50: 5.9 | G50: 6 | H50: 6.1 | I50: 6.2 | J50: 6.3 | K50: 6.4 | L50: 6.5 | M50: Проректор по социальному развитию | N50: D20 | O50: Раздел 7 «Ключевые показатели деятельности», стр. 33–43; KPI 1.1.1; строка определяется по полному наименованию | P50: Прямая связь не установлена — собственная цель университета либо требуется дополнительное подтверждение | R50: 3 | S50: ACT078; ACT079; ACT080 | T50: Связанное мероприятие найдено; достаточность обеспечения оценивается по результату, сроку, ответственности и финансированию | W50: Факт с формулой и единицей KPI в отчётах не найден | X50: Невозможно оценить — сопоставимый факт отсутствует | Z50: Приведены разные виды психологической помощи с возможным пересечением участников; уникальный охват не установлен. В исходной таблице годы 2028 и 2029 продублированы техническими колонками; использованы первые значения для каждого года.
A51: 49 | B51: PRG049 | C51: Социальное развитие | D51: 1.1.2. Охват обучающихся мерами социальной поддержки и материальной помощи | E51: % | F51: 7.3 | G51: 7.4 | H51: 7.5 | I51: 7.6 | J51: 7.7 | K51: 7.8 | L51: 7.9 | M51: Проректор по социальному развитию | N51: D20 | O51: Раздел 7 «Ключевые показатели деятельности», стр. 33–43; KPI 1.1.2; строка определяется по полному наименованию | P51: Прямая связь не установлена — собственная цель университета либо требуется дополнительное подтверждение | R51: 2 | S51: ACT143; ACT144 | T51: Связанное мероприятие найдено; достаточность обеспечения оценивается по результату, сроку, ответственности и финансированию | W51: Факт с формулой и единицей KPI в отчётах не найден | X51: Невозможно оценить — сопоставимый факт отсутствует | Z51: Указаны 493 получателя льгот по оплате обучения, но это не весь состав мер социальной поддержки и материальной помощи. В исходной таблице годы 2028 и 2029 продублированы техническими колонками; использованы первые значения для каждого года.
A52: 50 | B52: PRG050 | C52: Социальное развитие | D52: 1.2.1. Доля обучающихся вуза, вовлеченных в организованную общественную и волонтерскую деятельность | E52: % | F52: 11.5 | G52: 11.55 | H52: 11.6 | I52: 11.65 | J52: 11.7 | K52: 11.75 | L52: 11.8 | M52: Проректор по социальному развитию | N52: D20 | O52: Раздел 7 «Ключевые показатели деятельности», стр. 33–43; KPI 1.2.1; строка определяется по полному наименованию | P52: Связь с внешними требованиями найдена | Q52: K007; K110 | R52: 3 | S52: ACT081; ACT082; ACT083 | T52: Связанное мероприятие найдено; достаточность обеспечения оценивается по результату, сроку, ответственности и финансированию | U52: 42.77 | V52: Отчёт о результатах деятельности за 2025 год, раздел «Социальная работа»: волонтёрской деятельностью охвачено 8 950 студентов; расчёт 8 950 / 20 925 × 100 = 42,77% | W52: Расчётный факт; требуется подтвердить знаменатель и отсутствие повторного учёта | X52: Цель перевыполнена | Y52: =IF(OR(H52="",U52=""),"",U52-H52) -> 31.17 | Z52: В исходной таблице годы 2028 и 2029 продублированы техническими колонками; использованы первые значения для каждого года.
A53: 51 | B53: PRG051 | C53: Социальное развитие | D53: 1.2.2. Доля призеров олимпиад, конкурсов, турниров | E53: % | F53: 3.3 | G53: 3.4 | H53: 3.5 | I53: 3.6 | J53: 3.7 | K53: 3.8 | L53: 3.9 | M53: Проректор по академической деятельности Проректор по исследовательской деятельности и инновации Проректор по социальному развитию | N53: D20 | O53: Раздел 7 «Ключевые показатели деятельности», стр. 33–43; KPI 1.2.2; строка определяется по полному наименованию | P53: Прямая связь не установлена — собственная цель университета либо требуется дополнительное подтверждение | R53: 2 | S53: ACT145; ACT146 | T53: Связанное мероприятие найдено; достаточность обеспечения оценивается по результату, сроку, ответственности и финансированию | W53: Факт с формулой и единицей KPI в отчётах не найден | X53: Невозможно оценить — сопоставимый факт отсутствует | Z53: Указаны 612 победителей конкурсов и 258 спортивных призёров; возможны пересечения, поэтому долю нельзя надёжно рассчитать. В исходной таблице годы 2028 и 2029 продублированы техническими колонками; использованы первые значения для каждого года.
A54: 52 | B54: PRG052 | C54: Социальное развитие | D54: 1.2.3. Доля студентов занимающиеся творческой и спортивной деятельностью | E54: % | F54: 8.65 | G54: 8.7 | H54: 8.75 | I54: 8.8 | J54: 8.85 | K54: 8.9 | L54: 8.95 | M54: Проректор по социальному развитию | N54: D20 | O54: Раздел 7 «Ключевые показатели деятельности», стр. 33–43; KPI 1.2.3; строка определяется по полному наименованию | P54: Прямая связь не установлена — собственная цель университета либо требуется дополнительное подтверждение | R54: 7 | S54: ACT084; ACT085; ACT086; ACT087; ACT088; ACT089; ACT090 | T54: Связанное мероприятие найдено; достаточность обеспечения оценивается по результату, сроку, ответственности и финансированию | W54: Факт с формулой и единицей KPI в отчётах не найден | X54: Невозможно оценить — сопоставимый факт отсутствует | Z54: Отчёт содержит отдельные сведения об участии в спортивных мероприятиях, но не содержит уникальный охват творческой и спортивной деятельностью. В исходной таблице годы 2028 и 2029 продублированы техническими колонками; использованы первые значения для каждого года.
A55: 53 | B55: PRG053 | C55: Социальное развитие | D55: 1.2.4. Количество мероприятий и инициатив, способствующих раскрытию талантов, общению, коллаборации и формированию сообщества студентов | E55: ед. | F55: 70 | G55: 71 | H55: 72 | I55: 73 | J55: 74 | K55: 75 | L55: 76 | M55: Проректор по социальному развитию | N55: D20 | O55: Раздел 7 «Ключевые показатели деятельности», стр. 33–43; KPI 1.2.4; строка определяется по полному наименованию | P55: Прямая связь не установлена — собственная цель университета либо требуется дополнительное подтверждение | R55: 5 | S55: ACT091; ACT092; ACT093; ACT094; ACT095 | T55: Связанное мероприятие найдено; достаточность обеспечения оценивается по результату, сроку, ответственности и финансированию | W55: Факт с формулой и единицей KPI в отчётах не найден | X55: Невозможно оценить — сопоставимый факт отсутствует | Z55: В исходной таблице годы 2028 и 2029 продублированы техническими колонками; использованы первые значения для каждого года.
A56: 54 | B56: PRG054 | C56: Социальное развитие | D56: 1.3.1. Количество привлеченных студентов в Speaking Club | E56: чел. | F56: 50 | G56: 60 | H56: 70 | I56: 80 | J56: 90 | K56: 95 | L56: 100 | M56: Проректор по социальному развитию | N56: D20 | O56: Раздел 7 «Ключевые показатели деятельности», стр. 33–43; KPI 1.3.1; строка определяется по полному наименованию | P56: Прямая связь не установлена — собственная цель университета либо требуется дополнительное подтверждение | R56: 2 | S56: ACT096; ACT097 | T56: Связанное мероприятие найдено; достаточность обеспечения оценивается по результату, сроку, ответственности и финансированию | W56: Факт с формулой и единицей KPI в отчётах не найден | X56: Невозможно оценить — сопоставимый факт отсутствует | Z56: В исходной таблице годы 2028 и 2029 продублированы техническими колонками; использованы первые значения для каждого года.
A57: 55 | B57: PRG055 | C57: Социальное развитие | D57: 1.3.2. Количество привлеченных студентов в Honors College | E57: чел. | F57: 100 | G57: 105 | H57: 110 | I57: 115 | J57: 120 | K57: 125 | L57: 130 | M57: Проректор по социальному развитию | N57: D20 | O57: Раздел 7 «Ключевые показатели деятельности», стр. 33–43; KPI 1.3.2; строка определяется по полному наименованию | P57: Прямая связь не установлена — собственная цель университета либо требуется дополнительное подтверждение | R57: 3 | S57: ACT098; ACT099; ACT100 | T57: Связанное мероприятие найдено; достаточность обеспечения оценивается по результату, сроку, ответственности и финансированию | W57: Факт с формулой и единицей KPI в отчётах не найден | X57: Невозможно оценить — сопоставимый факт отсутствует | Z57: В исходной таблице годы 2028 и 2029 продублированы техническими колонками; использованы первые значения для каждого года.
A58: 56 | B58: PRG056 | C58: Социальное развитие | D58: 1.3.3. Количество студентов, принявших участие в туристических трекингах в РК | E58: чел. | F58: 1000 | G58: 1050 | H58: 1100 | I58: 1150 | J58: 1200 | K58: 1250 | L58: 1300 | M58: Проректор по социальному развитию | N58: D20 | O58: Раздел 7 «Ключевые показатели деятельности», стр. 33–43; KPI 1.3.3; строка определяется по полному наименованию | P58: Прямая связь не установлена — собственная цель университета либо требуется дополнительное подтверждение | R58: 1 | S58: ACT101 | T58: Связанное мероприятие найдено; достаточность обеспечения оценивается по результату, сроку, ответственности и финансированию | W58: Факт с формулой и единицей KPI в отчётах не найден | X58: Невозможно оценить — сопоставимый факт отсутствует | Z58: Факт проведения туристического трекинга подтверждён, но количество участников не указано. В исходной таблице годы 2028 и 2029 продублированы техническими колонками; использованы первые значения для каждого года.
A59: 57 | B59: PRG057 | C59: Инфраструктура и цифровизация | D59: 1.1.1. Количество койко-мест в студенческих общежитиях | E59: ед. | F59: 3060 | G59: 3242 | H59: 3242 | I59: 3242 | J59: 3242 | K59: 3242 | L59: 3242 | M59: Проректор по финансам и развитию инфраструктуры Проректор по социальному развитию | N59: D20 | O59: Раздел 7 «Ключевые показатели деятельности», стр. 33–43; KPI 1.1.1; строка определяется по полному наименованию | P59: Связь с внешними требованиями найдена | Q59: K009; Q011 | R59: 2 | S59: ACT102; ACT103 | T59: Связанное мероприятие найдено; достаточность обеспечения оценивается по результату, сроку, ответственности и финансированию | U59: 3652 | V59: Отчёт о результатах деятельности за 2025 год, раздел «Социальная работа»; презентация, раздел 7: 3 652 места в общежитиях | W59: Сопоставимо | X59: Цель перевыполнена | Y59: =IF(OR(H59="",U59=""),"",U59-H59) -> 410 | Z59: В исходной таблице годы 2028 и 2029 продублированы техническими колонками; использованы первые значения для каждого года.
A60: 58 | B60: PRG058 | C60: Инфраструктура и цифровизация | D60: 1.1.2. Введенные в эксплуатацию пространства для студенческого отдыха и общения | E60: м2 | F60: 1050 | G60: 1100 | H60: 1150 | I60: 1200 | J60: 1250 | K60: 1250 | L60: 1300 | M60: Проректор по финансам и развитию инфраструктуры Проректор по социальному развитию | N60: D20 | O60: Раздел 7 «Ключевые показатели деятельности», стр. 33–43; KPI 1.1.2; строка определяется по полному наименованию | P60: Прямая связь не установлена — собственная цель университета либо требуется дополнительное подтверждение | R60: 0 | T60: Мероприятие для KPI не найдено | W60: Факт с формулой и единицей KPI в отчётах не найден | X60: Невозможно оценить — сопоставимый факт отсутствует | Z60: В исходной таблице годы 2028 и 2029 продублированы техническими колонками; использованы первые значения для каждого года.
A61: 59 | B61: PRG059 | C61: Инфраструктура и цифровизация | D61: 1.2.1. Доля привлеченных инвестиций на развитие вуза от общего дохода, в том числе в рамках эндаумент фонда (в соответствии с коэффициентом для национальных университетов -1,5) | E61: % | F61: 0.01 | G61: 0.01 | H61: 0.01 | I61: 0.01 | J61: 0.01 | K61: 0.01 | L61: 0.01 | M61: Руководитель аппарата ректора Проректор по финансам и развитию инфраструктуры | N61: D20 | O61: Раздел 7 «Ключевые показатели деятельности», стр. 33–43; KPI 1.2.1; строка определяется по полному наименованию | P61: Прямая связь не установлена — собственная цель университета либо требуется дополнительное подтверждение | R61: 4 | S61: ACT104; ACT105; ACT106; ACT107 | T61: Связанное мероприятие найдено; достаточность обеспечения оценивается по результату, сроку, ответственности и финансированию | W61: Факт с формулой и единицей KPI в отчётах не найден | X61: Невозможно оценить — сопоставимый факт отсутствует | Z61: Общий объём инвестиций и закупок не равен привлечённым инвестициям по формуле KPI. В исходной таблице годы 2028 и 2029 продублированы техническими колонками; использованы первые значения для каждого года.
A62: 60 | B62: PRG060 | C62: Инфраструктура и цифровизация | D62: 1.3.1. Доля финансовых средств, затраченных на обновление инфраструктуры и учебного и научного оборудования в общих расходах | E62: % | F62: 3 | G62: 3.2 | H62: 3.4 | I62: 3.5 | J62: 3.7 | K62: 3.7 | L62: 3.8 | M62: Проректор по финансам и развитию инфраструктуры | N62: D20 | O62: Раздел 7 «Ключевые показатели деятельности», стр. 33–43; KPI 1.3.1; строка определяется по полному наименованию | P62: Связь с внешними требованиями найдена | Q62: K024 | R62: 3 | S62: ACT108; ACT109; ACT110 | T62: Связанное мероприятие найдено; достаточность обеспечения оценивается по результату, сроку, ответственности и финансированию | W62: Факт с формулой и единицей KPI в отчётах не найден | X62: Невозможно оценить — сопоставимый факт отсутствует | Z62: Расходы на инвестиции и закупки шире расходов на обновление инфраструктуры и оборудования по формуле KPI. В исходной таблице годы 2028 и 2029 продублированы техническими колонками; использованы первые значения для каждого года.
A63: 61 | B63: PRG061 | C63: Инфраструктура и цифровизация | D63: 2.1. Обновление парка компьютерного и периферийного оборудования | E63: ед. | F63: 400 | G63: 350 | H63: 350 | I63: 350 | J63: 350 | K63: 350 | L63: 350 | M63: Проректор по академической деятельности | N63: D20 | O63: Раздел 7 «Ключевые показатели деятельности», стр. 33–43; KPI 2.1; строка определяется по полному наименованию | P63: Прямая связь не установлена — собственная цель университета либо требуется дополнительное подтверждение | R63: 10 | S63: ACT111; ACT112; ACT113; ACT114; ACT115; ACT116; ACT117; ACT118; ACT119; ACT120 | T63: Связанное мероприятие найдено; достаточность обеспечения оценивается по результату, сроку, ответственности и финансированию | U63: 399 | V63: Отчёт о результатах деятельности за 2025 год, раздел «Цифровизация»; презентация, раздел 8: 329 моноблоков, 36 ноутбуков и 34 монитора, всего 399 единиц | W63: Сопоставимо при подтверждении состава показателя | X63: Цель перевыполнена | Y63: =IF(OR(H63="",U63=""),"",U63-H63) -> 49 | Z63: В исходной таблице годы 2028 и 2029 продублированы техническими колонками; использованы первые значения для каждого года.
A64: 62 | B64: PRG062 | C64: Инфраструктура и цифровизация | D64: 2.2. Увеличение пропускной способности Интернет | E64: Мбит/с | F64: 1200 | G64: 1300 | H64: 1500 | I64: 1600 | J64: 1700 | K64: 1700 | L64: 1800 | M64: Проректор по академической деятельности | N64: D20 | O64: Раздел 7 «Ключевые показатели деятельности», стр. 33–43; KPI 2.2; строка определяется по полному наименованию | P64: Связь с внешними требованиями найдена | Q64: Q035 | R64: 4 | S64: ACT121; ACT122; ACT123; ACT124 | T64: Связанное мероприятие найдено; достаточность обеспечения оценивается по результату, сроку, ответственности и финансированию | W64: Факт с формулой и единицей KPI в отчётах не найден | X64: Невозможно оценить — сопоставимый факт отсутствует | Z64: В исходной таблице годы 2028 и 2029 продублированы техническими колонками; использованы первые значения для каждого года.
A65: 63 | B65: PRG063 | C65: Инфраструктура и цифровизация | D65: 2.3. Увеличения зоны покрытия Wi-Fi | E65: % | F65: 75 | G65: 80 | H65: 85 | I65: 90 | J65: 95 | K65: 95 | L65: 100 | M65: Проректор по академической деятельности | N65: D20 | O65: Раздел 7 «Ключевые показатели деятельности», стр. 33–43; KPI 2.3; строка определяется по полному наименованию | P65: Прямая связь не установлена — собственная цель университета либо требуется дополнительное подтверждение | R65: 4 | S65: ACT125; ACT126; ACT127; ACT128 | T65: Связанное мероприятие найдено; достаточность обеспечения оценивается по результату, сроку, ответственности и финансированию | W65: Факт с формулой и единицей KPI в отчётах не найден | X65: Невозможно оценить — сопоставимый факт отсутствует | Z65: Расширение Wi‑Fi подтверждено описательно, но процент покрытия не указан. В исходной таблице годы 2028 и 2029 продублированы техническими колонками; использованы первые значения для каждого года.
A66: 64 | B66: PRG064 | C66: Инфраструктура и цифровизация | D66: 2.4. Приобретение интерактивных панелей | E66: ед. | F66: 49 | G66: 30 | H66: 30 | I66: 30 | J66: 30 | K66: 30 | L66: 30 | M66: Проректор по академической деятельности | N66: D20 | O66: Раздел 7 «Ключевые показатели деятельности», стр. 33–43; KPI 2.4; строка определяется по полному наименованию | P66: Прямая связь не установлена — собственная цель университета либо требуется дополнительное подтверждение | R66: 4 | S66: ACT129; ACT130; ACT131; ACT132 | T66: Связанное мероприятие найдено; достаточность обеспечения оценивается по результату, сроку, ответственности и финансированию | U66: 33 | V66: Отчёт о результатах деятельности за 2025 год, раздел «Цифровизация»; презентация, раздел 8: 33 интерактивные доски | W66: Не полностью сопоставимо: KPI использует термин «панели», отчёт — «доски» | X66: Невозможно оценить без подтверждения сопоставимости | Y66: =IF(OR(H66="",U66=""),"",U66-H66) -> 3 | Z66: В исходной таблице годы 2028 и 2029 продублированы техническими колонками; использованы первые значения для каждого года.
A67: 65 | B67: PRG065 | C67: Инфраструктура и цифровизация | D67: 2.5. Приобретение камер видеонаблюдения | E67: ед. | F67: 92 | G67: 377 | M67: Проректор по академической деятельности | N67: D20 | O67: Раздел 7 «Ключевые показатели деятельности», стр. 33–43; KPI 2.5; строка определяется по полному наименованию | P67: Прямая связь не установлена — собственная цель университета либо требуется дополнительное подтверждение | R67: 4 | S67: ACT133; ACT134; ACT135; ACT136 | T67: Связанное мероприятие найдено; достаточность обеспечения оценивается по результату, сроку, ответственности и финансированию | W67: Факт с формулой и единицей KPI в отчётах не найден | X67: Невозможно оценить — сопоставимый факт отсутствует | Z67: Модернизация видеонаблюдения описана, но количество приобретённых камер не приведено. В исходной таблице годы 2028 и 2029 продублированы техническими колонками; использованы первые значения для каждого года.

Sheet 03_План_мероприятий
A1: Реестр Плана мероприятий по реализации Программы развития
A2: ID мероприятия | B2: № направления | C2: Направление | D2: Код связанного KPI | E2: Мероприятие | F2: Срок / периодичность | G2: Форма завершения | H2: Измеримый результат 2023 | I2: Измеримый результат 2024 | J2: Измеримый результат 2025 | K2: Измеримый результат 2026 | L2: Измеримый результат 2027 | M2: Измеримый результат 2028 | N2: Измеримый результат 2029 | O2: Ответственный | P2: Финансирование | Q2: Источник финансирования | R2: Источник ID | S2: Источник / цитата | T2: Статус проверки
A3: ACT001 | B3: 1 | C3: Образование | D3: 1.1.1 | E3: Заключение соглашений с работодателями и социальными партнерами и выделение ими грантов на подготовку кадров | F3: ежегодно | G3: действующие договоры | H3: 17 | I3: 31 | J3: 41 | K3: 52 | L3: 60 | M3: 68 | N3: 75 | O3: Директор департамента по академическим вопросам | P3: Оценка невозможна: в Плане мероприятий отсутствует графа финансирования | Q3: Не указано в Плане мероприятий | R3: D21 | S3: План мероприятий, стр. 2; строка определяется по полному наименованию мероприятия | T3: Сверено с первоисточником
A4: ACT002 | B4: 1 | C4: Образование | D4: 1.1.1 | E4: Масштабирование педагогических классов в общеобразовательных школах г. Алматы и Алматинской области | F4: ежегодно | G4: количество педагогических классов | H4: 9 | I4: 20 | J4: 30 | K4: 40 | L4: 50 | M4: 60 | N4: 70 | O4: Директор департамента по академическим вопросам | P4: Оценка невозможна: в Плане мероприятий отсутствует графа финансирования | Q4: Не указано в Плане мероприятий | R4: D21 | S4: План мероприятий, стр. 2; строка определяется по полному наименованию мероприятия | T4: Сверено с первоисточником
A5: ACT003 | B5: 1 | C5: Образование | D5: 1.1.1 | E5: Осуществление взаимодействия с социальными партнерами и работодателями, организациями высшего и послевузовского образования по целевой подготовке докторов PhD | F5: ежегодно | G5: договоры | H5: 5 | I5: 5 | J5: 5 | K5: 6 | L5: 6 | M5: 6 | N5: 6 | O5: Директор департамента по академическим вопросам | P5: Оценка невозможна: в Плане мероприятий отсутствует графа финансирования | Q5: Не указано в Плане мероприятий | R5: D21 | S5: План мероприятий, стр. 2; строка определяется по полному наименованию мероприятия | T5: Сверено с первоисточником
A6: ACT004 | B6: 1 | C6: Образование | D6: 1.1.2 | E6: Активизация профориентационной работы, организация и проведение на базе университета, школ, лицеев и колледжей олимпиад, творческих конкурсов для отбора талантливой молодежи | F6: Не указано в строке источника | G6: количество олимпиад и конкурсов | H6: 1 | I6: 2 | J6: 2 | K6: 2 | L6: 2 | M6: 2 | N6: 2 | O6: Директор департамента по академическим вопросам | P6: Оценка невозможна: в Плане мероприятий отсутствует графа финансирования | Q6: Не указано в Плане мероприятий | R6: D21 | S6: План мероприятий, стр. 3; строка определяется по полному наименованию мероприятия | T6: Сверено с первоисточником
A7: ACT005 | B7: 1 | C7: Образование | D7: 1.1.2 | E7: Постоянное проведение мероприятий, популяризирующих педагогические профессии | F7: Не указано в строке источника | G7: Не указано в строке источника | O7: Директор департамента по академическим вопросам | P7: Оценка невозможна: в Плане мероприятий отсутствует графа финансирования | Q7: Не указано в Плане мероприятий | R7: D21 | S7: План мероприятий, стр. 3; строка определяется по полному наименованию мероприятия | T7: Сверено с первоисточником
A8: ACT006 | B8: 1 | C8: Образование | D8: 1.1.3 | E8: Установление партнерства с вузами, входящих в список рекомендуемых университетов, по программе “500 ученых” международной стипендиальной программы “Болашак” | F8: ежегодно | G8: договоры | H8: 8 | I8: 9 | J8: 9 | K8: 9 | L8: 10 | M8: 10 | N8: 10 | O8: Директор департамента международного сотрудничества | P8: Оценка невозможна: в Плане мероприятий отсутствует графа финансирования | Q8: Не указано в Плане мероприятий | R8: D21 | S8: План мероприятий, стр. 3; строка определяется по полному наименованию мероприятия | T8: Сверено с первоисточником
A9: ACT007 | B9: 1 | C9: Образование | D9: 1.1.3 | E9: Организация курсов повышения квалификации в формате Зимней и Летней школ, на базе ЦПМ | F9: Не указано в строке источника | G9: количество курсов | H9: 4 | I9: 4 | J9: 4 | K9: 4 | L9: 4 | M9: 4 | N9: 4 | O9: Директор департамента по проектированию образовательных программ | P9: Оценка невозможна: в Плане мероприятий отсутствует графа финансирования | Q9: Не указано в Плане мероприятий | R9: D21 | S9: План мероприятий, стр. 3; строка определяется по полному наименованию мероприятия | T9: Сверено с первоисточником
A10: ACT008 | B10: 1 | C10: Образование | D10: 1.1.3 | E10: Заключение договоров с зарубежными образовательными организациями по сотрудничеству и взаимообмена в области стажировок и повышения квалификации | F10: ежегодно | G10: 144 действующие договоры | H10: 148 | I10: 150 | J10: 154 | K10: 160 | L10: 165 | M10: 168 | O10: Директор департамента по международному сотрудничеству | P10: Оценка невозможна: в Плане мероприятий отсутствует графа финансирования | Q10: Не указано в Плане мероприятий | R10: D21 | S10: План мероприятий, стр. 4; строка определяется по полному наименованию мероприятия | T10: Сверено с первоисточником
A11: ACT009 | B11: 1 | C11: Образование | D11: 1.1.4 | E11: Осуществление взаимодействия со стейкхолдерами и работодателями по разработке учебных программ и проведению учебных занятий | F11: ежегодно | G11: действующие договоры, меморандумы | H11: 77 | I11: 80 | J11: 87 | K11: 92 | L11: 98 107 | M11: 115 | O11: Директор департамента по академическим вопросам | P11: Оценка невозможна: в Плане мероприятий отсутствует графа финансирования | Q11: Не указано в Плане мероприятий | R11: D21 | S11: План мероприятий, стр. 4; строка определяется по полному наименованию мероприятия | T11: Сверено с первоисточником
A12: ACT010 | B12: 1 | C12: Образование | D12: 1.1.4 | E12: Дальнейшее развитие дуального обучения, в том числе и в магистратуре | F12: ежегодно | G12: образовательные программы, договоры | H12: 1 | I12: 3 | J12: 7 | K12: 9 | L12: 12 | M12: 17 | N12: 22 | O12: Директор департамента по академическим вопросам | P12: Оценка невозможна: в Плане мероприятий отсутствует графа финансирования | Q12: Не указано в Плане мероприятий | R12: D21 | S12: План мероприятий, стр. 4; строка определяется по полному наименованию мероприятия | T12: Сверено с первоисточником
A13: ACT011 | B13: 1 | C13: Образование | D13: 1.1.4 | E13: Взаимодействие с сообществом работодателей по вопросам оценки квалификации выпускников | F13: ежегодно | G13: действующие договоры, меморандумы | H13: 3 | I13: 5 | J13: 7 | K13: 11 | L13: 18 | M13: 21 | N13: 23 | O13: Директор департамента по академическим вопросам Директор | P13: Оценка невозможна: в Плане мероприятий отсутствует графа финансирования | Q13: Не указано в Плане мероприятий | R13: D21 | S13: План мероприятий, стр. 4; строка определяется по полному наименованию мероприятия | T13: Сверено с первоисточником
A14: ACT012 | B14: 1 | C14: Образование | D14: 1.1.5 | E14: Подготовка списков респондентов, привлекаемых к участию в академических опросах | F14: ежегодно | G14: Не указано в строке источника | O14: Директора институтов | P14: Оценка невозможна: в Плане мероприятий отсутствует графа финансирования | Q14: Не указано в Плане мероприятий | R14: D21 | S14: План мероприятий, стр. 5; строка определяется по полному наименованию мероприятия | T14: Сверено с первоисточником
A15: ACT013 | B15: 1 | C15: Образование | D15: 1.1.7 | E15: Осуществление конкурсной чел. процедуры по замещению вакантных должностей профессорско- преподавательского состава | F15: ежегодно | G15: протокол конкурсной комиссии | O15: Руководитель управления кадровой политики | P15: Оценка невозможна: в Плане мероприятий отсутствует графа финансирования | Q15: Не указано в Плане мероприятий | R15: D21 | S15: План мероприятий, стр. 5; строка определяется по полному наименованию мероприятия | T15: Сверено с первоисточником
A16: ACT014 | B16: 1 | C16: Образование | D16: 1.1.8 | E16: Создание инструментов для чел. поддержки развития карьерных возможностей. | F16: в течение года | G16: положение приказ об ответственных лицах план мероприятий по продвижению развития карьерных возможностей | O16: Руководитель управления кадровой политики | P16: Оценка невозможна: в Плане мероприятий отсутствует графа финансирования | Q16: Не указано в Плане мероприятий | R16: D21 | S16: План мероприятий, стр. 6; строка определяется по полному наименованию мероприятия | T16: Сверено с первоисточником
A17: ACT015 | B17: 1 | C17: Образование | D17: 1.2.1 | E17: Установление сотрудничества и заключение договоров с вузами, входящими в ТОП-700 по рейтингу QS, по программе двойного диплома | F17: ежегодно | G17: подписанные договоры | I17: 2 | J17: 2 | K17: 2 | L17: 3 | M17: 3 | N17: 3 | O17: Директор департамента международного сотрудничества | P17: Оценка невозможна: в Плане мероприятий отсутствует графа финансирования | Q17: Не указано в Плане мероприятий | R17: D21 | S17: План мероприятий, стр. 6; строка определяется по полному наименованию мероприятия | T17: Сверено с первоисточником
A18: ACT016 | B18: 1 | C18: Образование | D18: 1.2.1 | E18: Выделение проездных грантов за счет университета для обучающихся по программе двойного диплома за счет университета | F18: ежегодно | G18: приказ о направлении студентов по академ. мобильности | H18: 20 | I18: 30 | J18: 40 | K18: 45 | L18: 50 | M18: 55 | N18: 60 | O18: Управление экономического планирования и анализа Директор департамента международного сотрудничества | P18: Оценка невозможна: в Плане мероприятий отсутствует графа финансирования | Q18: Не указано в Плане мероприятий | R18: D21 | S18: План мероприятий, стр. 7; строка определяется по полному наименованию мероприятия | T18: Сверено с первоисточником
A19: ACT017 | B19: 1 | C19: Образование | D19: 1.2.1 | E19: Проектирование и введение в Реестр | F19: ежегодно | G19: образовательные программы в реестре | K19: 1 | L19: 1 | N19: 1 | O19: Директор департамента проектирования образовательных программ | P19: Оценка невозможна: в Плане мероприятий отсутствует графа финансирования | Q19: Не указано в Плане мероприятий | R19: D21 | S19: План мероприятий, стр. 7; строка определяется по полному наименованию мероприятия | T19: Сверено с первоисточником
A20: ACT018 | B20: 1 | C20: Образование | D20: 1.2.2 | E20: Выделение проездных грантов студентам за счет средств университета | F20: ежегодно | G20: приказ о направлении студентов по академ мобильности | H20: 87 150 | I20: 180 | J20: 200 | K20: 220 | L20: 250 | M20: 300 | O20: Управление экономического планирования и анализа Директор департамента международного сотрудничества | P20: Оценка невозможна: в Плане мероприятий отсутствует графа финансирования | Q20: Не указано в Плане мероприятий | R20: D21 | S20: План мероприятий, стр. 7; строка определяется по полному наименованию мероприятия | T20: Сверено с первоисточником
A21: ACT019 | B21: 1 | C21: Образование | D21: 1.2.2 | E21: Выделение полных грантов студентам за счет средств университета | F21: ежегодно | G21: приказ о направлении студентов по академической мобильности | H21: 5 | I21: 20 | J21: 30 | K21: 40 | L21: 50 | M21: 60 | N21: 70 | O21: Управление экономического планирования и анализа Директор департамента международного сотрудничества | P21: Оценка невозможна: в Плане мероприятий отсутствует графа финансирования | Q21: Не указано в Плане мероприятий | R21: D21 | S21: План мероприятий, стр. 7; строка определяется по полному наименованию мероприятия | T21: Сверено с первоисточником
A22: ACT020 | B22: 1 | C22: Образование | D22: 1.2.2 | E22: Подача заявок на международные стипендиальные и грантовые программы путем диверсификации финансовых источников (Erasmus+, Orkhun, State Scholarships (Литва Словакия)) | F22: ежегодно | G22: отчет | I22: 12 | J22: 15 | K22: 20 | L22: 25 | M22: 30 | N22: 35 | O22: Директор департамента международного сотрудничества | P22: Оценка невозможна: в Плане мероприятий отсутствует графа финансирования | Q22: Не указано в Плане мероприятий | R22: D21 | S22: План мероприятий, стр. 8; строка определяется по полному наименованию мероприятия | T22: Сверено с первоисточником
A23: ACT021 | B23: 1 | C23: Образование | D23: 1.2.3 | E23: Организация языковых курсов для преподавателей и обучающихся университета на постоянной основе | F23: ежегодно | G23: кол-во курсов | H23: 2 | I23: 2 | J23: 3 | K23: 4 | L23: 4 | M23: 5 | N23: 5 | O23: Директор департамента по академическим вопросам Директор департамента проектирования образовательных программ | P23: Оценка невозможна: в Плане мероприятий отсутствует графа финансирования | Q23: Не указано в Плане мероприятий | R23: D21 | S23: План мероприятий, стр. 8; строка определяется по полному наименованию мероприятия | T23: Сверено с первоисточником
A24: ACT022 | B24: 1 | C24: Образование | D24: 1.2.3 | E24: Разработка и внедрение в учебный процесс новых образовательных программ на английском языке | F24: ежегодно | G24: образовательные программы | I24: 1 | K24: 1 | M24: 1 | O24: Директор департамента по академическим вопросам Директор департамента проектирования | P24: Оценка невозможна: в Плане мероприятий отсутствует графа финансирования | Q24: Не указано в Плане мероприятий | R24: D21 | S24: План мероприятий, стр. 8; строка определяется по полному наименованию мероприятия | T24: Сверено с первоисточником
A25: ACT023 | B25: 1 | C25: Образование | D25: 1.2.3 | E25: Проведение тренингов и обмен опытом преподавателей по полиязычному образованию | F25: ежегодно | G25: количество тренингов | H25: 2 | I25: 2 | J25: 3 | K25: 4 | L25: 4 | M25: 5 | N25: 5 | O25: Директор департамента по академическим вопросам Директор департамента проектирования образовательных программ | P25: Оценка невозможна: в Плане мероприятий отсутствует графа финансирования | Q25: Не указано в Плане мероприятий | R25: D21 | S25: План мероприятий, стр. 9; строка определяется по полному наименованию мероприятия | T25: Сверено с первоисточником
A26: ACT024 | B26: 1 | C26: Образование | D26: 1.2.4 | E26: Участие в международных выставках образования | F26: ежегодно | G26: отчет | H26: 2 | I26: 3 | J26: 3 | K26: 3 | L26: 3 | M26: 3 | N26: 3 | O26: Отдел маркетинга Директор департамента международного сотрудничества | P26: Оценка невозможна: в Плане мероприятий отсутствует графа финансирования | Q26: Не указано в Плане мероприятий | R26: D21 | S26: План мероприятий, стр. 9; строка определяется по полному наименованию мероприятия | T26: Сверено с первоисточником
A27: ACT025 | B27: 1 | C27: Образование | D27: 1.2.4 | E27: Предоставление чел. комфортного проживания в студенческих общежитиях | F27: ежегодно | G27: 100 отчет | H27: 150 | I27: 200 | J27: 250 | K27: 300 | L27: 350 | M27: 400 | O27: Департамент по воспитательной, социальной работе и молодежной политике Директор департамента международного сотрудничества | P27: Оценка невозможна: в Плане мероприятий отсутствует графа финансирования | Q27: Не указано в Плане мероприятий | R27: D21 | S27: План мероприятий, стр. 9; строка определяется по полному наименованию мероприятия | T27: Сверено с первоисточником
A28: ACT026 | B28: 1 | C28: Образование | D28: 1.2.4 | E28: Выделение стипендии и грантов для иностранных студентов | F28: Не указано в строке источника | G28: Не указано в строке источника | H28: 1 | I28: 2 | J28: 3 | K28: 4 | L28: 5 | M28: 5 | N28: 5 | O28: Проректор по финансам и развитию инфраструктуры | P28: Оценка невозможна: в Плане мероприятий отсутствует графа финансирования | Q28: Не указано в Плане мероприятий | R28: D21 | S28: План мероприятий, стр. 10; строка определяется по полному наименованию мероприятия | T28: Сверено с первоисточником
A29: ACT027 | B29: 1 | C29: Образование | D29: 1.2.5 | E29: Установление тесного партнерства между академическими институтами и конкретными факультетами/школами/инст итутами зарубежных партнеров с целью обеспечения непрерывной коммуникации и конкретизации сотрудничества | F29: ежегодно | G29: 144 действующие договоры, меморандумы | H29: 148 | I29: 150 | J29: 154 | K29: 160 | L29: 165 | M29: 168 | O29: Директор департамента международного сотрудничества | P29: Оценка невозможна: в Плане мероприятий отсутствует графа финансирования | Q29: Не указано в Плане мероприятий | R29: D21 | S29: План мероприятий, стр. 10; строка определяется по полному наименованию мероприятия | T29: Сверено с первоисточником
A30: ACT028 | B30: 1 | C30: Образование | D30: 1.2.5 | E30: Расширение программы стажировок и обменов для педагогов, предлагая возможность работать с зарубежными коллегами и получать опыт в международной среде | F30: ежегодно | G30: 144 действующие договоры, меморандумы | H30: 148 | I30: 150 | J30: 154 | K30: 160 | L30: 165 | M30: 168 | O30: Директор департамента международного сотрудничества Директор департамента по академическим вопросам | P30: Оценка невозможна: в Плане мероприятий отсутствует графа финансирования | Q30: Не указано в Плане мероприятий | R30: D21 | S30: План мероприятий, стр. 10; строка определяется по полному наименованию мероприятия | T30: Сверено с первоисточником
A31: ACT029 | B31: 1 | C31: Образование | D31: 1.2.5 | E31: Улучшение коммуникации и обмена информацией с зарубежными партнерами, с целью поддержания долгосрочных партнерских отношений и привлечения новых экспертов | F31: ежегодно | G31: действующие 144 договоры, меморандумы | H31: 148 | I31: 150 | J31: 154 | K31: 160 | L31: 165 | M31: 168 | O31: Директор департамента международного сотрудничества | P31: Оценка невозможна: в Плане мероприятий отсутствует графа финансирования | Q31: Не указано в Плане мероприятий | R31: D21 | S31: План мероприятий, стр. 10; строка определяется по полному наименованию мероприятия | T31: Сверено с первоисточником
A32: ACT030 | B32: 1 | C32: Образование | D32: 1.2.5 | E32: Выделение финансирования за счет средств тенге, университета учето НДС | F32: Не указано в строке источника | G32: 115 983 589 | H32: 279 075 200 | I32: 285 000 000 | J32: 285 000 000 | K32: 290 000 000 | L32: 290 000 000 | M32: 300 000 000 | O32: Управление экономического планирования и анализа Директор департамента международного сотрудничества | P32: Оценка невозможна: в Плане мероприятий отсутствует графа финансирования | Q32: Не указано в Плане мероприятий | R32: D21 | S32: План мероприятий, стр. 11; строка определяется по полному наименованию мероприятия | T32: Сверено с первоисточником
A33: ACT031 | B33: 1 | C33: Образование | D33: 1.2.5 | E33: Расширение связей с зарубежными партнерами для привлечения зарубежных экспертов из ведущих вузов | F33: Не указано в строке источника | G33: Не указано в строке источника | H33: 2 | I33: 2 | J33: 3 | K33: 3 | L33: 3 | M33: 4 | N33: 4 | O33: Директор департамента международного сотрудничества | P33: Оценка невозможна: в Плане мероприятий отсутствует графа финансирования | Q33: Не указано в Плане мероприятий | R33: D21 | S33: План мероприятий, стр. 11; строка определяется по полному наименованию мероприятия | T33: Сверено с первоисточником
A34: ACT032 | B34: 1 | C34: Образование | D34: 1.2.6 | E34: Подача конкурсных заявок в международные образовательные и стипендиальные программы (Erasmus+, Orhun, Government Scholarship Programs etc) | F34: ежегодно | G34: отчет | H34: 2 | I34: 2 | J34: 3 | K34: 4 | L34: 5 | M34: 6 | N34: 7 | O34: Директор департамента международного сотрудничества | P34: Оценка невозможна: в Плане мероприятий отсутствует графа финансирования | Q34: Не указано в Плане мероприятий | R34: D21 | S34: План мероприятий, стр. 11; строка определяется по полному наименованию мероприятия | T34: Сверено с первоисточником
A35: ACT033 | B35: 1 | C35: Образование | D35: 1.2.6 | E35: Заключение меж институциональных соглашений с вузами, входящих в ЕС. | F35: ежегодно | G35: подписанные договоры | H35: 2 | I35: 2 | J35: 2 | K35: 2 | L35: 2 | M35: 2 | N35: 2 | O35: Директор департамента международного сотрудничества | P35: Оценка невозможна: в Плане мероприятий отсутствует графа финансирования | Q35: Не указано в Плане мероприятий | R35: D21 | S35: План мероприятий, стр. 11; строка определяется по полному наименованию мероприятия | T35: Сверено с первоисточником
A36: ACT034 | B36: 1 | C36: Образование | D36: 1.2.7 | E36: Сбор, обработка информации по всем структурным подразделениям университета и ввод данных на онлайн портале в соответствии с методологией QS | F36: ежегодно | G36: 1 ссылка на сайт с данными | I36: 1 | J36: 1 | K36: 1 | L36: 1 | M36: 1 | N36: 1 | O36: Директор департамента стратегии | P36: Оценка невозможна: в Плане мероприятий отсутствует графа финансирования | Q36: Не указано в Плане мероприятий | R36: D21 | S36: План мероприятий, стр. 12; строка определяется по полному наименованию мероприятия | T36: Сверено с первоисточником
A37: ACT035 | B37: 1 | C37: Образование | D37: 1.2.8 | E37: Анализ предметных областей и образовательных программ университета на предмет участия в QS by Subject | F37: ежегодно | G37: 1 анализ | I37: 1 | J37: 1 | K37: 1 | L37: 1 | M37: 1 | N37: 1 | O37: Директора институтов Директор департамента стратегии | P37: Оценка невозможна: в Плане мероприятий отсутствует графа финансирования | Q37: Не указано в Плане мероприятий | R37: D21 | S37: План мероприятий, стр. 12; строка определяется по полному наименованию мероприятия | T37: Сверено с первоисточником
A38: ACT036 | B38: 1 | C38: Образование | D38: 1.2.8 | E38: Повышение осведомленности Департамента науки об интенсификации публикационной активности согласно методологии QS | F38: ежегодно | G38: 1 план | I38: 1 | J38: 1 | K38: 1 | L38: 1 | M38: 1 | N38: 1 | O38: Директор департамента стратегии | P38: Оценка невозможна: в Плане мероприятий отсутствует графа финансирования | Q38: Не указано в Плане мероприятий | R38: D21 | S38: План мероприятий, стр. 12; строка определяется по полному наименованию мероприятия | T38: Сверено с первоисточником
A39: ACT037 | B39: 1 | C39: Образование | D39: 1.3.1 | E39: Увеличение доли образовательных программ, при реализации которых используются мировые цифровые библиотеки | F39: ежегодно | G39: 120 образовательные программы | H39: 122 | I39: 125 | J39: 127 | K39: 130 | L39: 132 | M39: 135 | O39: Директор департамента проектирования образовательных программ Научная библиотека | P39: Оценка невозможна: в Плане мероприятий отсутствует графа финансирования | Q39: Не указано в Плане мероприятий | R39: D21 | S39: План мероприятий, стр. 13; строка определяется по полному наименованию мероприятия | T39: Сверено с первоисточником
A40: ACT038 | B40: 1 | C40: Образование | D40: 1.3.1 | E40: Использование ресурсов мировых цифровых библиотек в учебном процессе обучающихся PhD докторантуры и магистратуры на постоянной основе | F40: ежегодно | G40: 48272 посещения | H40: 49472 | I40: 50872 | J40: 52485 | K40: 54207 | L40: 56162 | M40: 58332 | O40: Директор департамента по академическим вопросам Научная библиотека | P40: Оценка невозможна: в Плане мероприятий отсутствует графа финансирования | Q40: Не указано в Плане мероприятий | R40: D21 | S40: План мероприятий, стр. 13; строка определяется по полному наименованию мероприятия | T40: Сверено с первоисточником
A41: ACT039 | B41: 1 | C41: Образование | D41: 1.3.1 | E41: Интегрирование онлайн- курсов платформы Coursera в учебные планы образовательных программ | F41: ежегодно | G41: образовательные программы | H41: 38 | I41: 38 | J41: 40 | K41: 41 | L41: 42 | M41: 43 | N41: 44 | O41: Директор департамента по академическим вопросам Директор департамента проектирования образовательных программ | P41: Оценка невозможна: в Плане мероприятий отсутствует графа финансирования | Q41: Не указано в Плане мероприятий | R41: D21 | S41: План мероприятий, стр. 13; строка определяется по полному наименованию мероприятия | T41: Сверено с первоисточником
A42: ACT040 | B42: 1 | C42: Образование | D42: 1.3.2 | E42: Создание более комфортных условий для работы пользователей и улучшение на этой основе информационно-библиотечного обеспечения качества образования | F42: ежегодно | G42: библиотечные ресурсы | H42: 17 | I42: 19 | J42: 21 | K42: 23 | L42: 25 | M42: 27 | N42: 29 | O42: Директор департамента по академическим вопросам; Директор департамента цифровизации образования; Научная библиотека | P42: Оценка невозможна: в Плане мероприятий отсутствует графа финансирования | Q42: Не указано в Плане мероприятий | R42: D21 | S42: План мероприятий, стр. 13; строка определяется по полному наименованию мероприятия | T42: Сверено с первоисточником
A43: ACT041 | B43: 1 | C43: Образование | D43: 1.3.2 | E43: Популяризация среди обучающихся образовательных платформ мировых цифровых библиотек | F43: ежегодно | G43: УМКД курса «платформам мировых цифровых библиотек» | H43: 9 | I43: 11 | J43: 13 | K43: 15 | L43: 17 | M43: 19 | N43: 21 | O43: Директор департамента по академическим вопросам Директор Научной библиотеки | P43: Оценка невозможна: в Плане мероприятий отсутствует графа финансирования | Q43: Не указано в Плане мероприятий | R43: D21 | S43: План мероприятий, стр. 14; строка определяется по полному наименованию мероприятия | T43: Сверено с первоисточником
A44: ACT042 | B44: 1 | C44: Образование | D44: 1.3.3 | E44: Разработка МООК по дисциплинам ООД, БД, ПД | F44: ежегодно | G44: количеств курсов | H44: 4 | I44: 14 | J44: 20 | K44: 25 | L44: 33 | M44: 38 | N44: 45 | O44: Директор департамента по академическим вопросам Директор департамента проектирования образовательных программ | P44: Оценка невозможна: в Плане мероприятий отсутствует графа финансирования | Q44: Не указано в Плане мероприятий | R44: D21 | S44: План мероприятий, стр. 14; строка определяется по полному наименованию мероприятия | T44: Сверено с первоисточником
A45: ACT043 | B45: 1 | C45: Образование | D45: 1.3.3 | E45: Разработка онлайн-курсов по профильным дисциплинам | F45: ежегодно | G45: количеств курсов | H45: 21 | I45: 24 | J45: 26 | K45: 29 | L45: 31 | M45: 34 | N45: 37 | O45: Не указано в строке источника | P45: Оценка невозможна: в Плане мероприятий отсутствует графа финансирования | Q45: Не указано в Плане мероприятий | R45: D21 | S45: План мероприятий, стр. 14; строка определяется по полному наименованию мероприятия | T45: Сверено с первоисточником
A46: ACT044 | B46: 1 | C46: Образование | D46: 2.1.1 | E46: Внедрение программ смешанного и онлайн обучения для студентов с | F46: ежегодно | G46: образовательные программы | I46: 1 | J46: 2 | K46: 3 | L46: 4 | M46: 5 | N46: 6 | O46: Директор департамента по академическим вопросам | P46: Оценка невозможна: в Плане мероприятий отсутствует графа финансирования | Q46: Не указано в Плане мероприятий | R46: D21 | S46: План мероприятий, стр. 15; строка определяется по полному наименованию мероприятия | T46: Сверено с первоисточником
A47: ACT045 | B47: 1 | C47: Образование | D47: 2.1.1 | E47: Открытие массовых онлайн курсов для студентов с особыми образовательными потребностями | F47: ежегодно | G47: МООК | I47: 4 | J47: 7 | K47: 9 | L47: 11 | M47: 15 | N47: 17 | O47: Директор департамента по академическим вопросам Директор департамента проектирования образовательных программ | P47: Оценка невозможна: в Плане мероприятий отсутствует графа финансирования | Q47: Не указано в Плане мероприятий | R47: D21 | S47: План мероприятий, стр. 16; строка определяется по полному наименованию мероприятия | T47: Сверено с первоисточником
A48: ACT046 | B48: 1 | C48: Образование | D48: 2.1.2 | E48: Осуществление взаимодействия с неправительственными организациями, общественными фондами, общественными объединениями по развитию инклюзивного образования | F48: ежегодно | G48: консультации, обсуждения, материалы оффлайн и онлайн семинаров, встреч | O48: Директор департамента по академическим вопросам Директор института педагогики и психологии | P48: Оценка невозможна: в Плане мероприятий отсутствует графа финансирования | Q48: Не указано в Плане мероприятий | R48: D21 | S48: План мероприятий, стр. 16; строка определяется по полному наименованию мероприятия | T48: Сверено с первоисточником
A49: ACT047 | B49: 1 | C49: Образование | D49: 2.2.1 | E49: Разработка и реализация программ | F49: ежегодно | G49: количество программ | I49: 1 | J49: 1 | K49: 2 | L49: 2 | M49: 3 | N49: 3 | O49: Директор департамента по академическим вопросам Директор департамента проектирования образовательных программ Руководитель Центра непрерывного образования | P49: Оценка невозможна: в Плане мероприятий отсутствует графа финансирования | Q49: Не указано в Плане мероприятий | R49: D21 | S49: План мероприятий, стр. 17; строка определяется по полному наименованию мероприятия | T49: Сверено с первоисточником
A50: ACT048 | B50: 1 | C50: Образование | D50: 2.2.1 | E50: Привлечение слушателей чел. | F50: постоянно | G50: список слушателей | I50: 10 | J50: 20 | K50: 25 | L50: 30 | M50: 35 | N50: 40 | O50: Директор департамента по академическим вопросам Директор департамента проектирования образовательных программ Руководитель Центра непрерывного образования | P50: Оценка невозможна: в Плане мероприятий отсутствует графа финансирования | Q50: Не указано в Плане мероприятий | R50: D21 | S50: План мероприятий, стр. 17; строка определяется по полному наименованию мероприятия | T50: Сверено с первоисточником
A51: ACT049 | B51: 1 | C51: Образование | D51: 2.2.2 | E51: Разработка и реализация программ | F51: ежегодно | G51: количество программ | H51: 1 | O51: Директор департамента по академическим вопросам Директор департамента проектирования образовательных программ Руководитель Центра непрерывного образования | P51: Оценка невозможна: в Плане мероприятий отсутствует графа финансирования | Q51: Не указано в Плане мероприятий | R51: D21 | S51: План мероприятий, стр. 18; строка определяется по полному наименованию мероприятия | T51: Сверено с первоисточником
A52: ACT050 | B52: 1 | C52: Образование | D52: 2.2.2 | E52: Привлечение слушателей чел. | F52: ежегодно | G52: 300 отчет | H52: 350 | I52: 350 | J52: 400 | K52: 400 | L52: 450 | M52: 500 | O52: Директор департамента по академическим вопросам Директор департамента проектирования образовательных программ Руководитель центра непрерывного образования | P52: Оценка невозможна: в Плане мероприятий отсутствует графа финансирования | Q52: Не указано в Плане мероприятий | R52: D21 | S52: План мероприятий, стр. 18; строка определяется по полному наименованию мероприятия | T52: Сверено с первоисточником
A53: ACT051 | B53: 1 | C53: Образование | D53: 2.2.3 | E53: Привлечение слушателей чел. | F53: постоянно | G53: 100 список слушателей | H53: 120 | I53: 130 | J53: 140 | K53: 150 | L53: 160 | M53: 170 | O53: Директор департамента проектирования образовательных программ Руководитель центра непрерывного образования | P53: Оценка невозможна: в Плане мероприятий отсутствует графа финансирования | Q53: Не указано в Плане мероприятий | R53: D21 | S53: План мероприятий, стр. 19; строка определяется по полному наименованию мероприятия | T53: Сверено с первоисточником
A54: ACT052 | B54: 1 | C54: Образование | D54: 2.2.3 | E54: Обновление контента | F54: ежегодно | G54: УМКД | I54: 1 | K54: 1 | L54: 1 | O54: Директор департамента проектирования образовательных программ Руководитель центра непрерывного образования | P54: Оценка невозможна: в Плане мероприятий отсутствует графа финансирования | Q54: Не указано в Плане мероприятий | R54: D21 | S54: План мероприятий, стр. 19; строка определяется по полному наименованию мероприятия | T54: Сверено с первоисточником
A55: ACT053 | B55: 1 | C55: Образование | D55: 2.2.3 | E55: Обновление образовательных программ в Реестре | F55: ежегодно | G55: ОП в реестре | I55: 1 | K55: 1 | L55: 1 | O55: Директор департамента проектирования образовательных программ Руководитель центра непрерывного образования | P55: Оценка невозможна: в Плане мероприятий отсутствует графа финансирования | Q55: Не указано в Плане мероприятий | R55: D21 | S55: План мероприятий, стр. 19; строка определяется по полному наименованию мероприятия | T55: Сверено с первоисточником
A56: ACT054 | B56: 1 | C56: Образование | D56: 2.3.1 | E56: Организация и проведение ярмарок вакансий и других мероприятий по содействию трудоустройства выпускников | F56: ежегодно | G56: кол-во мероприятий | H56: 1 | I56: 2 | J56: 2 | K56: 2 | L56: 2 | M56: 2 | N56: 2 | O56: Директор департамента по академическим вопросам | P56: Оценка невозможна: в Плане мероприятий отсутствует графа финансирования | Q56: Не указано в Плане мероприятий | R56: D21 | S56: План мероприятий, стр. 20; строка определяется по полному наименованию мероприятия | T56: Сверено с первоисточником
A57: ACT055 | B57: 1 | C57: Образование | D57: 2.3.1 | E57: Заключение договоров по прохождению практик с последующим трудоустройством выпускников | F57: ежегодно | G57: кол-во договоров | H57: 69 | I57: 75 | J57: 80 | K57: 85 | L57: 90 | M57: 95 100 | O57: Директор департамента по академическим вопросам | P57: Оценка невозможна: в Плане мероприятий отсутствует графа финансирования | Q57: Не указано в Плане мероприятий | R57: D21 | S57: План мероприятий, стр. 20; строка определяется по полному наименованию мероприятия | T57: Сверено с первоисточником
A58: ACT056 | B58: 1 | C58: Образование | D58: 2.3.1 | E58: Консультирование студентов выпускных курсов по вопросам составления резюме, прохождения интервью, сдачи оценки знаний педагогов, в том числе с использованием курсов платформы Coursera | F58: ежегодно | G58: отчет | O58: Директор департамента по академическим вопросам | P58: Оценка невозможна: в Плане мероприятий отсутствует графа финансирования | Q58: Не указано в Плане мероприятий | R58: D21 | S58: План мероприятий, стр. 20; строка определяется по полному наименованию мероприятия | T58: Сверено с первоисточником
A59: ACT057 | B59: 1 | C59: Образование | D59: 2.3.2 | E59: Подготовка списков респондентов, привлекаемых к участию в репутационных опросах работодателей | F59: ежегодно | G59: Не указано в строке источника | O59: Директор департамента по академическим вопросам | P59: Оценка невозможна: в Плане мероприятий отсутствует графа финансирования | Q59: Не указано в Плане мероприятий | R59: D21 | S59: План мероприятий, стр. 20; строка определяется по полному наименованию мероприятия | T59: Сверено с первоисточником
A60: ACT058 | B60: 1 | C60: Образование | D60: 2.3.3 | E60: Опросы среди студентов, выпускников и работодателей, чтобы получить их мнение о различных аспектах образования, включая качество преподавания, доступность программ и уровень поддержки | F60: ежегодно | G60: анкетирование | H60: 1 | I60: 1 | J60: 1 | K60: 1 | L60: 1 | M60: 1 | N60: 1 | O60: Офис институциональной эффективности | P60: Оценка невозможна: в Плане мероприятий отсутствует графа финансирования | Q60: Не указано в Плане мероприятий | R60: D21 | S60: План мероприятий, стр. 21; строка определяется по полному наименованию мероприятия | T60: Сверено с первоисточником
A61: ACT059 | B61: 1 | C61: Образование | D61: 2.3.3 | E61: Оценка и мониторинг образовательных программ | F61: ежегодно | G61: 100 отчет | H61: 100 | I61: 100 | J61: 100 | K61: 100 | L61: 100 | M61: 100 | O61: Руководители ОП | P61: Оценка невозможна: в Плане мероприятий отсутствует графа финансирования | Q61: Не указано в Плане мероприятий | R61: D21 | S61: План мероприятий, стр. 21; строка определяется по полному наименованию мероприятия | T61: Сверено с первоисточником
A62: ACT137 | B62: 1 | C62: Образование | D62: 1.3.5 | E62: Внедрение в образовательные программы дисциплины «Латинская графика казахского языка» | F62: Не указано в строке источника | G62: образовательные программы | I62: 66 | J62: 75 | K62: 85 | L62: 110 | M62: 120 | N62: 125 | O62: Директор департамента по академическим вопросам Руководитель Центра непрерывного образования | P62: Оценка невозможна: в Плане мероприятий отсутствует графа финансирования | Q62: Не указано в Плане мероприятий | R62: D21 | S62: План мероприятий, стр. 15; строка определяется по полному наименованию мероприятия | T62: Сверено с первоисточником
A63: ACT060 | B63: 2 | C63: Наука | D63: 1.1.1 | E63: Проведение обучающих семинаров представителями Scopus и Web of Science для ППС и научных работников вуза | F63: в течение года (с 2023 по 2029 годы) | G63: материалы оффлайн и онлайн семинаров (сертификаты при наличии, фото или видеозаписи, презентации) | O63: Директор департамента науки | P63: Оценка невозможна: в Плане мероприятий отсутствует графа финансирования | Q63: Не указано в Плане мероприятий | R63: D21 | S63: План мероприятий, стр. 21; строка определяется по полному наименованию мероприятия | T63: Сверено с первоисточником
A64: ACT061 | B64: 2 | C64: Наука | D64: 1.1.1 | E64: Проведение семинаров (вебинаров) для ППС и научных работников по использованию современных наукометрических и библиографических баз для изучения, написания научных статей, развития навыков академической письменности, поиска и подбора научных изданий | F64: в течение года (с 2023 по 2029 годы) | G64: материалы семинаров (вебинаров) – презентации, фото/видеозаписи | O64: Директор департамента науки | P64: Оценка невозможна: в Плане мероприятий отсутствует графа финансирования | Q64: Не указано в Плане мероприятий | R64: D21 | S64: План мероприятий, стр. 21; строка определяется по полному наименованию мероприятия | T64: Сверено с первоисточником
A65: ACT062 | B65: 2 | C65: Наука | D65: 1.2.1 | E65: Участие в конкурсах МНВО РК на грантовое финансирование научных проектов и программно- целевое финансирование науки | F65: в течение года (с 2023 по 2029 годы) | G65: кол-во проектов | H65: 20 | I65: 21 | J65: 22 | K65: 23 | L65: 24 | M65: 25 | N65: 26 | O65: Директор департамента науки | P65: Оценка невозможна: в Плане мероприятий отсутствует графа финансирования | Q65: Не указано в Плане мероприятий | R65: D21 | S65: План мероприятий, стр. 23; строка определяется по полному наименованию мероприятия | T65: Сверено с первоисточником
A66: ACT063 | B66: 2 | C66: Наука | D66: 1.2.1 | E66: Материальное/моральное стимулирование ППС и ученых за научные достижения, влияющие на положение университета в международных и республиканских рейтингах | F66: в течение года (с 2023 по 2029 годы) | G66: подтверждающие документы (приказы о награждении, сертификаты/дипломы) | H66: 1 | I66: 1 | J66: 1 | K66: 1 | L66: 1 | M66: 1 | N66: 1 | O66: Директор департамента науки | P66: Оценка невозможна: в Плане мероприятий отсутствует графа финансирования | Q66: Не указано в Плане мероприятий | R66: D21 | S66: План мероприятий, стр. 23; строка определяется по полному наименованию мероприятия | T66: Сверено с первоисточником
A67: ACT064 | B67: 2 | C67: Наука | D67: 1.2.2 | E67: Привлечение ППС и научных работников вуза в международные научные проекты представителями зарубежных организаций (университетов, фондов, институтов, центров и т.д.) | F67: в течение года (с 2023 по 2029 годы) | G67: 1 письма- приглашения, программы участия/работы в проекте | I67: 1 | J67: 1 | K67: 2 | L67: 2 | M67: 2 | N67: 2 | O67: Директор департамента науки | P67: Оценка невозможна: в Плане мероприятий отсутствует графа финансирования | Q67: Не указано в Плане мероприятий | R67: D21 | S67: План мероприятий, стр. 24; строка определяется по полному наименованию мероприятия | T67: Сверено с первоисточником
A68: ACT065 | B68: 2 | C68: Наука | D68: 1.2.3 | E68: Публикация результатов научно-исследовательских работ постдокторантов и профессоров-исследователей в высокорейтинговых журналах, входящих в базу данных Scopus и Web of Science | F68: в течение года (с 2023 по 2029 годы) | G68: оттиски статей, справки о принятии научных работ в журналы | H68: 20 | I68: 20 | J68: 22 | K68: 22 | L68: 23 | M68: 23 | N68: 24 | O68: Директор департамента науки | P68: Оценка невозможна: в Плане мероприятий отсутствует графа финансирования | Q68: Не указано в Плане мероприятий | R68: D21 | S68: План мероприятий, стр. 24; строка определяется по полному наименованию мероприятия | T68: Сверено с первоисточником
A69: ACT066 | B69: 2 | C69: Наука | D69: 1.2.3 | E69: Проведение научно- исследовательских работ в рамках участия во внутривузовских проектах, проектах МНВО РК | F69: в течение года (с 2023 по 2029 годы) | G69: договоры | H69: 25 | I69: 25 | J69: 25 | K69: 25 | L69: 25 | M69: 25 | N69: 25 | O69: Директор департамента науки | P69: Оценка невозможна: в Плане мероприятий отсутствует графа финансирования | Q69: Не указано в Плане мероприятий | R69: D21 | S69: План мероприятий, стр. 24; строка определяется по полному наименованию мероприятия | T69: Сверено с первоисточником
A70: ACT067 | B70: 2 | C70: Наука | D70: 1.2.4 | E70: Проведение внутриуниверситетских конкурсов для молодых ППС, научных работников | F70: в течение года (с 2023 по 2029 годы) | G70: договоры | H70: 15 | I70: 15 | J70: 15 | K70: 15 | L70: 15 | M70: 15 | N70: 15 | O70: Директор департамента науки | P70: Оценка невозможна: в Плане мероприятий отсутствует графа финансирования | Q70: Не указано в Плане мероприятий | R70: D21 | S70: План мероприятий, стр. 25; строка определяется по полному наименованию мероприятия | T70: Сверено с первоисточником
A71: ACT068 | B71: 2 | C71: Наука | D71: 1.2.4 | E71: Участие молодых ППС, чел. научных работников в конкурсах МНВО РК | F71: в течение года (с 2023 по 2029 годы) | G71: договоры | H71: 30 | I71: 32 | J71: 34 | K71: 36 | L71: 38 | M71: 40 | N71: 42 | O71: Директор департамента науки | P71: Оценка невозможна: в Плане мероприятий отсутствует графа финансирования | Q71: Не указано в Плане мероприятий | R71: D21 | S71: План мероприятий, стр. 25; строка определяется по полному наименованию мероприятия | T71: Сверено с первоисточником
A72: ACT069 | B72: 2 | C72: Наука | D72: 1.3.1 | E72: Участие ППС и научных чел. работников вуза в конкурсах на грантовое финансирование по научным и (или) научно- техническим проектам (МНВО РК) и конкурсах на программно-целевое финансирование по научным и (или) научно-техническим программам (МНВО РК) | F72: в течение года (с 2023 по 2029 годы) | G72: 220 проекты | H72: 225 | I72: 230 | J72: 235 | K72: 240 | L72: 245 | M72: 250 | O72: Директор департамента науки | P72: Оценка невозможна: в Плане мероприятий отсутствует графа финансирования | Q72: Не указано в Плане мероприятий | R72: D21 | S72: План мероприятий, стр. 25; строка определяется по полному наименованию мероприятия | T72: Сверено с первоисточником
A73: ACT070 | B73: 2 | C73: Наука | D73: 1.3.2 | E73: Мероприятия по разъяснению подачи заявок на ГФ и ПЦФ МНВО РК | F73: Не указано в строке источника | G73: Семинары | H73: 2 | I73: 2 | J73: 2 | K73: 2 | L73: 3 | M73: 3 | N73: 3 | O73: Директор департамента науки | P73: Оценка невозможна: в Плане мероприятий отсутствует графа финансирования | Q73: Не указано в Плане мероприятий | R73: D21 | S73: План мероприятий, стр. 26; строка определяется по полному наименованию мероприятия | T73: Сверено с первоисточником
A74: ACT071 | B74: 2 | C74: Наука | D74: 1.3.3 | E74: Привлечение ППС и научных работников вуза в международные научные проекты представителями зарубежных организаций (университетов, фондов, институтов, центров и т.д.) | F74: в течение года (с 2023 по 2029 годы) | G74: 1 письма- приглашения, программы участия/работы в проекте | I74: 1 | J74: 1 | K74: 1 | L74: 1 | M74: 2 | N74: 2 | O74: Директор департамента науки | P74: Оценка невозможна: в Плане мероприятий отсутствует графа финансирования | Q74: Не указано в Плане мероприятий | R74: D21 | S74: План мероприятий, стр. 26; строка определяется по полному наименованию мероприятия | T74: Сверено с первоисточником
A75: ACT072 | B75: 2 | C75: Наука | D75: 1.3.4 | E75: Мониторинг, осуществляемых межправительственных соглашений в сфере науки и образования | F75: в течение года (с 2023 по 2029 годы) | G75: рассылка | H75: 0 | I75: 0 | J75: 1 | K75: 1 | L75: 1 | M75: 2 | N75: 2 | O75: Директор департамента науки | P75: Оценка невозможна: в Плане мероприятий отсутствует графа финансирования | Q75: Не указано в Плане мероприятий | R75: D21 | S75: План мероприятий, стр. 26; строка определяется по полному наименованию мероприятия | T75: Сверено с первоисточником
A76: ACT073 | B76: 2 | C76: Наука | D76: 1.3.5 | E76: Проведение консультационных работ для ППС вуза по подаче заявки на получение патента | F76: в течение года (с 2023 по 2029 годы) | G76: заявки | H76: 1 | I76: 1 | J76: 1 | K76: 1 | L76: 1 | M76: 1 | N76: 1 | O76: Директор департамента науки | P76: Оценка невозможна: в Плане мероприятий отсутствует графа финансирования | Q76: Не указано в Плане мероприятий | R76: D21 | S76: План мероприятий, стр. 27; строка определяется по полному наименованию мероприятия | T76: Сверено с первоисточником
A77: ACT074 | B77: 2 | C77: Наука | D77: 1.3.6 | E77: Проведение консультационных и разъяснительных работ по участию ППС в конкурсах по коммерциализации результатов научной и научно-технической деятельности, объявленных Комитетом науки МНВО РК, МИО | F77: в течение года (с 2023 по 2029 годы) | G77: материалы для сопровождения ППС | H77: 1 | I77: 1 | J77: 1 | K77: 1 | L77: 1 | M77: 1 | N77: 1 | O77: Директор департамента науки | P77: Оценка невозможна: в Плане мероприятий отсутствует графа финансирования | Q77: Не указано в Плане мероприятий | R77: D21 | S77: План мероприятий, стр. 27; строка определяется по полному наименованию мероприятия | T77: Сверено с первоисточником
A78: ACT075 | B78: 2 | C78: Наука | D78: 1.3.7 | E78: Мониторинг результатов научных проектов вуза по высоко-востребованным направлениям с целью составления бизнес-плана, предлагаемых объектам частного со-финансирования | F78: в течение года (с 2023 по 2029 годы) | G78: акты результатов мониторинга, бизнес-планы | H78: 2 | I78: 2 | J78: 2 | K78: 2 | L78: 2 | M78: 2 | N78: 2 | O78: Директор департамента науки | P78: Оценка невозможна: в Плане мероприятий отсутствует графа финансирования | Q78: Не указано в Плане мероприятий | R78: D21 | S78: План мероприятий, стр. 27; строка определяется по полному наименованию мероприятия | T78: Сверено с первоисточником
A79: ACT076 | B79: 2 | C79: Наука | D79: 1.3.8 | E79: Организация и проведение подготовительных работ (сопровождение) для участия в стартап мероприятиях AUBIAK (Ассоциации бизнес- инкубаторов и акселерации) | F79: в течение года (с 2023 по 2029 годы) | G79: количество стартап проектов | H79: 0 | I79: 1 | J79: 1 | K79: 2 | L79: 2 | M79: 3 | N79: 3 | O79: Директор департамента науки | P79: Оценка невозможна: в Плане мероприятий отсутствует графа финансирования | Q79: Не указано в Плане мероприятий | R79: D21 | S79: План мероприятий, стр. 28; строка определяется по полному наименованию мероприятия | T79: Сверено с первоисточником
A80: ACT077 | B80: 2 | C80: Наука | D80: 1.3.8 | E80: Участие в мероприятиях АО «Фонд науки» по разработке и реализации стартап проектов | F80: в течение года (с 2023 по 2029 годы) | G80: подтверждающие документы об участии | H80: 0 | I80: 1 | J80: 1 | K80: 1 | L80: 1 | M80: 2 | N80: 2 | O80: Директор департамента науки | P80: Оценка невозможна: в Плане мероприятий отсутствует графа финансирования | Q80: Не указано в Плане мероприятий | R80: D21 | S80: План мероприятий, стр. 28; строка определяется по полному наименованию мероприятия | T80: Сверено с первоисточником
A81: ACT138 | B81: 2 | C81: Наука | D81: 1.1.2 | E81: Информационно- консультативное сопровождение ППС и сотрудников вуза по повышению индекса цитируемости авторов в научных изданиях | F81: в течение года (с 2023 по 2029 годы) | G81: Информационные материалы | H81: 1 | I81: 2 | J81: 2 | K81: 2 | L81: 2 | M81: 2 | N81: 2 | O81: Директор департамента науки | P81: Оценка невозможна: в Плане мероприятий отсутствует графа финансирования | Q81: Не указано в Плане мероприятий | R81: D21 | S81: План мероприятий, стр. 22; строка определяется по полному наименованию мероприятия | T81: Сверено с первоисточником
A82: ACT139 | B82: 2 | C82: Наука | D82: 1.1.3 | E82: Информационно- консультативное сопровождение ППС и сотрудников вуза по повышению индекса цитируемости публикаций в научных изданиях | F82: в течение года (с 2023 по 2029 годы) | G82: Информационные материалы | H82: 0 | I82: 2 | J82: 2 | K82: 2 | L82: 2 | M82: 2 | N82: 2 | O82: Директор департамента науки | P82: Оценка невозможна: в Плане мероприятий отсутствует графа финансирования | Q82: Не указано в Плане мероприятий | R82: D21 | S82: План мероприятий, стр. 22; строка определяется по полному наименованию мероприятия | T82: Сверено с первоисточником
A83: ACT140 | B83: 2 | C83: Наука | D83: 1.1.4 | E83: Привлечение зарубежных авторов, представителей редакционных коллегий журналов для повышения качества публикационных материалов ППС и сотрудников вуза | F83: в течение года (с 2023 по 2029 годы) | G83: Информационные материалы | H83: 0 | I83: 2 | J83: 2 | K83: 2 | L83: 2 | M83: 2 | N83: 2 | O83: Директор департамента науки | P83: Оценка невозможна: в Плане мероприятий отсутствует графа финансирования | Q83: Не указано в Плане мероприятий | R83: D21 | S83: План мероприятий, стр. 23; строка определяется по полному наименованию мероприятия | T83: Сверено с первоисточником
A84: ACT141 | B84: 2 | C84: Наука | D84: 1.1.5 | E84: Информационно- консультативное сопровождение ППС и сотрудников вуза по выполнению ЦУР и публикации результатов научно-исследовательской деятельности | F84: в течение года (с 2023 по 2029 годы) | G84: Информационные материалы | H84: 0 | I84: 2 | J84: 2 | K84: 2 | L84: 2 | M84: 2 | N84: 2 | O84: Директор департамента науки | P84: Оценка невозможна: в Плане мероприятий отсутствует графа финансирования | Q84: Не указано в Плане мероприятий | R84: D21 | S84: План мероприятий, стр. 23; строка определяется по полному наименованию мероприятия | T84: Сверено с первоисточником
A85: ACT142 | B85: 2 | C85: Наука | D85: 1.3.1 | E85: Мероприятия по увеличению дохода от коммерциализации | F85: в течение года (с 2023 по 2029 годы) | G85: семинар | H85: 1 | I85: 1 | J85: 2 | K85: 2 | L85: 2 | M85: 2 | N85: 2 | O85: Директор департамента науки | P85: Оценка невозможна: в Плане мероприятий отсутствует графа финансирования | Q85: Не указано в Плане мероприятий | R85: D21 | S85: План мероприятий, стр. 25; строка определяется по полному наименованию мероприятия | T85: Сверено с первоисточником
A86: ACT078 | B86: 3 | C86: Социальное развитие | D86: 1.1.1 | E86: Проведение разьяснительной кол. работы для обучающихся | F86: два раза в год (ежегодно) | G86: публикации в СМИ | H86: 24 | I86: 25 | J86: 26 | K86: 27 | L86: 28 | M86: 29 | N86: 30 | O86: Проректор по социальному развитию | P86: Оценка невозможна: в Плане мероприятий отсутствует графа финансирования | Q86: Не указано в Плане мероприятий | R86: D21 | S86: План мероприятий, стр. 28; строка определяется по полному наименованию мероприятия | T86: Сверено с первоисточником
A87: ACT079 | B87: 3 | C87: Социальное развитие | D87: 1.1.1 | E87: Проведение групповых кол. тренингов для обучающихся | F87: в течении учебного года (ежегодно) | G87: протокол тренингов | H87: 39 | I87: 42 | J87: 44 | K87: 46 | L87: 48 | M87: 50 | N87: 52 | O87: Проректор по социальному развитию | P87: Оценка невозможна: в Плане мероприятий отсутствует графа финансирования | Q87: Не указано в Плане мероприятий | R87: D21 | S87: План мероприятий, стр. 28; строка определяется по полному наименованию мероприятия | T87: Сверено с первоисточником
A88: ACT080 | B88: 3 | C88: Социальное развитие | D88: 1.1.1 | E88: Проведение индивидуальных кол. консультации для обучающихся с ООП | F88: в течении учебного года (ежегодно) | G88: 200 протоколы консультации | H88: 210 | I88: 220 | J88: 230 | K88: 240 | L88: 250 | M88: 260 | O88: Проректор по социальному развитию | P88: Оценка невозможна: в Плане мероприятий отсутствует графа финансирования | Q88: Не указано в Плане мероприятий | R88: D21 | S88: План мероприятий, стр. 28; строка определяется по полному наименованию мероприятия | T88: Сверено с первоисточником
A89: ACT081 | B89: 3 | C89: Социальное развитие | D89: 1.2.1 | E89: Набор волонтеров среди чел. студентов вуза | F89: в начале учебного года (ежегодно) | G89: публикации в 1856 СМИ | H89: 2000 | I89: 2100 | J89: 2150 | K89: 2200 | L89: 2250 | M89: 2300 | O89: Проректор по социальному развитию | P89: Оценка невозможна: в Плане мероприятий отсутствует графа финансирования | Q89: Не указано в Плане мероприятий | R89: D21 | S89: План мероприятий, стр. 29; строка определяется по полному наименованию мероприятия | T89: Сверено с первоисточником
A90: ACT082 | B90: 3 | C90: Социальное развитие | D90: 1.2.1 | E90: Проведение мастер-классов кол. среди обучающихся о важности вовлеченности в волонтерскую и общественную деятельность. | F90: в течении учебного года (ежегодно) | G90: публикации в СМИ | H90: 7 | I90: 8 | J90: 9 | K90: 10 | L90: 11 | M90: 12 | N90: 13 | O90: Проректор по социальному развитию | P90: Оценка невозможна: в Плане мероприятий отсутствует графа финансирования | Q90: Не указано в Плане мероприятий | R90: D21 | S90: План мероприятий, стр. 29; строка определяется по полному наименованию мероприятия | T90: Сверено с первоисточником
A91: ACT083 | B91: 3 | C91: Социальное развитие | D91: 1.2.1 | E91: Форум волонтеров вуза кол. | F91: ІІ квартал (ежегодно) | G91: публикации в СМИ | H91: 1 | I91: 1 | J91: 1 | K91: 1 | L91: 1 | M91: 1 | N91: 1 | O91: Проректор по социальному развитию | P91: Оценка невозможна: в Плане мероприятий отсутствует графа финансирования | Q91: Не указано в Плане мероприятий | R91: D21 | S91: План мероприятий, стр. 29; строка определяется по полному наименованию мероприятия | T91: Сверено с первоисточником
A92: ACT084 | B92: 3 | C92: Социальное развитие | D92: 1.2.3 | E92: Проведение международного кол. айтыс | F92: в течении учебного года (ежегодно) | G92: публикации в СМИ | H92: 1 | I92: 1 | J92: 1 | K92: 1 | L92: 1 | M92: 1 | N92: 1 | O92: Проректор по социальному развитию | P92: Оценка невозможна: в Плане мероприятий отсутствует графа финансирования | Q92: Не указано в Плане мероприятий | R92: D21 | S92: План мероприятий, стр. 30; строка определяется по полному наименованию мероприятия | T92: Сверено с первоисточником
A93: ACT085 | B93: 3 | C93: Социальное развитие | D93: 1.2.3 | E93: Проведение республиканского кол. фестиваля студенческих театров | F93: в течении учебного года (ежегодно) | G93: публикации в СМИ | H93: 1 | I93: 1 | J93: 1 | K93: 1 | L93: 1 | M93: 1 | N93: 1 | O93: Проректор по социальному развитию | P93: Оценка невозможна: в Плане мероприятий отсутствует графа финансирования | Q93: Не указано в Плане мероприятий | R93: D21 | S93: План мероприятий, стр. 30; строка определяется по полному наименованию мероприятия | T93: Сверено с первоисточником
A94: ACT086 | B94: 3 | C94: Социальное развитие | D94: 1.2.3 | E94: Проведение студенческой недели | F94: в течении учебного года (ежегодно) | G94: публикации в СМИ | H94: 2 | I94: 2 | J94: 2 | K94: 2 | L94: 2 | M94: 2 | N94: 2 | O94: Проректор по социальному развитию | P94: Оценка невозможна: в Плане мероприятий отсутствует графа финансирования | Q94: Не указано в Плане мероприятий | R94: D21 | S94: План мероприятий, стр. 30; строка определяется по полному наименованию мероприятия | T94: Сверено с первоисточником
A95: ACT087 | B95: 3 | C95: Социальное развитие | D95: 1.2.3 | E95: Спортивные соревнования кол. среди студентов | F95: в течении учебного года (ежегодно) | G95: публикации в СМИ | H95: 60 | I95: 62 | J95: 62 | K95: 64 | L95: 64 | M95: 66 | N95: 66 | O95: Проректор по социальному развитию | P95: Оценка невозможна: в Плане мероприятий отсутствует графа финансирования | Q95: Не указано в Плане мероприятий | R95: D21 | S95: План мероприятий, стр. 31; строка определяется по полному наименованию мероприятия | T95: Сверено с первоисточником
A96: ACT088 | B96: 3 | C96: Социальное развитие | D96: 1.2.3 | E96: Городской конкурс «Dance кол. Fest» | F96: ІІ квартал (ежегодно) | G96: публикации в СМИ | H96: 1 | I96: 1 | J96: 1 | K96: 1 | L96: 1 | M96: 1 | N96: 1 | O96: Проректор по социальному развитию | P96: Оценка невозможна: в Плане мероприятий отсутствует графа финансирования | Q96: Не указано в Плане мероприятий | R96: D21 | S96: План мероприятий, стр. 31; строка определяется по полному наименованию мероприятия | T96: Сверено с первоисточником
A97: ACT089 | B97: 3 | C97: Социальное развитие | D97: 1.2.3 | E97: Игры городской лигы «Абай» кол. по Жайдарман | F97: в течении учебного года (ежегодно) | G97: публикации в СМИ | H97: 6 | I97: 6 | J97: 6 | K97: 6 | L97: 6 | M97: 6 | N97: 6 | O97: Проректор по социальному развитию | P97: Оценка невозможна: в Плане мероприятий отсутствует графа финансирования | Q97: Не указано в Плане мероприятий | R97: D21 | S97: План мероприятий, стр. 31; строка определяется по полному наименованию мероприятия | T97: Сверено с первоисточником
A98: ACT090 | B98: 3 | C98: Социальное развитие | D98: 1.2.3 | E98: Проведение международного кол. айтыс | F98: в течении учебного года (ежегодно) | G98: публикации в СМИ | H98: 1 | I98: 1 | J98: 1 | K98: 1 | L98: 1 | M98: 1 | N98: 1 | O98: Проректор по социальному развитию | P98: Оценка невозможна: в Плане мероприятий отсутствует графа финансирования | Q98: Не указано в Плане мероприятий | R98: D21 | S98: План мероприятий, стр. 31; строка определяется по полному наименованию мероприятия | T98: Сверено с первоисточником
A99: ACT091 | B99: 3 | C99: Социальное развитие | D99: 1.2.4 | E99: Проведение дебатных кол. турниров (совместно с вузами) | F99: ежегодно | G99: публикации в СМИ | H99: 3 | I99: 3 | J99: 3 | K99: 3 | L99: 3 | M99: 3 | N99: 3 | O99: Проректор по социальному развитию | P99: Оценка невозможна: в Плане мероприятий отсутствует графа финансирования | Q99: Не указано в Плане мероприятий | R99: D21 | S99: План мероприятий, стр. 31; строка определяется по полному наименованию мероприятия | T99: Сверено с первоисточником
A100: ACT092 | B100: 3 | C100: Социальное развитие | D100: 1.2.4 | E100: Проведение Әз-Наурыз чел (совместно с вузами) | F100: ежегодно | G100: публикации в 3000 СМИ | H100: 3100 | I100: 3150 | J100: 3200 | K100: 3250 | L100: 3300 | M100: 3350 | O100: Проректор по социальному развитию | P100: Оценка невозможна: в Плане мероприятий отсутствует графа финансирования | Q100: Не указано в Плане мероприятий | R100: D21 | S100: План мероприятий, стр. 31; строка определяется по полному наименованию мероприятия | T100: Сверено с первоисточником
...

Sheet 04_Анализ_соответствия
A1: Сквозной анализ: требования госорганов — Программа развития — План мероприятий — факт за 2025 год
A2: Категория записи | B2: ID анализа | C2: Направление | D2: ID требования | E2: Требование государственного органа / внешний ориентир | F2: Применимость к Abai | G2: ID KPI Программы | H2: KPI Программы развития | I2: Единица KPI | J2: Требование 2023 | K2: Требование 2024 | L2: Требование 2025 | M2: Требование 2026 | N2: Требование 2027 | O2: Требование 2028 | P2: Требование 2029 | Q2: Программа 2023 | R2: Программа 2024 | S2: Программа 2025 | T2: Программа 2026 | U2: Программа 2027 | V2: Программа 2028 | W2: Программа 2029 | X2: ID мероприятий | Y2: Мероприятия Плана | Z2: Результат Плана 2023 | AA2: Результат Плана 2024 | AB2: Результат Плана 2025 | AC2: Результат Плана 2026 | AD2: Результат Плана 2027 | AE2: Результат Плана 2028 | AF2: Результат Плана 2029 | AG2: Ответственный по Плану | AH2: Финансирование | AI2: Факт 2025 | AJ2: Источник факта | AK2: Качество сопоставления факта | AL2: Отклонение 2025 | AM2: Отношение факта к плану Программы 2025 | AN2: Сопоставление требования госоргана и факта 2025 | AO2: Факт выполнения мероприятия за 2025 год | AP2: Выполнение мероприятия за 2025 год | AQ2: Положение факта 2025 относительно целей 2026–2029 | AR2: Актуальность целей 2026–2029 | AS2: Соответствие: требование — Программа | AT2: Соответствие: Программа — План | AU2: Исполнение за 2025 год | AV2: Выявленный пробел | AW2: Управленческое действие | AX2: Источники ID | AY2: Итоговый статус | AZ2: Открыть связанные мероприятия | BA2: Краткое пояснение | BB2: Подтверждённый факт | BC2: Что требуется запросить | BD2: Открыть пояснение
A3: Требование государственного органа | B3: AN-K002 | C3: Образование | D3: K002 | E3: Количество казахстанских вузов в топ-700 рейтинга QS World University Rankings | F3: Требуется декомпозиция | G3: PRG016 | H3: PRG016: 1.2.7. Позиция вуза в рейтинге QS-WUR, в том числе ТОП-700 | I3: место | K3: 6 | L3: 7 | M3: 8 | N3: 9 | O3: 10 | P3: 11 | Q3: PRG016: 690 место | R3: PRG016: 680 место | S3: PRG016: 680 место | T3: PRG016: 670 место | U3: PRG016: 660 место | V3: PRG016: 650 место | W3: PRG016: 640 место | X3: ACT034 | Y3: ACT034: Сбор, обработка информации по всем структурным подразделениям университета и ввод данных на онлайн портале в соответствии с методологией QS | AA3: ACT034: 1 | AB3: ACT034: 1 | AC3: ACT034: 1 | AD3: ACT034: 1 | AE3: ACT034: 1 | AF3: ACT034: 1 | AG3: Директор департамента стратегии | AH3: Оценка невозможна: в Плане мероприятий отсутствует графа финансирования | AK3: PRG016: Факт с формулой и единицей KPI в отчётах не найден | AM3: PRG016: не рассчитывается — факт 2025 отсутствует | AN3: Прямое сравнение невозможно: требуется утверждённое индивидуальное значение Abai University | AO3: В текущем реестре отсутствует сопоставленный факт выполнения мероприятия за 2025 год | AP3: Оценка невозможна: факт мероприятия за 2025 год не подтверждён в текущем реестре | AQ3: PRG016: не оценивается — факт 2025 отсутствует | AR3: Оценка невозможна: факт за 2025 год отсутствует | AS3: Частичное соответствие — показатели связаны, но не тождественны | AT3: Связь установлена по коду KPI; количественная сопоставимость KPI и результата мероприятия отдельно не подтверждена | AU3: PRG016: Невозможно оценить — сопоставимый факт отсутствует | AV3: Сопоставимый факт исполнения за 2025 год не найден либо не подтверждён | AW3: Оценить достаточность связанных мероприятий для выполнения требования; источник и объём финансирования запросить отдельно | AX3: D04 D20 D21 | AY3: Цепочка подтверждена до Плана; факт 2025 не подтверждён | AZ3: Открыть: 1 | BA3: Показывает позиция вуза в рейтинге QS-WUR, в том числе ТОП-700. Частичное соответствие — показатели связаны, но не тождественны | BB3: План 2025: 680; факт 2025: не найден; оценка: Невозможно оценить — сопоставимый факт отсутствует | BC3: Запросить документ, утверждающий вклад или индивидуальное значение Abai University; Запросить подтверждённый факт за 2025 год, расчёт и первичный источник; Запросить источник и объём финансирования связанных мероприятий | BD3: Открыть PRG016
A4: Требование государственного органа | B4: AN-K004 | C4: Образование | D4: K004 | E4: Количество казахстанских вузов, вошедших в рейтинг QS WUR | F4: Требуется декомпозиция | G4: PRG016 | H4: PRG016: 1.2.7. Позиция вуза в рейтинге QS-WUR, в том числе ТОП-700 | I4: место | K4: 21 | L4: 22 | M4: 23 | N4: 24 | O4: 25 | P4: 26 | Q4: PRG016: 690 место | R4: PRG016: 680 место | S4: PRG016: 680 место | T4: PRG016: 670 место | U4: PRG016: 660 место | V4: PRG016: 650 место | W4: PRG016: 640 место | X4: ACT034 | Y4: ACT034: Сбор, обработка информации по всем структурным подразделениям университета и ввод данных на онлайн портале в соответствии с методологией QS | AA4: ACT034: 1 | AB4: ACT034: 1 | AC4: ACT034: 1 | AD4: ACT034: 1 | AE4: ACT034: 1 | AF4: ACT034: 1 | AG4: Директор департамента стратегии | AH4: Оценка невозможна: в Плане мероприятий отсутствует графа финансирования | AK4: PRG016: Факт с формулой и единицей KPI в отчётах не найден | AM4: PRG016: не рассчитывается — факт 2025 отсутствует | AN4: Прямое сравнение невозможно: требуется утверждённое индивидуальное значение Abai University | AO4: В текущем реестре отсутствует сопоставленный факт выполнения мероприятия за 2025 год | AP4: Оценка невозможна: факт мероприятия за 2025 год не подтверждён в текущем реестре | AQ4: PRG016: не оценивается — факт 2025 отсутствует | AR4: Оценка невозможна: факт за 2025 год отсутствует | AS4: Частичное соответствие — показатели связаны, но не тождественны | AT4: Связь установлена по коду KPI; количественная сопоставимость KPI и результата мероприятия отдельно не подтверждена | AU4: PRG016: Невозможно оценить — сопоставимый факт отсутствует | AV4: Сопоставимый факт исполнения за 2025 год не найден либо не подтверждён | AW4: Оценить достаточность связанных мероприятий для выполнения требования; источник и объём финансирования запросить отдельно | AX4: D04 D20 D21 | AY4: Цепочка подтверждена до Плана; факт 2025 не подтверждён | AZ4: Открыть: 1
A5: Требование государственного органа | B5: AN-K005 | C5: Образование | D5: K005 | E5: Доля обновленных образовательных программ вузов с учетом профессиональных стандартов | F5: Требуется декомпозиция | K5: 75.8 | L5: 77 | M5: 80 | N5: 85 | O5: 90 | P5: 95 | AH5: Оценка невозможна: в Плане мероприятий отсутствует графа финансирования | AK5: Сопоставимый факт отсутствует | AM5: Не рассчитывается: связанный KPI Программы не установлен | AN5: Прямое сравнение невозможно: требуется утверждённое индивидуальное значение Abai University | AO5: В текущем реестре отсутствует сопоставленный факт выполнения мероприятия за 2025 год | AP5: Оценка невозможна: факт мероприятия за 2025 год не подтверждён в текущем реестре | AQ5: Не оценивается: связанный KPI Программы не установлен | AR5: Оценка невозможна: связанный KPI Программы не установлен | AS5: Связь с KPI Программы не установлена | AT5: Связь с мероприятием Плана не установлена | AU5: Оценка невозможна: сопоставимый факт отсутствует | AV5: В представленных документах не установлена связь требования с KPI Программы | AW5: Определить, требуется ли декомпозиция требования на KPI университета; при необходимости утвердить показатель, владельца и целевое значение | AX5: D04 | AY5: Связь с Программой не установлена | BA5: Национальный или отраслевой показатель. Вклад Abai University и индивидуальное значение в представленных документах не подтверждены. | BB5: Связь с KPI Программы в представленных документах не подтверждена | BC5: Определить вклад университета и запросить документ, утверждающий индивидуальное значение, владельца и методику. | BD5: Открыть K005
A6: Требование государственного органа | B6: AN-K006 | C6: Образование | D6: K006 | E6: Доля организаций высшего и послевузовского образования, создавших условия для инклюзивного образования | F6: Требуется декомпозиция | G6: PRG023 | H6: PRG023: 2.1.1. Уровень созданных условий для инклюзивного образования в университете | I6: % | K6: 70 | L6: 80 | M6: 100 | N6: 100 | O6: 100 | P6: 100 | Q6: PRG023: 40 % | R6: PRG023: 42 % | S6: PRG023: 43 % | T6: PRG023: 44 % | U6: PRG023: 45 % | V6: PRG023: 45 % | W6: PRG023: 45 % | X6: ACT044; ACT045 | Y6: ACT044: Внедрение программ смешанного и онлайн обучения для студентов с ACT045: Открытие массовых онлайн курсов для студентов с особыми образовательными потребностями | AA6: ACT044: 1 ACT045: 4 | AB6: ACT044: 2 ACT045: 7 | AC6: ACT044: 3 ACT045: 9 | AD6: ACT044: 4 ACT045: 11 | AE6: ACT044: 5 ACT045: 15 | AF6: ACT044: 6 ACT045: 17 | AG6: Директор департамента по академическим вопросам Директор департамента по академическим вопросам Директор департамента проектирования образовательных программ | AH6: Оценка невозможна: в Плане мероприятий отсутствует графа финансирования | AK6: PRG023: Факт с формулой и единицей KPI в отчётах не найден | AM6: PRG023: не рассчитывается — факт 2025 отсутствует | AN6: Прямое сравнение невозможно: требуется утверждённое индивидуальное значение Abai University | AO6: В текущем реестре отсутствует сопоставленный факт выполнения мероприятия за 2025 год | AP6: Оценка невозможна: факт мероприятия за 2025 год не подтверждён в текущем реестре | AQ6: PRG023: не оценивается — факт 2025 отсутствует | AR6: Оценка невозможна: факт за 2025 год отсутствует | AS6: Частичное соответствие — показатели связаны, но не тождественны | AT6: Связь установлена по коду KPI; количественная сопоставимость KPI и результата мероприятия отдельно не подтверждена | AU6: PRG023: Невозможно оценить — сопоставимый факт отсутствует | AV6: Сопоставимый факт исполнения за 2025 год не найден либо не подтверждён | AW6: Оценить достаточность связанных мероприятий для выполнения требования; источник и объём финансирования запросить отдельно | AX6: D04 D20 D21 | AY6: Цепочка подтверждена до Плана; факт 2025 не подтверждён | AZ6: Открыть: 2 | BA6: Показывает установленный Программой уровень созданных условий для инклюзивного образования в университете. Частичное соответствие — показатели связаны, но не тождественны; Нормативное требование — связанный KPI не заменяет контроль соблюдения | BB6: План 2025: 43; факт 2025: не найден; оценка: Невозможно оценить — сопоставимый факт отсутствует | BC6: Запросить документ, утверждающий вклад или индивидуальное значение Abai University; Запросить подтверждённый факт за 2025 год, расчёт и первичный источник; Запросить источник и объём финансирования связанных мероприятий | BD6: Открыть PRG023
